Workbook

Sheet Cover
A1: Capital Structure & Valuation — Indian FMCG (FY2022–FY2026)
A2: 8 firms · Screener.in standalone statements · built by the analysis/scripts pipeline — regenerate with export_to_excel.py
B4: The question | C4: Does capital structure explain profitability and valuation differences across Indian FMCG firms — and where does the optimal leverage band lie?
B6: Sheets
B7: Raw Data | C7: single source of truth — statement inputs (blue) + derived formula columns
B8: Market Data | C8: July-2026 market snapshot per firm (inputs to WACC / DCF / Comps)
B9: Ratio Analysis | C9: 10 ratios per firm-year, live formulas + heatmaps + ROE trend chart
B10: DuPont Analysis | C10: 5-step ROE decomposition, identity check, ln-contribution chart
B11: Capital Structure | C11: leverage bands via IF formulas + D/E and coverage charts
B12: Leverage Threshold | C12: where ROE peaks across the D/E spectrum (python bins + live scatter)
B13: WACC | C13: CAPM assumptions (yellow) → per-firm WACC + book-weight evolution
B14: Correlation Matrix | C14: ratio correlation heatmap + multicollinearity shortlist
B15: Regression Analysis | C15: OLS: ROE ~ D/E + NetMargin + log(assets), interpretation + fit plot
B16: DCF - FCFF | C16: 5-year FCFF DCF per firm → EV → equity → value per share vs market
B17: DCF - FCFE | C17: equity-direct DCF at cost of equity; gap vs FCFF = leverage effect
B18: Comps | C18: EV/EBITDA vs sector median — premium / discount flags
B19: Sensitivity Analysis | C19: value-per-share grids: WACC ±200bp × terminal g 1–5% per firm
B21: Colour legend
B22: blue font | C22: hardcoded input — traceable to data/cleaned/ CSVs
B23: black font | C23: live Excel formula — recalculates when Raw Data changes
B24: yellow fill | C24: assumption meant to be challenged (Rf, ERP, beta, growth…)
B25: grey fill | C25: computed in python (script credited beside the block)
B27: Sources
B28: HUL | C28: https://www.screener.in/company/HINDUNILVR/
B29: ITC | C29: https://www.screener.in/company/ITC/
B30: Dabur | C30: https://www.screener.in/company/DABUR/
B31: Marico | C31: https://www.screener.in/company/MARICO/
B32: Colgate | C32: https://www.screener.in/company/COLPAL/
B33: Nestle | C33: https://www.screener.in/company/NESTLEIND/
B34: Godrej | C34: https://www.screener.in/company/GODREJCP/
B35: Emami | C35: https://www.screener.in/company/EMAMILTD/
B37: Statements: standalone, FY2015–FY2026 scraped 2026-07 · schedules (cash, payables, capex detail) via the Screener schedules API · market snapshot as of July 2026

Sheet Raw Data
A1: Company | B1: Year | C1: Revenue | D1: OperatingProfit | E1: OtherIncome | F1: InterestExpense | G1: Depreciation | H1: PBT | I1: TaxPct | J1: NetProfit | K1: ShareCapital | L1: Reserves | M1: TotalDebt | N1: TotalAssets | O1: Cash | P1: Inventories | Q1: TradeReceivables | R1: OtherLiabilities | S1: OperatingCashFlow | T1: FreeCashFlow | U1: PrevTotalDebt | V1: TaxRate | W1: EBIT | X1: EBITDA | Y1: TotalEquity | Z1: CurrentAssets | AA1: CurrentLiabilities | AB1: Capex | AC1: NetBorrowing | AD1: SharesOutstanding
A2: HUL | B2: FY2022 | C2: 51193 | D2: 12503 | E2: 359 | F2: 98 | G2: 1025 | H2: 11739 | I2: 25 | J2: 8818 | K2: 235 | L2: 48525 | M2: 971 | N2: 69737 | O2: 3618 | P2: 3890 | Q2: 1932 | R2: 20006 | S2: 8964 | T2: 8220 | U2: 943 | V2: =I2/100 | W2: =H2+F2 | X2: =W2+G2 | Y2: =K2+L2 | Z2: =O2+P2+Q2 | AA2: =R2 | AB2: =S2-T2 | AC2: =M2-U2 | AD2: =K2/INDEX('Market Data'!$D$2:$D$9,MATCH(A2,'Market Data'!$A$2:$A$9,0))
A3: HUL | B3: FY2023 | C3: 59144 | D3: 13632 | E3: 578 | F3: 101 | G3: 1030 | H3: 13079 | I3: 24 | J3: 9962 | K3: 235 | L3: 49986 | M3: 1039 | N3: 71825 | O3: 4422 | P3: 4031 | Q3: 2735 | R3: 20565 | S3: 9626 | T3: 8765 | U3: 971 | V3: =I3/100 | W3: =H3+F3 | X3: =W3+G3 | Y3: =K3+L3 | Z3: =O3+P3+Q3 | AA3: =R3 | AB3: =S3-T3 | AC3: =M3-U3 | AD3: =K3/INDEX('Market Data'!$D$2:$D$9,MATCH(A3,'Market Data'!$A$2:$A$9,0))
A4: HUL | B4: FY2024 | C4: 60469 | D4: 14190 | E4: 884 | F4: 302 | G4: 1097 | H4: 13675 | I4: 26 | J4: 10114 | K4: 235 | L4: 50738 | M4: 1374 | N4: 77076 | O4: 7216 | P4: 3812 | Q4: 2690 | R4: 24729 | S4: 14884 | T4: 13586 | U4: 1039 | V4: =I4/100 | W4: =H4+F4 | X4: =W4+G4 | Y4: =K4+L4 | Z4: =O4+P4+Q4 | AA4: =R4 | AB4: =S4-T4 | AC4: =M4-U4 | AD4: =K4/INDEX('Market Data'!$D$2:$D$9,MATCH(A4,'Market Data'!$A$2:$A$9,0))
A5: HUL | B5: FY2025 | C5: 59676 | D5: 14144 | E5: 1632 | F5: 350 | G5: 1122 | H5: 14304 | I5: 26 | J5: 10644 | K5: 235 | L5: 48918 | M5: 1537 | N5: 78313 | O5: 7293 | P5: 4161 | Q5: 3450 | R5: 27623 | S5: 11606 | T5: 10470 | U5: 1374 | V5: =I5/100 | W5: =H5+F5 | X5: =W5+G5 | Y5: =K5+L5 | Z5: =O5+P5+Q5 | AA5: =R5 | AB5: =S5-T5 | AC5: =M5-U5 | AD5: =K5/INDEX('Market Data'!$D$2:$D$9,MATCH(A5,'Market Data'!$A$2:$A$9,0))
A6: HUL | B6: FY2026 | C6: 61975 | D6: 14464 | E6: 5572 | F6: 363 | G6: 1186 | H6: 18487 | I6: 17 | J6: 15427 | K6: 235 | L6: 48988 | M6: 1325 | N6: 77982 | O6: 2830 | P6: 4383 | Q6: 3037 | R6: 27434 | S6: 10496 | T6: 9251 | U6: 1537 | V6: =I6/100 | W6: =H6+F6 | X6: =W6+G6 | Y6: =K6+L6 | Z6: =O6+P6+Q6 | AA6: =R6 | AB6: =S6-T6 | AC6: =M6-U6 | AD6: =K6/INDEX('Market Data'!$D$2:$D$9,MATCH(A6,'Market Data'!$A$2:$A$9,0))
A7: ITC | B7: FY2022 | C7: 56341 | D7: 18893 | E7: 2649 | F7: 61 | G7: 1652 | H7: 19830 | I7: 24 | J7: 15058 | K7: 1232 | L7: 60167 | M7: 311 | N7: 75092 | O7: 3878 | P7: 9998 | Q7: 1952 | R7: 13382 | S7: 14808 | T7: 13133 | U7: 329 | V7: =I7/100 | W7: =H7+F7 | X7: =W7+G7 | Y7: =K7+L7 | Z7: =O7+P7+Q7 | AA7: =R7 | AB7: =S7-T7 | AC7: =M7-U7 | AD7: =K7/INDEX('Market Data'!$D$2:$D$9,MATCH(A7,'Market Data'!$A$2:$A$9,0))
A8: ITC | B8: FY2023 | C8: 66043 | D8: 23981 | E8: 2506 | F8: 74 | G8: 1663 | H8: 24750 | I8: 24 | J8: 18753 | K8: 1243 | L8: 66351 | M8: 325 | N8: 82262 | O8: 3831 | P8: 10594 | Q8: 2321 | R8: 14343 | S8: 17912 | T8: 16102 | U8: 311 | V8: =I8/100 | W8: =H8+F8 | X8: =W8+G8 | Y8: =K8+L8 | Z8: =O8+P8+Q8 | AA8: =R8 | AB8: =S8-T8 | AC8: =M8-U8 | AD8: =K8/INDEX('Market Data'!$D$2:$D$9,MATCH(A8,'Market Data'!$A$2:$A$9,0))
A9: ITC | B9: FY2024 | C9: 62628 | D9: 23435 | E9: 4100 | F9: 34 | G9: 1357 | H9: 26144 | I9: 22 | J9: 20422 | K9: 1248 | L9: 70985 | M9: 312 | N9: 87328 | O9: 6218 | P9: 12632 | Q9: 3311 | R9: 14782 | S9: 16118 | T9: 13572 | U9: 325 | V9: =I9/100 | W9: =H9+F9 | X9: =W9+G9 | Y9: =K9+L9 | Z9: =O9+P9+Q9 | AA9: =R9 | AB9: =S9-T9 | AC9: =M9-U9 | AD9: =K9/INDEX('Market Data'!$D$2:$D$9,MATCH(A9,'Market Data'!$A$2:$A$9,0))
A10: ITC | B10: FY2025 | C10: 69326 | D10: 23906 | E10: 19206 | F10: 36 | G10: 1442 | H10: 41634 | I10: 15 | J10: 35197 | K10: 1251 | L10: 66642 | M10: 157 | N10: 84005 | O10: 3185 | P10: 15061 | Q10: 3911 | R10: 15954 | S10: 16754 | T10: 15123 | U10: 312 | V10: =I10/100 | W10: =H10+F10 | X10: =W10+G10 | Y10: =K10+L10 | Z10: =O10+P10+Q10 | AA10: =R10 | AB10: =S10-T10 | AC10: =M10-U10 | AD10: =K10/INDEX('Market Data'!$D$2:$D$9,MATCH(A10,'Market Data'!$A$2:$A$9,0))
A11: ITC | B11: FY2026 | C11: 71984 | D11: 25196 | E11: 3115 | F11: 70 | G11: 1474 | H11: 26768 | I11: 24 | J11: 20286 | K11: 1253 | L11: 68676 | M11: 2162 | N11: 88916 | O11: 2136 | P11: 17932 | Q11: 2926 | R11: 16825 | S11: 17095 | T11: 15075 | U11: 157 | V11: =I11/100 | W11: =H11+F11 | X11: =W11+G11 | Y11: =K11+L11 | Z11: =O11+P11+Q11 | AA11: =R11 | AB11: =S11-T11 | AC11: =M11-U11 | AD11: =K11/INDEX('Market Data'!$D$2:$D$9,MATCH(A11,'Market Data'!$A$2:$A$9,0))
A12: Dabur | B12: FY2022 | C12: 8180 | D12: 1734 | E12: 341 | F12: 19 | G12: 160 | H12: 1896 | I12: 24 | J12: 1433 | K12: 177 | L12: 5687 | M12: 560 | N12: 8592 | O12: 136 | P12: 1238 | Q12: 455 | R12: 2168 | S12: 1320 | T12: 1025 | U12: 180 | V12: =I12/100 | W12: =H12+F12 | X12: =W12+G12 | Y12: =K12+L12 | Z12: =O12+P12+Q12 | AA12: =R12 | AB12: =S12-T12 | AC12: =M12-U12 | AD12: =K12/INDEX('Market Data'!$D$2:$D$9,MATCH(A12,'Market Data'!$A$2:$A$9,0))
A13: Dabur | B13: FY2023 | C13: 8684 | D13: 1701 | E13: 363 | F13: 46 | G13: 188 | H13: 1829 | I13: 25 | J13: 1373 | K13: 177 | L13: 6110 | M13: 615 | N13: 9352 | O13: 33 | P13: 1224 | Q13: 561 | R13: 2450 | S13: 1562 | T13: 1173 | U13: 560 | V13: =I13/100 | W13: =H13+F13 | X13: =W13+G13 | Y13: =K13+L13 | Z13: =O13+P13+Q13 | AA13: =R13 | AB13: =S13-T13 | AC13: =M13-U13 | AD13: =K13/INDEX('Market Data'!$D$2:$D$9,MATCH(A13,'Market Data'!$A$2:$A$9,0))
... A41: Emami | B41: FY2026 | C41: 3048 | D41: 950 | E41: 108 | F41: 2 | G41: 156 | H41: 901 | I41: 7 | J41: 842 | K41: 44 | L41: 3112 | M41: 92 | N41: 3726 | O41: 317 | P41: 334 | Q41: 190 | R41: 478 | S41: 794 | T41: 760 | U41: 14 | V41: =I41/100 | W41: =H41+F41 | X41: =W41+G41 | Y41: =K41+L41 | Z41: =O41+P41+Q41 | AA41: =R41 | AB41: =S41-T41 | AC41: =M41-U41 | AD41: =K41/INDEX('Market Data'!$D$2:$D$9,MATCH(A41,'Market Data'!$A$2:$A$9,0))
A43: All figures ₹ Cr (SharesOutstanding in Cr shares; TaxPct in %). Blue = input from data/cleaned/. Black = derived formula. PrevTotalDebt = prior-FY borrowings (for ΔDebt).

Sheet Market Data
A1: Company | B1: MarketCap | C1: CurrentPrice | D1: FaceValue | E1: StockPE | F1: BookValue | G1: DividendYieldPct | H1: ScreenerROCEPct | I1: ScreenerROEPct
A2: HUL | B2: 512511 | C2: 2182 | D2: 1 | E2: 33.6 | F2: 210 | G2: 1.88 | H2: 28.1 | I2: 31
A3: ITC | B3: 363667 | C3: 290 | D3: 1 | E3: 17.8 | F3: 55.8 | G3: 4.99 | H3: 38.6 | I3: 29.6
A4: Dabur | B4: 78915 | C4: 445 | D4: 1 | E4: 52.5 | F4: 42.4 | G4: 1.85 | H4: 25.1 | I4: 20.1
A5: Marico | B5: 110506 | C5: 851 | D5: 1 | E5: 56.9 | F5: 44.7 | G5: 0.47 | H5: 41.5 | I5: 36.7
A6: Colgate | B6: 56334 | C6: 2072 | D6: 1 | E6: 41.9 | F6: 58.2 | G6: 2.46 | H6: 108 | I6: 82.7
A7: Nestle | B7: 279940 | C7: 1454 | D7: 1 | E7: 81.2 | F7: 27.5 | G7: 0.83 | H7: 84.1 | I7: 73.2
A8: Godrej | B8: 106775 | C8: 1044 | D8: 1 | E8: 68.6 | F8: 76.7 | G8: 1.92 | H8: 20.9 | I8: 19.2
A9: Emami | B9: 18120 | C9: 415 | D9: 1 | E9: 21.3 | F9: 72.3 | G9: 2.41 | H9: 29.8 | I9: 28.3
A11: Screener.in snapshot, July 2026 (data/cleaned/market_snapshot.csv). MarketCap ₹ Cr; prices/face/book ₹ per share; yields & returns in %.

Sheet Ratio Analysis
A1: Company | B1: Year | C1: ROE | D1: ROA | E1: NetMargin | F1: EBITMargin | G1: AssetTurnover | H1: EquityMultiplier | I1: DebtToEquity | J1: DebtRatio | K1: InterestCoverage | L1: CurrentRatio | N1: ROE trend
A2: ='Raw Data'!A2 | B2: ='Raw Data'!B2 | C2: ='Raw Data'!J2/'Raw Data'!Y2 | D2: ='Raw Data'!J2/'Raw Data'!N2 | E2: ='Raw Data'!J2/'Raw Data'!C2 | F2: ='Raw Data'!W2/'Raw Data'!C2 | G2: ='Raw Data'!C2/'Raw Data'!N2 | H2: ='Raw Data'!N2/'Raw Data'!Y2 | I2: ='Raw Data'!M2/'Raw Data'!Y2 | J2: ='Raw Data'!M2/'Raw Data'!N2 | K2: =IF('Raw Data'!F2=0,NA(),'Raw Data'!W2/'Raw Data'!F2) | L2: ='Raw Data'!Z2/'Raw Data'!AA2 | O2: ='Raw Data'!A2 | P2: ='Raw Data'!A7 | Q2: ='Raw Data'!A12 | R2: ='Raw Data'!A17 | S2: ='Raw Data'!A22 | T2: ='Raw Data'!A27 | U2: ='Raw Data'!A32 | V2: ='Raw Data'!A37
A3: ='Raw Data'!A3 | B3: ='Raw Data'!B3 | C3: ='Raw Data'!J3/'Raw Data'!Y3 | D3: ='Raw Data'!J3/'Raw Data'!N3 | E3: ='Raw Data'!J3/'Raw Data'!C3 | F3: ='Raw Data'!W3/'Raw Data'!C3 | G3: ='Raw Data'!C3/'Raw Data'!N3 | H3: ='Raw Data'!N3/'Raw Data'!Y3 | I3: ='Raw Data'!M3/'Raw Data'!Y3 | J3: ='Raw Data'!M3/'Raw Data'!N3 | K3: =IF('Raw Data'!F3=0,NA(),'Raw Data'!W3/'Raw Data'!F3) | L3: ='Raw Data'!Z3/'Raw Data'!AA3 | N3: FY2022 | O3: =C2 | P3: =C7 | Q3: =C12 | R3: =C17 | S3: =C22 | T3: =C27 | U3: =C32 | V3: =C37
A4: ='Raw Data'!A4 | B4: ='Raw Data'!B4 | C4: ='Raw Data'!J4/'Raw Data'!Y4 | D4: ='Raw Data'!J4/'Raw Data'!N4 | E4: ='Raw Data'!J4/'Raw Data'!C4 | F4: ='Raw Data'!W4/'Raw Data'!C4 | G4: ='Raw Data'!C4/'Raw Data'!N4 | H4: ='Raw Data'!N4/'Raw Data'!Y4 | I4: ='Raw Data'!M4/'Raw Data'!Y4 | J4: ='Raw Data'!M4/'Raw Data'!N4 | K4: =IF('Raw Data'!F4=0,NA(),'Raw Data'!W4/'Raw Data'!F4) | L4: ='Raw Data'!Z4/'Raw Data'!AA4 | N4: FY2023 | O4: =C3 | P4: =C8 | Q4: =C13 | R4: =C18 | S4: =C23 | T4: =C28 | U4: =C33 | V4: =C38
A5: ='Raw Data'!A5 | B5: ='Raw Data'!B5 | C5: ='Raw Data'!J5/'Raw Data'!Y5 | D5: ='Raw Data'!J5/'Raw Data'!N5 | E5: ='Raw Data'!J5/'Raw Data'!C5 | F5: ='Raw Data'!W5/'Raw Data'!C5 | G5: ='Raw Data'!C5/'Raw Data'!N5 | H5: ='Raw Data'!N5/'Raw Data'!Y5 | I5: ='Raw Data'!M5/'Raw Data'!Y5 | J5: ='Raw Data'!M5/'Raw Data'!N5 | K5: =IF('Raw Data'!F5=0,NA(),'Raw Data'!W5/'Raw Data'!F5) | L5: ='Raw Data'!Z5/'Raw Data'!AA5 | N5: FY2024 | O5: =C4 | P5: =C9 | Q5: =C14 | R5: =C19 | S5: =C24 | T5: =C29 | U5: =C34 | V5: =C39
A6: ='Raw Data'!A6 | B6: ='Raw Data'!B6 | C6: ='Raw Data'!J6/'Raw Data'!Y6 | D6: ='Raw Data'!J6/'Raw Data'!N6 | E6: ='Raw Data'!J6/'Raw Data'!C6 | F6: ='Raw Data'!W6/'Raw Data'!C6 | G6: ='Raw Data'!C6/'Raw Data'!N6 | H6: ='Raw Data'!N6/'Raw Data'!Y6 | I6: ='Raw Data'!M6/'Raw Data'!Y6 | J6: ='Raw Data'!M6/'Raw Data'!N6 | K6: =IF('Raw Data'!F6=0,NA(),'Raw Data'!W6/'Raw Data'!F6) | L6: ='Raw Data'!Z6/'Raw Data'!AA6 | N6: FY2025 | O6: =C5 | P6: =C10 | Q6: =C15 | R6: =C20 | S6: =C25 | T6: =C30 | U6: =C35 | V6: =C40
A7: ='Raw Data'!A7 | B7: ='Raw Data'!B7 | C7: ='Raw Data'!J7/'Raw Data'!Y7 | D7: ='Raw Data'!J7/'Raw Data'!N7 | E7: ='Raw Data'!J7/'Raw Data'!C7 | F7: ='Raw Data'!W7/'Raw Data'!C7 | G7: ='Raw Data'!C7/'Raw Data'!N7 | H7: ='Raw Data'!N7/'Raw Data'!Y7 | I7: ='Raw Data'!M7/'Raw Data'!Y7 | J7: ='Raw Data'!M7/'Raw Data'!N7 | K7: =IF('Raw Data'!F7=0,NA(),'Raw Data'!W7/'Raw Data'!F7) | L7: ='Raw Data'!Z7/'Raw Data'!AA7 | N7: FY2026 | O7: =C6 | P7: =C11 | Q7: =C16 | R7: =C21 | S7: =C26 | T7: =C31 | U7: =C36 | V7: =C41
A8: ='Raw Data'!A8 | B8: ='Raw Data'!B8 | C8: ='Raw Data'!J8/'Raw Data'!Y8 | D8: ='Raw Data'!J8/'Raw Data'!N8 | E8: ='Raw Data'!J8/'Raw Data'!C8 | F8: ='Raw Data'!W8/'Raw Data'!C8 | G8: ='Raw Data'!C8/'Raw Data'!N8 | H8: ='Raw Data'!N8/'Raw Data'!Y8 | I8: ='Raw Data'!M8/'Raw Data'!Y8 | J8: ='Raw Data'!M8/'Raw Data'!N8 | K8: =IF('Raw Data'!F8=0,NA(),'Raw Data'!W8/'Raw Data'!F8) | L8: ='Raw Data'!Z8/'Raw Data'!AA8
A9: ='Raw Data'!A9 | B9: ='Raw Data'!B9 | C9: ='Raw Data'!J9/'Raw Data'!Y9 | D9: ='Raw Data'!J9/'Raw Data'!N9 | E9: ='Raw Data'!J9/'Raw Data'!C9 | F9: ='Raw Data'!W9/'Raw Data'!C9 | G9: ='Raw Data'!C9/'Raw Data'!N9 | H9: ='Raw Data'!N9/'Raw Data'!Y9 | I9: ='Raw Data'!M9/'Raw Data'!Y9 | J9: ='Raw Data'!M9/'Raw Data'!N9 | K9: =IF('Raw Data'!F9=0,NA(),'Raw Data'!W9/'Raw Data'!F9) | L9: ='Raw Data'!Z9/'Raw Data'!AA9
A10: ='Raw Data'!A10 | B10: ='Raw Data'!B10 | C10: ='Raw Data'!J10/'Raw Data'!Y10 | D10: ='Raw Data'!J10/'Raw Data'!N10 | E10: ='Raw Data'!J10/'Raw Data'!C10 | F10: ='Raw Data'!W10/'Raw Data'!C10 | G10: ='Raw Data'!C10/'Raw Data'!N10 | H10: ='Raw Data'!N10/'Raw Data'!Y10 | I10: ='Raw Data'!M10/'Raw Data'!Y10 | J10: ='Raw Data'!M10/'Raw Data'!N10 | K10: =IF('Raw Data'!F10=0,NA(),'Raw Data'!W10/'Raw Data'!F10) | L10: ='Raw Data'!Z10/'Raw Data'!AA10
A11: ='Raw Data'!A11 | B11: ='Raw Data'!B11 | C11: ='Raw Data'!J11/'Raw Data'!Y11 | D11: ='Raw Data'!J11/'Raw Data'!N11 | E11: ='Raw Data'!J11/'Raw Data'!C11 | F11: ='Raw Data'!W11/'Raw Data'!C11 | G11: ='Raw Data'!C11/'Raw Data'!N11 | H11: ='Raw Data'!N11/'Raw Data'!Y11 | I11: ='Raw Data'!M11/'Raw Data'!Y11 | J11: ='Raw Data'!M11/'Raw Data'!N11 | K11: =IF('Raw Data'!F11=0,NA(),'Raw Data'!W11/'Raw Data'!F11) | L11: ='Raw Data'!Z11/'Raw Data'!AA11
A12: ='Raw Data'!A12 | B12: ='Raw Data'!B12 | C12: ='Raw Data'!J12/'Raw Data'!Y12 | D12: ='Raw Data'!J12/'Raw Data'!N12 | E12: ='Raw Data'!J12/'Raw Data'!C12 | F12: ='Raw Data'!W12/'Raw Data'!C12 | G12: ='Raw Data'!C12/'Raw Data'!N12 | H12: ='Raw Data'!N12/'Raw Data'!Y12 | I12: ='Raw Data'!M12/'Raw Data'!Y12 | J12: ='Raw Data'!M12/'Raw Data'!N12 | K12: =IF('Raw Data'!F12=0,NA(),'Raw Data'!W12/'Raw Data'!F12) | L12: ='Raw Data'!Z12/'Raw Data'!AA12
A13: ='Raw Data'!A13 | B13: ='Raw Data'!B13 | C13: ='Raw Data'!J13/'Raw Data'!Y13 | D13: ='Raw Data'!J13/'Raw Data'!N13 | E13: ='Raw Data'!J13/'Raw Data'!C13 | F13: ='Raw Data'!W13/'Raw Data'!C13 | G13: ='Raw Data'!C13/'Raw Data'!N13 | H13: ='Raw Data'!N13/'Raw Data'!Y13 | I13: ='Raw Data'!M13/'Raw Data'!Y13 | J13: ='Raw Data'!M13/'Raw Data'!N13 | K13: =IF('Raw Data'!F13=0,NA(),'Raw Data'!W13/'Raw Data'!F13) | L13: ='Raw Data'!Z13/'Raw Data'!AA13
A14: ='Raw Data'!A14 | B14: ='Raw Data'!B14 | C14: ='Raw Data'!J14/'Raw Data'!Y14 | D14: ='Raw Data'!J14/'Raw Data'!N14 | E14: ='Raw Data'!J14/'Raw Data'!C14 | F14: ='Raw Data'!W14/'Raw Data'!C14 | G14: ='Raw Data'!C14/'Raw Data'!N14 | H14: ='Raw Data'!N14/'Raw Data'!Y14 | I14: ='Raw Data'!M14/'Raw Data'!Y14 | J14: ='Raw Data'!M14/'Raw Data'!N14 | K14: =IF('Raw Data'!F14=0,NA(),'Raw Data'!W14/'Raw Data'!F14) | L14: ='Raw Data'!Z14/'Raw Data'!AA14
A15: ='Raw Data'!A15 | B15: ='Raw Data'!B15 | C15: ='Raw Data'!J15/'Raw Data'!Y15 | D15: ='Raw Data'!J15/'Raw Data'!N15 | E15: ='Raw Data'!J15/'Raw Data'!C15 | F15: ='Raw Data'!W15/'Raw Data'!C15 | G15: ='Raw Data'!C15/'Raw Data'!N15 | H15: ='Raw Data'!N15/'Raw Data'!Y15 | I15: ='Raw Data'!M15/'Raw Data'!Y15 | J15: ='Raw Data'!M15/'Raw Data'!N15 | K15: =IF('Raw Data'!F15=0,NA(),'Raw Data'!W15/'Raw Data'!F15) | L15: ='Raw Data'!Z15/'Raw Data'!AA15
A16: ='Raw Data'!A16 | B16: ='Raw Data'!B16 | C16: ='Raw Data'!J16/'Raw Data'!Y16 | D16: ='Raw Data'!J16/'Raw Data'!N16 | E16: ='Raw Data'!J16/'Raw Data'!C16 | F16: ='Raw Data'!W16/'Raw Data'!C16 | G16: ='Raw Data'!C16/'Raw Data'!N16 | H16: ='Raw Data'!N16/'Raw Data'!Y16 | I16: ='Raw Data'!M16/'Raw Data'!Y16 | J16: ='Raw Data'!M16/'Raw Data'!N16 | K16: =IF('Raw Data'!F16=0,NA(),'Raw Data'!W16/'Raw Data'!F16) | L16: ='Raw Data'!Z16/'Raw Data'!AA16
A17: ='Raw Data'!A17 | B17: ='Raw Data'!B17 | C17: ='Raw Data'!J17/'Raw Data'!Y17 | D17: ='Raw Data'!J17/'Raw Data'!N17 | E17: ='Raw Data'!J17/'Raw Data'!C17 | F17: ='Raw Data'!W17/'Raw Data'!C17 | G17: ='Raw Data'!C17/'Raw Data'!N17 | H17: ='Raw Data'!N17/'Raw Data'!Y17 | I17: ='Raw Data'!M17/'Raw Data'!Y17 | J17: ='Raw Data'!M17/'Raw Data'!N17 | K17: =IF('Raw Data'!F17=0,NA(),'Raw Data'!W17/'Raw Data'!F17) | L17: ='Raw Data'!Z17/'Raw Data'!AA17
A18: ='Raw Data'!A18 | B18: ='Raw Data'!B18 | C18: ='Raw Data'!J18/'Raw Data'!Y18 | D18: ='Raw Data'!J18/'Raw Data'!N18 | E18: ='Raw Data'!J18/'Raw Data'!C18 | F18: ='Raw Data'!W18/'Raw Data'!C18 | G18: ='Raw Data'!C18/'Raw Data'!N18 | H18: ='Raw Data'!N18/'Raw Data'!Y18 | I18: ='Raw Data'!M18/'Raw Data'!Y18 | J18: ='Raw Data'!M18/'Raw Data'!N18 | K18: =IF('Raw Data'!F18=0,NA(),'Raw Data'!W18/'Raw Data'!F18) | L18: ='Raw Data'!Z18/'Raw Data'!AA18
A19: ='Raw Data'!A19 | B19: ='Raw Data'!B19 | C19: ='Raw Data'!J19/'Raw Data'!Y19 | D19: ='Raw Data'!J19/'Raw Data'!N19 | E19: ='Raw Data'!J19/'Raw Data'!C19 | F19: ='Raw Data'!W19/'Raw Data'!C19 | G19: ='Raw Data'!C19/'Raw Data'!N19 | H19: ='Raw Data'!N19/'Raw Data'!Y19 | I19: ='Raw Data'!M19/'Raw Data'!Y19 | J19: ='Raw Data'!M19/'Raw Data'!N19 | K19: =IF('Raw Data'!F19=0,NA(),'Raw Data'!W19/'Raw Data'!F19) | L19: ='Raw Data'!Z19/'Raw Data'!AA19
... A41: ='Raw Data'!A41 | B41: ='Raw Data'!B41 | C41: ='Raw Data'!J41/'Raw Data'!Y41 | D41: ='Raw Data'!J41/'Raw Data'!N41 | E41: ='Raw Data'!J41/'Raw Data'!C41 | F41: ='Raw Data'!W41/'Raw Data'!C41 | G41: ='Raw Data'!C41/'Raw Data'!N41 | H41: ='Raw Data'!N41/'Raw Data'!Y41 | I41: ='Raw Data'!M41/'Raw Data'!Y41 | J41: ='Raw Data'!M41/'Raw Data'!N41 | K41: =IF('Raw Data'!F41=0,NA(),'Raw Data'!W41/'Raw Data'!F41) | L41: ='Raw Data'!Z41/'Raw Data'!AA41
A43: Every cell is a live formula into Raw Data. InterestCoverage is #N/A when InterestExpense = 0. CurrentRatio uses the schedule-based approximations (see Raw Data note).

Sheet DuPont Analysis
A1: Company | B1: Year | C1: TaxBurden NI/PBT | D1: IntBurden PBT/EBIT | E1: EBITMargin EBIT/Rev | F1: AssetTurn Rev/Assets | G1: EqMult Assets/Equity | H1: DuPont ROE | I1: Reported ROE | J1: Check | L1: ln-contributions (latest FY)
A2: ='Raw Data'!A2 | B2: ='Raw Data'!B2 | C2: ='Raw Data'!J2/'Raw Data'!H2 | D2: ='Raw Data'!H2/'Raw Data'!W2 | E2: ='Raw Data'!W2/'Raw Data'!C2 | F2: ='Raw Data'!C2/'Raw Data'!N2 | G2: ='Raw Data'!N2/'Raw Data'!Y2 | H2: =C2*D2*E2*F2*G2 | I2: ='Ratio Analysis'!C2 | J2: =IF(ABS(H2-I2)<0.0001,"✓","⚠") | L2: Firm | M2: TaxBurden | N2: IntBurden | O2: EBITMargin | P2: AssetTurn | Q2: EqMult
A3: ='Raw Data'!A3 | B3: ='Raw Data'!B3 | C3: ='Raw Data'!J3/'Raw Data'!H3 | D3: ='Raw Data'!H3/'Raw Data'!W3 | E3: ='Raw Data'!W3/'Raw Data'!C3 | F3: ='Raw Data'!C3/'Raw Data'!N3 | G3: ='Raw Data'!N3/'Raw Data'!Y3 | H3: =C3*D3*E3*F3*G3 | I3: ='Ratio Analysis'!C3 | J3: =IF(ABS(H3-I3)<0.0001,"✓","⚠") | L3: ='Raw Data'!A6 | M3: =LN(C6) | N3: =LN(D6) | O3: =LN(E6) | P3: =LN(F6) | Q3: =LN(G6)
A4: ='Raw Data'!A4 | B4: ='Raw Data'!B4 | C4: ='Raw Data'!J4/'Raw Data'!H4 | D4: ='Raw Data'!H4/'Raw Data'!W4 | E4: ='Raw Data'!W4/'Raw Data'!C4 | F4: ='Raw Data'!C4/'Raw Data'!N4 | G4: ='Raw Data'!N4/'Raw Data'!Y4 | H4: =C4*D4*E4*F4*G4 | I4: ='Ratio Analysis'!C4 | J4: =IF(ABS(H4-I4)<0.0001,"✓","⚠") | L4: ='Raw Data'!A11 | M4: =LN(C11) | N4: =LN(D11) | O4: =LN(E11) | P4: =LN(F11) | Q4: =LN(G11)
A5: ='Raw Data'!A5 | B5: ='Raw Data'!B5 | C5: ='Raw Data'!J5/'Raw Data'!H5 | D5: ='Raw Data'!H5/'Raw Data'!W5 | E5: ='Raw Data'!W5/'Raw Data'!C5 | F5: ='Raw Data'!C5/'Raw Data'!N5 | G5: ='Raw Data'!N5/'Raw Data'!Y5 | H5: =C5*D5*E5*F5*G5 | I5: ='Ratio Analysis'!C5 | J5: =IF(ABS(H5-I5)<0.0001,"✓","⚠") | L5: ='Raw Data'!A16 | M5: =LN(C16) | N5: =LN(D16) | O5: =LN(E16) | P5: =LN(F16) | Q5: =LN(G16)
A6: ='Raw Data'!A6 | B6: ='Raw Data'!B6 | C6: ='Raw Data'!J6/'Raw Data'!H6 | D6: ='Raw Data'!H6/'Raw Data'!W6 | E6: ='Raw Data'!W6/'Raw Data'!C6 | F6: ='Raw Data'!C6/'Raw Data'!N6 | G6: ='Raw Data'!N6/'Raw Data'!Y6 | H6: =C6*D6*E6*F6*G6 | I6: ='Ratio Analysis'!C6 | J6: =IF(ABS(H6-I6)<0.0001,"✓","⚠") | L6: ='Raw Data'!A21 | M6: =LN(C21) | N6: =LN(D21) | O6: =LN(E21) | P6: =LN(F21) | Q6: =LN(G21)
A7: ='Raw Data'!A7 | B7: ='Raw Data'!B7 | C7: ='Raw Data'!J7/'Raw Data'!H7 | D7: ='Raw Data'!H7/'Raw Data'!W7 | E7: ='Raw Data'!W7/'Raw Data'!C7 | F7: ='Raw Data'!C7/'Raw Data'!N7 | G7: ='Raw Data'!N7/'Raw Data'!Y7 | H7: =C7*D7*E7*F7*G7 | I7: ='Ratio Analysis'!C7 | J7: =IF(ABS(H7-I7)<0.0001,"✓","⚠") | L7: ='Raw Data'!A26 | M7: =LN(C26) | N7: =LN(D26) | O7: =LN(E26) | P7: =LN(F26) | Q7: =LN(G26)
A8: ='Raw Data'!A8 | B8: ='Raw Data'!B8 | C8: ='Raw Data'!J8/'Raw Data'!H8 | D8: ='Raw Data'!H8/'Raw Data'!W8 | E8: ='Raw Data'!W8/'Raw Data'!C8 | F8: ='Raw Data'!C8/'Raw Data'!N8 | G8: ='Raw Data'!N8/'Raw Data'!Y8 | H8: =C8*D8*E8*F8*G8 | I8: ='Ratio Analysis'!C8 | J8: =IF(ABS(H8-I8)<0.0001,"✓","⚠") | L8: ='Raw Data'!A31 | M8: =LN(C31) | N8: =LN(D31) | O8: =LN(E31) | P8: =LN(F31) | Q8: =LN(G31)
A9: ='Raw Data'!A9 | B9: ='Raw Data'!B9 | C9: ='Raw Data'!J9/'Raw Data'!H9 | D9: ='Raw Data'!H9/'Raw Data'!W9 | E9: ='Raw Data'!W9/'Raw Data'!C9 | F9: ='Raw Data'!C9/'Raw Data'!N9 | G9: ='Raw Data'!N9/'Raw Data'!Y9 | H9: =C9*D9*E9*F9*G9 | I9: ='Ratio Analysis'!C9 | J9: =IF(ABS(H9-I9)<0.0001,"✓","⚠") | L9: ='Raw Data'!A36 | M9: =LN(C36) | N9: =LN(D36) | O9: =LN(E36) | P9: =LN(F36) | Q9: =LN(G36)
A10: ='Raw Data'!A10 | B10: ='Raw Data'!B10 | C10: ='Raw Data'!J10/'Raw Data'!H10 | D10: ='Raw Data'!H10/'Raw Data'!W10 | E10: ='Raw Data'!W10/'Raw Data'!C10 | F10: ='Raw Data'!C10/'Raw Data'!N10 | G10: ='Raw Data'!N10/'Raw Data'!Y10 | H10: =C10*D10*E10*F10*G10 | I10: ='Ratio Analysis'!C10 | J10: =IF(ABS(H10-I10)<0.0001,"✓","⚠") | L10: ='Raw Data'!A41 | M10: =LN(C41) | N10: =LN(D41) | O10: =LN(E41) | P10: =LN(F41) | Q10: =LN(G41)
A11: ='Raw Data'!A11 | B11: ='Raw Data'!B11 | C11: ='Raw Data'!J11/'Raw Data'!H11 | D11: ='Raw Data'!H11/'Raw Data'!W11 | E11: ='Raw Data'!W11/'Raw Data'!C11 | F11: ='Raw Data'!C11/'Raw Data'!N11 | G11: ='Raw Data'!N11/'Raw Data'!Y11 | H11: =C11*D11*E11*F11*G11 | I11: ='Ratio Analysis'!C11 | J11: =IF(ABS(H11-I11)<0.0001,"✓","⚠")
A12: ='Raw Data'!A12 | B12: ='Raw Data'!B12 | C12: ='Raw Data'!J12/'Raw Data'!H12 | D12: ='Raw Data'!H12/'Raw Data'!W12 | E12: ='Raw Data'!W12/'Raw Data'!C12 | F12: ='Raw Data'!C12/'Raw Data'!N12 | G12: ='Raw Data'!N12/'Raw Data'!Y12 | H12: =C12*D12*E12*F12*G12 | I12: ='Ratio Analysis'!C12 | J12: =IF(ABS(H12-I12)<0.0001,"✓","⚠")
A13: ='Raw Data'!A13 | B13: ='Raw Data'!B13 | C13: ='Raw Data'!J13/'Raw Data'!H13 | D13: ='Raw Data'!H13/'Raw Data'!W13 | E13: ='Raw Data'!W13/'Raw Data'!C13 | F13: ='Raw Data'!C13/'Raw Data'!N13 | G13: ='Raw Data'!N13/'Raw Data'!Y13 | H13: =C13*D13*E13*F13*G13 | I13: ='Ratio Analysis'!C13 | J13: =IF(ABS(H13-I13)<0.0001,"✓","⚠")
A14: ='Raw Data'!A14 | B14: ='Raw Data'!B14 | C14: ='Raw Data'!J14/'Raw Data'!H14 | D14: ='Raw Data'!H14/'Raw Data'!W14 | E14: ='Raw Data'!W14/'Raw Data'!C14 | F14: ='Raw Data'!C14/'Raw Data'!N14 | G14: ='Raw Data'!N14/'Raw Data'!Y14 | H14: =C14*D14*E14*F14*G14 | I14: ='Ratio Analysis'!C14 | J14: =IF(ABS(H14-I14)<0.0001,"✓","⚠")
A15: ='Raw Data'!A15 | B15: ='Raw Data'!B15 | C15: ='Raw Data'!J15/'Raw Data'!H15 | D15: ='Raw Data'!H15/'Raw Data'!W15 | E15: ='Raw Data'!W15/'Raw Data'!C15 | F15: ='Raw Data'!C15/'Raw Data'!N15 | G15: ='Raw Data'!N15/'Raw Data'!Y15 | H15: =C15*D15*E15*F15*G15 | I15: ='Ratio Analysis'!C15 | J15: =IF(ABS(H15-I15)<0.0001,"✓","⚠")
A16: ='Raw Data'!A16 | B16: ='Raw Data'!B16 | C16: ='Raw Data'!J16/'Raw Data'!H16 | D16: ='Raw Data'!H16/'Raw Data'!W16 | E16: ='Raw Data'!W16/'Raw Data'!C16 | F16: ='Raw Data'!C16/'Raw Data'!N16 | G16: ='Raw Data'!N16/'Raw Data'!Y16 | H16: =C16*D16*E16*F16*G16 | I16: ='Ratio Analysis'!C16 | J16: =IF(ABS(H16-I16)<0.0001,"✓","⚠")
A17: ='Raw Data'!A17 | B17: ='Raw Data'!B17 | C17: ='Raw Data'!J17/'Raw Data'!H17 | D17: ='Raw Data'!H17/'Raw Data'!W17 | E17: ='Raw Data'!W17/'Raw Data'!C17 | F17: ='Raw Data'!C17/'Raw Data'!N17 | G17: ='Raw Data'!N17/'Raw Data'!Y17 | H17: =C17*D17*E17*F17*G17 | I17: ='Ratio Analysis'!C17 | J17: =IF(ABS(H17-I17)<0.0001,"✓","⚠")
A18: ='Raw Data'!A18 | B18: ='Raw Data'!B18 | C18: ='Raw Data'!J18/'Raw Data'!H18 | D18: ='Raw Data'!H18/'Raw Data'!W18 | E18: ='Raw Data'!W18/'Raw Data'!C18 | F18: ='Raw Data'!C18/'Raw Data'!N18 | G18: ='Raw Data'!N18/'Raw Data'!Y18 | H18: =C18*D18*E18*F18*G18 | I18: ='Ratio Analysis'!C18 | J18: =IF(ABS(H18-I18)<0.0001,"✓","⚠")
A19: ='Raw Data'!A19 | B19: ='Raw Data'!B19 | C19: ='Raw Data'!J19/'Raw Data'!H19 | D19: ='Raw Data'!H19/'Raw Data'!W19 | E19: ='Raw Data'!W19/'Raw Data'!C19 | F19: ='Raw Data'!C19/'Raw Data'!N19 | G19: ='Raw Data'!N19/'Raw Data'!Y19 | H19: =C19*D19*E19*F19*G19 | I19: ='Ratio Analysis'!C19 | J19: =IF(ABS(H19-I19)<0.0001,"✓","⚠")
A20: ='Raw Data'!A20 | B20: ='Raw Data'!B20 | C20: ='Raw Data'!J20/'Raw Data'!H20 | D20: ='Raw Data'!H20/'Raw Data'!W20 | E20: ='Raw Data'!W20/'Raw Data'!C20 | F20: ='Raw Data'!C20/'Raw Data'!N20 | G20: ='Raw Data'!N20/'Raw Data'!Y20 | H20: =C20*D20*E20*F20*G20 | I20: ='Ratio Analysis'!C20 | J20: =IF(ABS(H20-I20)<0.0001,"✓","⚠")
A21: ='Raw Data'!A21 | B21: ='Raw Data'!B21 | C21: ='Raw Data'!J21/'Raw Data'!H21 | D21: ='Raw Data'!H21/'Raw Data'!W21 | E21: ='Raw Data'!W21/'Raw Data'!C21 | F21: ='Raw Data'!C21/'Raw Data'!N21 | G21: ='Raw Data'!N21/'Raw Data'!Y21 | H21: =C21*D21*E21*F21*G21 | I21: ='Ratio Analysis'!C21 | J21: =IF(ABS(H21-I21)<0.0001,"✓","⚠")
A22: ='Raw Data'!A22 | B22: ='Raw Data'!B22 | C22: ='Raw Data'!J22/'Raw Data'!H22 | D22: ='Raw Data'!H22/'Raw Data'!W22 | E22: ='Raw Data'!W22/'Raw Data'!C22 | F22: ='Raw Data'!C22/'Raw Data'!N22 | G22: ='Raw Data'!N22/'Raw Data'!Y22 | H22: =C22*D22*E22*F22*G22 | I22: ='Ratio Analysis'!C22 | J22: =IF(ABS(H22-I22)<0.0001,"✓","⚠")
... A41: ='Raw Data'!A41 | B41: ='Raw Data'!B41 | C41: ='Raw Data'!J41/'Raw Data'!H41 | D41: ='Raw Data'!H41/'Raw Data'!W41 | E41: ='Raw Data'!W41/'Raw Data'!C41 | F41: ='Raw Data'!C41/'Raw Data'!N41 | G41: ='Raw Data'!N41/'Raw Data'!Y41 | H41: =C41*D41*E41*F41*G41 | I41: ='Ratio Analysis'!C41 | J41: =IF(ABS(H41-I41)<0.0001,"✓","⚠")
A43: 5-step DuPont: ROE = TaxBurden × IntBurden × EBITMargin × AssetTurnover × EqMultiplier. EBIT = PBT + Interest, so the identity is exact — Check must read ✓ on every row. Segments below zero in the chart (ln of components < 1) drag ROE down.

Sheet Capital Structure
A1: Company | B1: Year | C1: DebtToEquity | D1: DebtRatio | E1: InterestCoverage | F1: Band | H1: band edges | K1: D/E pivot
A2: ='Raw Data'!A2 | B2: ='Raw Data'!B2 | C2: ='Raw Data'!M2/'Raw Data'!Y2 | D2: ='Raw Data'!M2/'Raw Data'!N2 | E2: =IF('Raw Data'!F2=0,NA(),'Raw Data'!W2/'Raw Data'!F2) | F2: =IF(C2<$I$2,"Low",IF(C2<=$I$3,"Mid","High")) | H2: Low ≤ | I2: 0.3 | L2: ='Raw Data'!A2 | M2: ='Raw Data'!A7 | N2: ='Raw Data'!A12 | O2: ='Raw Data'!A17 | P2: ='Raw Data'!A22 | Q2: ='Raw Data'!A27 | R2: ='Raw Data'!A32 | S2: ='Raw Data'!A37
A3: ='Raw Data'!A3 | B3: ='Raw Data'!B3 | C3: ='Raw Data'!M3/'Raw Data'!Y3 | D3: ='Raw Data'!M3/'Raw Data'!N3 | E3: =IF('Raw Data'!F3=0,NA(),'Raw Data'!W3/'Raw Data'!F3) | F3: =IF(C3<$I$2,"Low",IF(C3<=$I$3,"Mid","High")) | H3: Mid ≤ | I3: 0.7 | K3: FY2022 | L3: =C2 | M3: =C7 | N3: =C12 | O3: =C17 | P3: =C22 | Q3: =C27 | R3: =C32 | S3: =C37
A4: ='Raw Data'!A4 | B4: ='Raw Data'!B4 | C4: ='Raw Data'!M4/'Raw Data'!Y4 | D4: ='Raw Data'!M4/'Raw Data'!N4 | E4: =IF('Raw Data'!F4=0,NA(),'Raw Data'!W4/'Raw Data'!F4) | F4: =IF(C4<$I$2,"Low",IF(C4<=$I$3,"Mid","High")) | K4: FY2023 | L4: =C3 | M4: =C8 | N4: =C13 | O4: =C18 | P4: =C23 | Q4: =C28 | R4: =C33 | S4: =C38
A5: ='Raw Data'!A5 | B5: ='Raw Data'!B5 | C5: ='Raw Data'!M5/'Raw Data'!Y5 | D5: ='Raw Data'!M5/'Raw Data'!N5 | E5: =IF('Raw Data'!F5=0,NA(),'Raw Data'!W5/'Raw Data'!F5) | F5: =IF(C5<$I$2,"Low",IF(C5<=$I$3,"Mid","High")) | K5: FY2024 | L5: =C4 | M5: =C9 | N5: =C14 | O5: =C19 | P5: =C24 | Q5: =C29 | R5: =C34 | S5: =C39
A6: ='Raw Data'!A6 | B6: ='Raw Data'!B6 | C6: ='Raw Data'!M6/'Raw Data'!Y6 | D6: ='Raw Data'!M6/'Raw Data'!N6 | E6: =IF('Raw Data'!F6=0,NA(),'Raw Data'!W6/'Raw Data'!F6) | F6: =IF(C6<$I$2,"Low",IF(C6<=$I$3,"Mid","High")) | K6: FY2025 | L6: =C5 | M6: =C10 | N6: =C15 | O6: =C20 | P6: =C25 | Q6: =C30 | R6: =C35 | S6: =C40
A7: ='Raw Data'!A7 | B7: ='Raw Data'!B7 | C7: ='Raw Data'!M7/'Raw Data'!Y7 | D7: ='Raw Data'!M7/'Raw Data'!N7 | E7: =IF('Raw Data'!F7=0,NA(),'Raw Data'!W7/'Raw Data'!F7) | F7: =IF(C7<$I$2,"Low",IF(C7<=$I$3,"Mid","High")) | K7: FY2026 | L7: =C6 | M7: =C11 | N7: =C16 | O7: =C21 | P7: =C26 | Q7: =C31 | R7: =C36 | S7: =C41
A8: ='Raw Data'!A8 | B8: ='Raw Data'!B8 | C8: ='Raw Data'!M8/'Raw Data'!Y8 | D8: ='Raw Data'!M8/'Raw Data'!N8 | E8: =IF('Raw Data'!F8=0,NA(),'Raw Data'!W8/'Raw Data'!F8) | F8: =IF(C8<$I$2,"Low",IF(C8<=$I$3,"Mid","High"))
A9: ='Raw Data'!A9 | B9: ='Raw Data'!B9 | C9: ='Raw Data'!M9/'Raw Data'!Y9 | D9: ='Raw Data'!M9/'Raw Data'!N9 | E9: =IF('Raw Data'!F9=0,NA(),'Raw Data'!W9/'Raw Data'!F9) | F9: =IF(C9<$I$2,"Low",IF(C9<=$I$3,"Mid","High"))
A10: ='Raw Data'!A10 | B10: ='Raw Data'!B10 | C10: ='Raw Data'!M10/'Raw Data'!Y10 | D10: ='Raw Data'!M10/'Raw Data'!N10 | E10: =IF('Raw Data'!F10=0,NA(),'Raw Data'!W10/'Raw Data'!F10) | F10: =IF(C10<$I$2,"Low",IF(C10<=$I$3,"Mid","High")) | K10: InterestCoverage pivot
A11: ='Raw Data'!A11 | B11: ='Raw Data'!B11 | C11: ='Raw Data'!M11/'Raw Data'!Y11 | D11: ='Raw Data'!M11/'Raw Data'!N11 | E11: =IF('Raw Data'!F11=0,NA(),'Raw Data'!W11/'Raw Data'!F11) | F11: =IF(C11<$I$2,"Low",IF(C11<=$I$3,"Mid","High")) | L11: ='Raw Data'!A2 | M11: ='Raw Data'!A7 | N11: ='Raw Data'!A12 | O11: ='Raw Data'!A17 | P11: ='Raw Data'!A22 | Q11: ='Raw Data'!A27 | R11: ='Raw Data'!A32 | S11: ='Raw Data'!A37
A12: ='Raw Data'!A12 | B12: ='Raw Data'!B12 | C12: ='Raw Data'!M12/'Raw Data'!Y12 | D12: ='Raw Data'!M12/'Raw Data'!N12 | E12: =IF('Raw Data'!F12=0,NA(),'Raw Data'!W12/'Raw Data'!F12) | F12: =IF(C12<$I$2,"Low",IF(C12<=$I$3,"Mid","High")) | K12: FY2022 | L12: =E2 | M12: =E7 | N12: =E12 | O12: =E17 | P12: =E22 | Q12: =E27 | R12: =E32 | S12: =E37
A13: ='Raw Data'!A13 | B13: ='Raw Data'!B13 | C13: ='Raw Data'!M13/'Raw Data'!Y13 | D13: ='Raw Data'!M13/'Raw Data'!N13 | E13: =IF('Raw Data'!F13=0,NA(),'Raw Data'!W13/'Raw Data'!F13) | F13: =IF(C13<$I$2,"Low",IF(C13<=$I$3,"Mid","High")) | K13: FY2023 | L13: =E3 | M13: =E8 | N13: =E13 | O13: =E18 | P13: =E23 | Q13: =E28 | R13: =E33 | S13: =E38
A14: ='Raw Data'!A14 | B14: ='Raw Data'!B14 | C14: ='Raw Data'!M14/'Raw Data'!Y14 | D14: ='Raw Data'!M14/'Raw Data'!N14 | E14: =IF('Raw Data'!F14=0,NA(),'Raw Data'!W14/'Raw Data'!F14) | F14: =IF(C14<$I$2,"Low",IF(C14<=$I$3,"Mid","High")) | K14: FY2024 | L14: =E4 | M14: =E9 | N14: =E14 | O14: =E19 | P14: =E24 | Q14: =E29 | R14: =E34 | S14: =E39
A15: ='Raw Data'!A15 | B15: ='Raw Data'!B15 | C15: ='Raw Data'!M15/'Raw Data'!Y15 | D15: ='Raw Data'!M15/'Raw Data'!N15 | E15: =IF('Raw Data'!F15=0,NA(),'Raw Data'!W15/'Raw Data'!F15) | F15: =IF(C15<$I$2,"Low",IF(C15<=$I$3,"Mid","High")) | K15: FY2025 | L15: =E5 | M15: =E10 | N15: =E15 | O15: =E20 | P15: =E25 | Q15: =E30 | R15: =E35 | S15: =E40
A16: ='Raw Data'!A16 | B16: ='Raw Data'!B16 | C16: ='Raw Data'!M16/'Raw Data'!Y16 | D16: ='Raw Data'!M16/'Raw Data'!N16 | E16: =IF('Raw Data'!F16=0,NA(),'Raw Data'!W16/'Raw Data'!F16) | F16: =IF(C16<$I$2,"Low",IF(C16<=$I$3,"Mid","High")) | K16: FY2026 | L16: =E6 | M16: =E11 | N16: =E16 | O16: =E21 | P16: =E26 | Q16: =E31 | R16: =E36 | S16: =E41
A17: ='Raw Data'!A17 | B17: ='Raw Data'!B17 | C17: ='Raw Data'!M17/'Raw Data'!Y17 | D17: ='Raw Data'!M17/'Raw Data'!N17 | E17: =IF('Raw Data'!F17=0,NA(),'Raw Data'!W17/'Raw Data'!F17) | F17: =IF(C17<$I$2,"Low",IF(C17<=$I$3,"Mid","High"))
A18: ='Raw Data'!A18 | B18: ='Raw Data'!B18 | C18: ='Raw Data'!M18/'Raw Data'!Y18 | D18: ='Raw Data'!M18/'Raw Data'!N18 | E18: =IF('Raw Data'!F18=0,NA(),'Raw Data'!W18/'Raw Data'!F18) | F18: =IF(C18<$I$2,"Low",IF(C18<=$I$3,"Mid","High"))
A19: ='Raw Data'!A19 | B19: ='Raw Data'!B19 | C19: ='Raw Data'!M19/'Raw Data'!Y19 | D19: ='Raw Data'!M19/'Raw Data'!N19 | E19: =IF('Raw Data'!F19=0,NA(),'Raw Data'!W19/'Raw Data'!F19) | F19: =IF(C19<$I$2,"Low",IF(C19<=$I$3,"Mid","High"))
A20: ='Raw Data'!A20 | B20: ='Raw Data'!B20 | C20: ='Raw Data'!M20/'Raw Data'!Y20 | D20: ='Raw Data'!M20/'Raw Data'!N20 | E20: =IF('Raw Data'!F20=0,NA(),'Raw Data'!W20/'Raw Data'!F20) | F20: =IF(C20<$I$2,"Low",IF(C20<=$I$3,"Mid","High"))
A21: ='Raw Data'!A21 | B21: ='Raw Data'!B21 | C21: ='Raw Data'!M21/'Raw Data'!Y21 | D21: ='Raw Data'!M21/'Raw Data'!N21 | E21: =IF('Raw Data'!F21=0,NA(),'Raw Data'!W21/'Raw Data'!F21) | F21: =IF(C21<$I$2,"Low",IF(C21<=$I$3,"Mid","High"))
A22: ='Raw Data'!A22 | B22: ='Raw Data'!B22 | C22: ='Raw Data'!M22/'Raw Data'!Y22 | D22: ='Raw Data'!M22/'Raw Data'!N22 | E22: =IF('Raw Data'!F22=0,NA(),'Raw Data'!W22/'Raw Data'!F22) | F22: =IF(C22<$I$2,"Low",IF(C22<=$I$3,"Mid","High"))
A23: ='Raw Data'!A23 | B23: ='Raw Data'!B23 | C23: ='Raw Data'!M23/'Raw Data'!Y23 | D23: ='Raw Data'!M23/'Raw Data'!N23 | E23: =IF('Raw Data'!F23=0,NA(),'Raw Data'!W23/'Raw Data'!F23) | F23: =IF(C23<$I$2,"Low",IF(C23<=$I$3,"Mid","High"))
A24: ='Raw Data'!A24 | B24: ='Raw Data'!B24 | C24: ='Raw Data'!M24/'Raw Data'!Y24 | D24: ='Raw Data'!M24/'Raw Data'!N24 | E24: =IF('Raw Data'!F24=0,NA(),'Raw Data'!W24/'Raw Data'!F24) | F24: =IF(C24<$I$2,"Low",IF(C24<=$I$3,"Mid","High"))
A25: ='Raw Data'!A25 | B25: ='Raw Data'!B25 | C25: ='Raw Data'!M25/'Raw Data'!Y25 | D25: ='Raw Data'!M25/'Raw Data'!N25 | E25: =IF('Raw Data'!F25=0,NA(),'Raw Data'!W25/'Raw Data'!F25) | F25: =IF(C25<$I$2,"Low",IF(C25<=$I$3,"Mid","High"))
A26: ='Raw Data'!A26 | B26: ='Raw Data'!B26 | C26: ='Raw Data'!M26/'Raw Data'!Y26 | D26: ='Raw Data'!M26/'Raw Data'!N26 | E26: =IF('Raw Data'!F26=0,NA(),'Raw Data'!W26/'Raw Data'!F26) | F26: =IF(C26<$I$2,"Low",IF(C26<=$I$3,"Mid","High"))
A27: ='Raw Data'!A27 | B27: ='Raw Data'!B27 | C27: ='Raw Data'!M27/'Raw Data'!Y27 | D27: ='Raw Data'!M27/'Raw Data'!N27 | E27: =IF('Raw Data'!F27=0,NA(),'Raw Data'!W27/'Raw Data'!F27) | F27: =IF(C27<$I$2,"Low",IF(C27<=$I$3,"Mid","High"))
A28: ='Raw Data'!A28 | B28: ='Raw Data'!B28 | C28: ='Raw Data'!M28/'Raw Data'!Y28 | D28: ='Raw Data'!M28/'Raw Data'!N28 | E28: =IF('Raw Data'!F28=0,NA(),'Raw Data'!W28/'Raw Data'!F28) | F28: =IF(C28<$I$2,"Low",IF(C28<=$I$3,"Mid","High"))
... A41: ='Raw Data'!A41 | B41: ='Raw Data'!B41 | C41: ='Raw Data'!M41/'Raw Data'!Y41 | D41: ='Raw Data'!M41/'Raw Data'!N41 | E41: =IF('Raw Data'!F41=0,NA(),'Raw Data'!W41/'Raw Data'!F41) | F41: =IF(C41<$I$2,"Low",IF(C41<=$I$3,"Mid","High"))
A43: Band = IF(D/E < edge1, Low, IF(≤ edge2, Mid, High)) — edges are the yellow cells, change them and the classification recomputes. This universe is structurally low-leverage.

Sheet Leverage Threshold
A1: Leverage threshold — where does ROE peak across D/E?
A2: bin table computed in python (leverage_threshold.py) on the live ratio panel · scatter is formula-driven off the sheets
A4: Method | B4: Bin | C4: DE_low | D4: DE_high | E4: MeanROE | F4: MeanNetMargin | G4: N
A5: Band | B5: Low | C5: 0.0023 | D5: 0.2835 | E5: 0.41751912 | F5: 0.20892741 | G5: 38 | H5: ← peak ROE
A6: Band | B6: Mid | C6: 0.3163 | D6: 0.3758 | E6: 0.17738751 | F6: 0.15582214 | G6: 2
A7: Quintile | B7: (0.00131, 0.00927] | C7: 0.0023 | D7: 0.0092 | E7: 0.28297954 | F7: 0.28841903 | G7: 8
A8: Quintile | B8: (0.00927, 0.031] | C8: 0.0093 | D8: 0.0309 | E8: 0.31724356 | F8: 0.21649188 | G8: 8
A9: Quintile | B9: (0.031, 0.0534] | C9: 0.031 | D9: 0.0511 | E9: 0.4827884 | F9: 0.19748366 | G9: 8
A10: Quintile | B10: (0.0534, 0.104] | C10: 0.0569 | D10: 0.1033 | E10: 0.43885226 | F10: 0.16485194 | G10: 8
A11: Quintile | B11: (0.104, 0.376] | C11: 0.1074 | D11: 0.3758 | E11: 0.50569895 | F11: 0.16411424 | G11: 8 | H11: ← peak ROE
A12: Decile | B12: (0.00131, 0.00487] | C12: 0.0023 | D12: 0.0048 | E12: 0.31674054 | F12: 0.3326207 | G12: 4
A13: Decile | B13: (0.00487, 0.00927] | C13: 0.0049 | D13: 0.0092 | E13: 0.24921853 | F13: 0.24421735 | G13: 4
A14: Decile | B14: (0.00927, 0.0269] | C14: 0.0093 | D14: 0.0269 | E14: 0.23653804 | F14: 0.19676596 | G14: 4
A15: Decile | B15: (0.0269, 0.031] | C15: 0.027 | D15: 0.0309 | E15: 0.39794908 | F15: 0.2362178 | G15: 4
A16: Decile | B16: (0.031, 0.0393] | C16: 0.031 | D16: 0.0384 | E16: 0.5302086 | F16: 0.21395527 | G16: 4
A17: Decile | B17: (0.0393, 0.0534] | C17: 0.0402 | D17: 0.0511 | E17: 0.4353682 | F17: 0.18101205 | G17: 4
A18: Decile | B18: (0.0534, 0.0819] | C18: 0.0569 | D18: 0.0812 | E18: 0.30069488 | F18: 0.1677996 | G18: 4
A19: Decile | B19: (0.0819, 0.104] | C19: 0.0836 | D19: 0.1033 | E19: 0.57700963 | F19: 0.16190427 | G19: 4
A20: Decile | B20: (0.104, 0.122] | C20: 0.1074 | D20: 0.1122 | E20: 0.70453175 | F20: 0.19007584 | G20: 4 | H20: ← peak ROE
A21: Decile | B21: (0.122, 0.376] | C21: 0.2103 | D21: 0.3758 | E21: 0.30686615 | F21: 0.13815263 | G21: 4
A23: Finding: average ROE peaks at 70% in the D/E 0.11–0.11 decile, then falls to 31% in the top decile (D/E 0.21–0.38) — an inverted-U inside a low-leverage sector.

Sheet WACC
A1: WACC — CAPM cost of equity + clamped cost of debt
A2: yellow = assumptions to challenge · every other cell recalculates from Raw Data / Market Data
A4: Risk-free rate (10Y G-Sec) | B4: 0.07
A5: Equity risk premium (India) | B5: 0.055
A6: Kd clamp low (Rf - 2%) | B6: =B4-0.02
A7: Kd clamp high (Rf + 6%) | B7: =B4+0.06
A9: Company | B9: Beta | C9: Ke (CAPM) | D9: Debt latest | E9: Debt prior | F9: Interest | G9: Kd raw | H9: Kd used | I9: Tax (3y avg) | J9: E = MktCap | K9: V = E+D | L9: D/V | M9: WACC
A10: HUL | B10: 0.55 | C10: =$B$4+B10*$B$5 | D10: ='Raw Data'!M6 | E10: ='Raw Data'!U6 | F10: ='Raw Data'!F6 | G10: =IF((D10+E10)=0,NA(),F10/((D10+E10)/2)) | H10: =IF(ISNA(G10),$B$4+0.01,MIN(MAX(G10,$B$6),$B$7)) | I10: =AVERAGE('Raw Data'!V6,'Raw Data'!V5,'Raw Data'!V4) | J10: ='Market Data'!B2 | K10: =J10+D10 | L10: =D10/K10 | M10: =(J10/K10)*C10+(D10/K10)*H10*(1-I10)
A11: ITC | B11: 0.75 | C11: =$B$4+B11*$B$5 | D11: ='Raw Data'!M11 | E11: ='Raw Data'!U11 | F11: ='Raw Data'!F11 | G11: =IF((D11+E11)=0,NA(),F11/((D11+E11)/2)) | H11: =IF(ISNA(G11),$B$4+0.01,MIN(MAX(G11,$B$6),$B$7)) | I11: =AVERAGE('Raw Data'!V11,'Raw Data'!V10,'Raw Data'!V9) | J11: ='Market Data'!B3 | K11: =J11+D11 | L11: =D11/K11 | M11: =(J11/K11)*C11+(D11/K11)*H11*(1-I11)
A12: Dabur | B12: 0.6 | C12: =$B$4+B12*$B$5 | D12: ='Raw Data'!M16 | E12: ='Raw Data'!U16 | F12: ='Raw Data'!F16 | G12: =IF((D12+E12)=0,NA(),F12/((D12+E12)/2)) | H12: =IF(ISNA(G12),$B$4+0.01,MIN(MAX(G12,$B$6),$B$7)) | I12: =AVERAGE('Raw Data'!V16,'Raw Data'!V15,'Raw Data'!V14) | J12: ='Market Data'!B4 | K12: =J12+D12 | L12: =D12/K12 | M12: =(J12/K12)*C12+(D12/K12)*H12*(1-I12)
A13: Marico | B13: 0.55 | C13: =$B$4+B13*$B$5 | D13: ='Raw Data'!M21 | E13: ='Raw Data'!U21 | F13: ='Raw Data'!F21 | G13: =IF((D13+E13)=0,NA(),F13/((D13+E13)/2)) | H13: =IF(ISNA(G13),$B$4+0.01,MIN(MAX(G13,$B$6),$B$7)) | I13: =AVERAGE('Raw Data'!V21,'Raw Data'!V20,'Raw Data'!V19) | J13: ='Market Data'!B5 | K13: =J13+D13 | L13: =D13/K13 | M13: =(J13/K13)*C13+(D13/K13)*H13*(1-I13)
A14: Colgate | B14: 0.65 | C14: =$B$4+B14*$B$5 | D14: ='Raw Data'!M26 | E14: ='Raw Data'!U26 | F14: ='Raw Data'!F26 | G14: =IF((D14+E14)=0,NA(),F14/((D14+E14)/2)) | H14: =IF(ISNA(G14),$B$4+0.01,MIN(MAX(G14,$B$6),$B$7)) | I14: =AVERAGE('Raw Data'!V26,'Raw Data'!V25,'Raw Data'!V24) | J14: ='Market Data'!B6 | K14: =J14+D14 | L14: =D14/K14 | M14: =(J14/K14)*C14+(D14/K14)*H14*(1-I14)
A15: Nestle | B15: 0.5 | C15: =$B$4+B15*$B$5 | D15: ='Raw Data'!M31 | E15: ='Raw Data'!U31 | F15: ='Raw Data'!F31 | G15: =IF((D15+E15)=0,NA(),F15/((D15+E15)/2)) | H15: =IF(ISNA(G15),$B$4+0.01,MIN(MAX(G15,$B$6),$B$7)) | I15: =AVERAGE('Raw Data'!V31,'Raw Data'!V30,'Raw Data'!V29) | J15: ='Market Data'!B7 | K15: =J15+D15 | L15: =D15/K15 | M15: =(J15/K15)*C15+(D15/K15)*H15*(1-I15)
A16: Godrej | B16: 0.7 | C16: =$B$4+B16*$B$5 | D16: ='Raw Data'!M36 | E16: ='Raw Data'!U36 | F16: ='Raw Data'!F36 | G16: =IF((D16+E16)=0,NA(),F16/((D16+E16)/2)) | H16: =IF(ISNA(G16),$B$4+0.01,MIN(MAX(G16,$B$6),$B$7)) | I16: =AVERAGE('Raw Data'!V36,'Raw Data'!V35,'Raw Data'!V34) | J16: ='Market Data'!B8 | K16: =J16+D16 | L16: =D16/K16 | M16: =(J16/K16)*C16+(D16/K16)*H16*(1-I16)
A17: Emami | B17: 0.65 | C17: =$B$4+B17*$B$5 | D17: ='Raw Data'!M41 | E17: ='Raw Data'!U41 | F17: ='Raw Data'!F41 | G17: =IF((D17+E17)=0,NA(),F17/((D17+E17)/2)) | H17: =IF(ISNA(G17),$B$4+0.01,MIN(MAX(G17,$B$6),$B$7)) | I17: =AVERAGE('Raw Data'!V41,'Raw Data'!V40,'Raw Data'!V39) | J17: ='Market Data'!B9 | K17: =J17+D17 | L17: =D17/K17 | M17: =(J17/K17)*C17+(D17/K17)*H17*(1-I17)
A19: Book-weight WACC per firm-year (equity at book value — shows the leverage-mix effect)
B20: FY2022 | C20: FY2023 | D20: FY2024 | E20: FY2025 | F20: FY2026
A21: HUL | B21: =('Raw Data'!Y2/('Raw Data'!Y2+'Raw Data'!M2))*$C$10+('Raw Data'!M2/('Raw Data'!Y2+'Raw Data'!M2))*$H$10*(1-'Raw Data'!V2) | C21: =('Raw Data'!Y3/('Raw Data'!Y3+'Raw Data'!M3))*$C$10+('Raw Data'!M3/('Raw Data'!Y3+'Raw Data'!M3))*$H$10*(1-'Raw Data'!V3) | D21: =('Raw Data'!Y4/('Raw Data'!Y4+'Raw Data'!M4))*$C$10+('Raw Data'!M4/('Raw Data'!Y4+'Raw Data'!M4))*$H$10*(1-'Raw Data'!V4) | E21: =('Raw Data'!Y5/('Raw Data'!Y5+'Raw Data'!M5))*$C$10+('Raw Data'!M5/('Raw Data'!Y5+'Raw Data'!M5))*$H$10*(1-'Raw Data'!V5) | F21: =('Raw Data'!Y6/('Raw Data'!Y6+'Raw Data'!M6))*$C$10+('Raw Data'!M6/('Raw Data'!Y6+'Raw Data'!M6))*$H$10*(1-'Raw Data'!V6)
A22: ITC | B22: =('Raw Data'!Y7/('Raw Data'!Y7+'Raw Data'!M7))*$C$11+('Raw Data'!M7/('Raw Data'!Y7+'Raw Data'!M7))*$H$11*(1-'Raw Data'!V7) | C22: =('Raw Data'!Y8/('Raw Data'!Y8+'Raw Data'!M8))*$C$11+('Raw Data'!M8/('Raw Data'!Y8+'Raw Data'!M8))*$H$11*(1-'Raw Data'!V8) | D22: =('Raw Data'!Y9/('Raw Data'!Y9+'Raw Data'!M9))*$C$11+('Raw Data'!M9/('Raw Data'!Y9+'Raw Data'!M9))*$H$11*(1-'Raw Data'!V9) | E22: =('Raw Data'!Y10/('Raw Data'!Y10+'Raw Data'!M10))*$C$11+('Raw Data'!M10/('Raw Data'!Y10+'Raw Data'!M10))*$H$11*(1-'Raw Data'!V10) | F22: =('Raw Data'!Y11/('Raw Data'!Y11+'Raw Data'!M11))*$C$11+('Raw Data'!M11/('Raw Data'!Y11+'Raw Data'!M11))*$H$11*(1-'Raw Data'!V11)
A23: Dabur | B23: =('Raw Data'!Y12/('Raw Data'!Y12+'Raw Data'!M12))*$C$12+('Raw Data'!M12/('Raw Data'!Y12+'Raw Data'!M12))*$H$12*(1-'Raw Data'!V12) | C23: =('Raw Data'!Y13/('Raw Data'!Y13+'Raw Data'!M13))*$C$12+('Raw Data'!M13/('Raw Data'!Y13+'Raw Data'!M13))*$H$12*(1-'Raw Data'!V13) | D23: =('Raw Data'!Y14/('Raw Data'!Y14+'Raw Data'!M14))*$C$12+('Raw Data'!M14/('Raw Data'!Y14+'Raw Data'!M14))*$H$12*(1-'Raw Data'!V14) | E23: =('Raw Data'!Y15/('Raw Data'!Y15+'Raw Data'!M15))*$C$12+('Raw Data'!M15/('Raw Data'!Y15+'Raw Data'!M15))*$H$12*(1-'Raw Data'!V15) | F23: =('Raw Data'!Y16/('Raw Data'!Y16+'Raw Data'!M16))*$C$12+('Raw Data'!M16/('Raw Data'!Y16+'Raw Data'!M16))*$H$12*(1-'Raw Data'!V16)
A24: Marico | B24: =('Raw Data'!Y17/('Raw Data'!Y17+'Raw Data'!M17))*$C$13+('Raw Data'!M17/('Raw Data'!Y17+'Raw Data'!M17))*$H$13*(1-'Raw Data'!V17) | C24: =('Raw Data'!Y18/('Raw Data'!Y18+'Raw Data'!M18))*$C$13+('Raw Data'!M18/('Raw Data'!Y18+'Raw Data'!M18))*$H$13*(1-'Raw Data'!V18) | D24: =('Raw Data'!Y19/('Raw Data'!Y19+'Raw Data'!M19))*$C$13+('Raw Data'!M19/('Raw Data'!Y19+'Raw Data'!M19))*$H$13*(1-'Raw Data'!V19) | E24: =('Raw Data'!Y20/('Raw Data'!Y20+'Raw Data'!M20))*$C$13+('Raw Data'!M20/('Raw Data'!Y20+'Raw Data'!M20))*$H$13*(1-'Raw Data'!V20) | F24: =('Raw Data'!Y21/('Raw Data'!Y21+'Raw Data'!M21))*$C$13+('Raw Data'!M21/('Raw Data'!Y21+'Raw Data'!M21))*$H$13*(1-'Raw Data'!V21)
A25: Colgate | B25: =('Raw Data'!Y22/('Raw Data'!Y22+'Raw Data'!M22))*$C$14+('Raw Data'!M22/('Raw Data'!Y22+'Raw Data'!M22))*$H$14*(1-'Raw Data'!V22) | C25: =('Raw Data'!Y23/('Raw Data'!Y23+'Raw Data'!M23))*$C$14+('Raw Data'!M23/('Raw Data'!Y23+'Raw Data'!M23))*$H$14*(1-'Raw Data'!V23) | D25: =('Raw Data'!Y24/('Raw Data'!Y24+'Raw Data'!M24))*$C$14+('Raw Data'!M24/('Raw Data'!Y24+'Raw Data'!M24))*$H$14*(1-'Raw Data'!V24) | E25: =('Raw Data'!Y25/('Raw Data'!Y25+'Raw Data'!M25))*$C$14+('Raw Data'!M25/('Raw Data'!Y25+'Raw Data'!M25))*$H$14*(1-'Raw Data'!V25) | F25: =('Raw Data'!Y26/('Raw Data'!Y26+'Raw Data'!M26))*$C$14+('Raw Data'!M26/('Raw Data'!Y26+'Raw Data'!M26))*$H$14*(1-'Raw Data'!V26)
A26: Nestle | B26: =('Raw Data'!Y27/('Raw Data'!Y27+'Raw Data'!M27))*$C$15+('Raw Data'!M27/('Raw Data'!Y27+'Raw Data'!M27))*$H$15*(1-'Raw Data'!V27) | C26: =('Raw Data'!Y28/('Raw Data'!Y28+'Raw Data'!M28))*$C$15+('Raw Data'!M28/('Raw Data'!Y28+'Raw Data'!M28))*$H$15*(1-'Raw Data'!V28) | D26: =('Raw Data'!Y29/('Raw Data'!Y29+'Raw Data'!M29))*$C$15+('Raw Data'!M29/('Raw Data'!Y29+'Raw Data'!M29))*$H$15*(1-'Raw Data'!V29) | E26: =('Raw Data'!Y30/('Raw Data'!Y30+'Raw Data'!M30))*$C$15+('Raw Data'!M30/('Raw Data'!Y30+'Raw Data'!M30))*$H$15*(1-'Raw Data'!V30) | F26: =('Raw Data'!Y31/('Raw Data'!Y31+'Raw Data'!M31))*$C$15+('Raw Data'!M31/('Raw Data'!Y31+'Raw Data'!M31))*$H$15*(1-'Raw Data'!V31)
A27: Godrej | B27: =('Raw Data'!Y32/('Raw Data'!Y32+'Raw Data'!M32))*$C$16+('Raw Data'!M32/('Raw Data'!Y32+'Raw Data'!M32))*$H$16*(1-'Raw Data'!V32) | C27: =('Raw Data'!Y33/('Raw Data'!Y33+'Raw Data'!M33))*$C$16+('Raw Data'!M33/('Raw Data'!Y33+'Raw Data'!M33))*$H$16*(1-'Raw Data'!V33) | D27: =('Raw Data'!Y34/('Raw Data'!Y34+'Raw Data'!M34))*$C$16+('Raw Data'!M34/('Raw Data'!Y34+'Raw Data'!M34))*$H$16*(1-'Raw Data'!V34) | E27: =('Raw Data'!Y35/('Raw Data'!Y35+'Raw Data'!M35))*$C$16+('Raw Data'!M35/('Raw Data'!Y35+'Raw Data'!M35))*$H$16*(1-'Raw Data'!V35) | F27: =('Raw Data'!Y36/('Raw Data'!Y36+'Raw Data'!M36))*$C$16+('Raw Data'!M36/('Raw Data'!Y36+'Raw Data'!M36))*$H$16*(1-'Raw Data'!V36)
A28: Emami | B28: =('Raw Data'!Y37/('Raw Data'!Y37+'Raw Data'!M37))*$C$17+('Raw Data'!M37/('Raw Data'!Y37+'Raw Data'!M37))*$H$17*(1-'Raw Data'!V37) | C28: =('Raw Data'!Y38/('Raw Data'!Y38+'Raw Data'!M38))*$C$17+('Raw Data'!M38/('Raw Data'!Y38+'Raw Data'!M38))*$H$17*(1-'Raw Data'!V38) | D28: =('Raw Data'!Y39/('Raw Data'!Y39+'Raw Data'!M39))*$C$17+('Raw Data'!M39/('Raw Data'!Y39+'Raw Data'!M39))*$H$17*(1-'Raw Data'!V39) | E28: =('Raw Data'!Y40/('Raw Data'!Y40+'Raw Data'!M40))*$C$17+('Raw Data'!M40/('Raw Data'!Y40+'Raw Data'!M40))*$H$17*(1-'Raw Data'!V40) | F28: =('Raw Data'!Y41/('Raw Data'!Y41+'Raw Data'!M41))*$C$17+('Raw Data'!M41/('Raw Data'!Y41+'Raw Data'!M41))*$H$17*(1-'Raw Data'!V41)
A30: Main table: market-value equity weights (feeds the DCF). Matrix: book weights per year — more debt in the mix lowers book WACC via the tax shield, until risk reprices Ke/Kd (not modelled by CAPM with a constant beta).

Sheet Correlation Matrix
A1: Ratio correlation matrix (Pearson, 40 firm-years)
A2: computed in python — correlation_matrix.py · heatmap: red −1 → white 0 → green +1
B4: ROE | C4: ROA | D4: NetMargin | E4: EBITMargin | F4: AssetTurnover | G4: EquityMultiplier | H4: DebtToEquity | I4: DebtRatio | J4: InterestCoverage | K4: CurrentRatio
A5: ROE | B5: 1 | C5: 0.78 | D5: 0.005 | E5: 0.039 | F5: 0.902 | G5: 0.846 | H5: 0.062 | I5: -0.175 | J5: 0.034 | K5: -0.133
A6: ROA | B6: 0.78 | C6: 1 | D6: 0.457 | E6: 0.429 | F6: 0.757 | G6: 0.343 | H6: -0.268 | I6: -0.39 | J6: 0.454 | K6: 0.366
A7: NetMargin | B7: 0.005 | C7: 0.457 | D7: 1 | E7: 0.932 | F7: -0.202 | G7: -0.347 | H7: -0.443 | I7: -0.42 | J7: 0.868 | K7: 0.451
A8: EBITMargin | B8: 0.039 | C8: 0.429 | D8: 0.932 | E8: 1 | F8: -0.187 | G8: -0.274 | H8: -0.352 | I8: -0.341 | J8: 0.862 | K8: 0.358
A9: AssetTurnover | B9: 0.902 | C9: 0.757 | D9: -0.202 | E9: -0.187 | F9: 1 | G9: 0.716 | H9: 0.021 | I9: -0.165 | J9: -0.136 | K9: 0.038
A10: EquityMultiplier | B10: 0.846 | C10: 0.343 | D10: -0.347 | E10: -0.274 | F10: 0.716 | G10: 1 | H10: 0.361 | I10: 0.098 | J10: -0.331 | K10: -0.522
A11: DebtToEquity | B11: 0.062 | C11: -0.268 | D11: -0.443 | E11: -0.352 | F11: 0.021 | G11: 0.361 | H11: 1 | I11: 0.945 | J11: -0.458 | K11: -0.432
A12: DebtRatio | B12: -0.175 | C12: -0.39 | D12: -0.42 | E12: -0.341 | F12: -0.165 | G12: 0.098 | H12: 0.945 | I12: 1 | J12: -0.433 | K12: -0.311
A13: InterestCoverage | B13: 0.034 | C13: 0.454 | D13: 0.868 | E13: 0.862 | F13: -0.136 | G13: -0.331 | H13: -0.458 | I13: -0.433 | J13: 1 | K13: 0.492
A14: CurrentRatio | B14: -0.133 | C14: 0.366 | D14: 0.451 | E14: 0.358 | F14: 0.038 | G14: -0.522 | H14: -0.432 | I14: -0.311 | J14: 0.492 | K14: 1
A16: Multicollinearity shortlist (|r| > 0.8) — kept out of one regression together:
A17: ROE × AssetTurnover r = +0.90
A18: ROE × EquityMultiplier r = +0.85
A19: NetMargin × EBITMargin r = +0.93
A20: NetMargin × InterestCoverage r = +0.87
A21: EBITMargin × InterestCoverage r = +0.86
A22: DebtToEquity × DebtRatio r = +0.95
A24: Regression uses D/E + NetMargin + log(assets) — none of these pairs.

Sheet Regression Analysis
A1: OLS — ROE ~ DebtToEquity + NetMargin + log(TotalAssets)
A2: pooled panel, 40 firm-years · computed in python (ols_regression.py) · significance flag is a live formula
A4: Variable | B4: Coefficient | C4: StdErr | D4: p-value | E4: CI low | F4: CI high | G4: p (cluster) | H4: Sig (p<0.05) | J4: Actual vs fitted (python residuals file)
A5: Intercept | B5: 0.9795 | C5: 0.3742 | D5: 0.0129 | E5: 0.2205 | F5: 1.7384 | G5: 0.0728 | H5: =IF(D5<0.05,"✓","·") | J5: Company | K5: Year | L5: ROE | M5: Fitted
A6: DebtToEquity | B6: 0.2754 | C6: 0.5954 | D6: 0.6465 | E6: -0.9322 | F6: 1.4829 | G6: 0.7291 | H6: =IF(D6<0.05,"✓","·") | J6: HUL | K6: FY2022 | L6: 0.1808 | M6: 0.2462
A7: NetMargin | B7: 0.4653 | C7: 0.7295 | D7: 0.5276 | E7: -1.0142 | F7: 1.9447 | G7: 0.5819 | H7: =IF(D7<0.05,"✓","·") | J7: HUL | K7: FY2023 | L7: 0.1984 | M7: 0.2425
A8: log_assets | B8: -0.0734 | C8: 0.0387 | D8: 0.0661 | E8: -0.152 | F8: 0.0052 | G8: 0.1695 | H8: =IF(D8<0.05,"✓","·") | J8: HUL | K8: FY2024 | L8: 0.1984 | M8: 0.2385
J9: HUL | K9: FY2025 | L9: 0.2165 | M9: 0.2437
A10: Model summary | J10: HUL | K10: FY2026 | L10: 0.3134 | M10: 0.2756
A11: R-squared | B11: 0.0954 | J11: ITC | K11: FY2022 | L11: 0.2452 | M11: 0.2809
A12: Adj R-squared | B12: 0.02 | J12: ITC | K12: FY2023 | L12: 0.2774 | M12: 0.2819
A13: F-statistic | B13: 1.265 | J13: ITC | K13: FY2024 | L13: 0.2827 | M13: 0.297
A14: F p-value | B14: 0.301 | J14: ITC | K14: FY2025 | L14: 0.5184 | M14: 0.3838
A15: Observations | B15: 40 | J15: ITC | K15: FY2026 | L15: 0.2901 | M15: 0.2824
A16: DoF residual | B16: 36 | J16: Dabur | K16: FY2022 | L16: 0.2444 | M16: 0.4221
J17: Dabur | K17: FY2023 | L17: 0.2184 | M17: 0.4086
A18: Plain-English read | J18: Dabur | K18: FY2024 | L18: 0.2182 | M18: 0.4071
A19: R² = 0.10: the three variables explain ~10% of ROE variation — LOW, and that is the finding, not a failure: | J19: Dabur | K19: FY2025 | L19: 0.189 | M19: 0.3822
A20: in this universe leverage barely varies (median D/E ≈ 0.04), so it cannot statistically separate high-ROE firms from low-ROE firms. | J20: Dabur | K20: FY2026 | L20: 0.1981 | M20: 0.3875
A21: The correlation sheet shows what does: AssetTurnover (r ≈ 0.90) and EquityMultiplier (r ≈ 0.85) — FMCG ROE is turnover- and float-driven. | J21: Marico | K21: FY2022 | L21: 0.3814 | M21: 0.452
A22: No coefficient survives firm-clustered errors at 5% — with 8 firms, pooled firm-years are not 40 independent observations. | J22: Marico | K22: FY2023 | L22: 0.3206 | M22: 0.4386
A23: D/E's coefficient is positive but insignificant — consistent with the threshold sheet: mild leverage coincides with higher ROE, more does not. | J23: Marico | K23: FY2024 | L23: 0.2997 | M23: 0.4438
J24: Marico | K24: FY2025 | L24: 0.3235 | M24: 0.4505
J25: Marico | K25: FY2026 | L25: 0.3342 | M25: 0.4277
J26: Colgate | K26: FY2022 | L26: 0.6217 | M26: 0.5055
J27: Colgate | K27: FY2023 | L27: 0.6101 | M27: 0.4988
J28: Colgate | K28: FY2024 | L28: 0.7065 | M28: 0.5059
J29: Colgate | K29: FY2025 | L29: 0.8636 | M29: 0.5119
J30: Colgate | K30: FY2026 | L30: 0.8365 | M30: 0.4925
J31: Nestle | K31: FY2022 | L31: 0.9723 | M31: 0.4073
J32: Nestle | K32: FY2023 | L32: 1.2196 | M32: 0.4144
J33: Nestle | K33: FY2024 | L33: 1.1775 | M33: 0.4029
J34: Nestle | K34: FY2025 | L34: 0.805 | M34: 0.4422
J35: Nestle | K35: FY2026 | L35: 0.6677 | M35: 0.3762
... J45: Emami | K45: FY2026 | L45: 0.2668 | M45: 0.5122

Sheet DCF - FCFF
A1: DCF - FCFF — 5-year projection, Gordon terminal value
A2: yellow = growth assumptions · flows/rates are formulas into Raw Data / WACC — nothing hardcoded
A4: Terminal growth g | B4: 0.04
A5: Forecast growth floor | B5: 0.03
A6: Forecast growth cap | B6: 0.15
A8: Historical FCFF per FY (formulas)
B9: FY2022 | C9: FY2023 | D9: FY2024 | E9: FY2025 | F9: FY2026
A10: HUL | B10: ='Raw Data'!S2+'Raw Data'!F2*(1-'Raw Data'!V2)-'Raw Data'!AB2 | C10: ='Raw Data'!S3+'Raw Data'!F3*(1-'Raw Data'!V3)-'Raw Data'!AB3 | D10: ='Raw Data'!S4+'Raw Data'!F4*(1-'Raw Data'!V4)-'Raw Data'!AB4 | E10: ='Raw Data'!S5+'Raw Data'!F5*(1-'Raw Data'!V5)-'Raw Data'!AB5 | F10: ='Raw Data'!S6+'Raw Data'!F6*(1-'Raw Data'!V6)-'Raw Data'!AB6
A11: ITC | B11: ='Raw Data'!S7+'Raw Data'!F7*(1-'Raw Data'!V7)-'Raw Data'!AB7 | C11: ='Raw Data'!S8+'Raw Data'!F8*(1-'Raw Data'!V8)-'Raw Data'!AB8 | D11: ='Raw Data'!S9+'Raw Data'!F9*(1-'Raw Data'!V9)-'Raw Data'!AB9 | E11: ='Raw Data'!S10+'Raw Data'!F10*(1-'Raw Data'!V10)-'Raw Data'!AB10 | F11: ='Raw Data'!S11+'Raw Data'!F11*(1-'Raw Data'!V11)-'Raw Data'!AB11
A12: Dabur | B12: ='Raw Data'!S12+'Raw Data'!F12*(1-'Raw Data'!V12)-'Raw Data'!AB12 | C12: ='Raw Data'!S13+'Raw Data'!F13*(1-'Raw Data'!V13)-'Raw Data'!AB13 | D12: ='Raw Data'!S14+'Raw Data'!F14*(1-'Raw Data'!V14)-'Raw Data'!AB14 | E12: ='Raw Data'!S15+'Raw Data'!F15*(1-'Raw Data'!V15)-'Raw Data'!AB15 | F12: ='Raw Data'!S16+'Raw Data'!F16*(1-'Raw Data'!V16)-'Raw Data'!AB16
A13: Marico | B13: ='Raw Data'!S17+'Raw Data'!F17*(1-'Raw Data'!V17)-'Raw Data'!AB17 | C13: ='Raw Data'!S18+'Raw Data'!F18*(1-'Raw Data'!V18)-'Raw Data'!AB18 | D13: ='Raw Data'!S19+'Raw Data'!F19*(1-'Raw Data'!V19)-'Raw Data'!AB19 | E13: ='Raw Data'!S20+'Raw Data'!F20*(1-'Raw Data'!V20)-'Raw Data'!AB20 | F13: ='Raw Data'!S21+'Raw Data'!F21*(1-'Raw Data'!V21)-'Raw Data'!AB21
A14: Colgate | B14: ='Raw Data'!S22+'Raw Data'!F22*(1-'Raw Data'!V22)-'Raw Data'!AB22 | C14: ='Raw Data'!S23+'Raw Data'!F23*(1-'Raw Data'!V23)-'Raw Data'!AB23 | D14: ='Raw Data'!S24+'Raw Data'!F24*(1-'Raw Data'!V24)-'Raw Data'!AB24 | E14: ='Raw Data'!S25+'Raw Data'!F25*(1-'Raw Data'!V25)-'Raw Data'!AB25 | F14: ='Raw Data'!S26+'Raw Data'!F26*(1-'Raw Data'!V26)-'Raw Data'!AB26
A15: Nestle | B15: ='Raw Data'!S27+'Raw Data'!F27*(1-'Raw Data'!V27)-'Raw Data'!AB27 | C15: ='Raw Data'!S28+'Raw Data'!F28*(1-'Raw Data'!V28)-'Raw Data'!AB28 | D15: ='Raw Data'!S29+'Raw Data'!F29*(1-'Raw Data'!V29)-'Raw Data'!AB29 | E15: ='Raw Data'!S30+'Raw Data'!F30*(1-'Raw Data'!V30)-'Raw Data'!AB30 | F15: ='Raw Data'!S31+'Raw Data'!F31*(1-'Raw Data'!V31)-'Raw Data'!AB31
A16: Godrej | B16: ='Raw Data'!S32+'Raw Data'!F32*(1-'Raw Data'!V32)-'Raw Data'!AB32 | C16: ='Raw Data'!S33+'Raw Data'!F33*(1-'Raw Data'!V33)-'Raw Data'!AB33 | D16: ='Raw Data'!S34+'Raw Data'!F34*(1-'Raw Data'!V34)-'Raw Data'!AB34 | E16: ='Raw Data'!S35+'Raw Data'!F35*(1-'Raw Data'!V35)-'Raw Data'!AB35 | F16: ='Raw Data'!S36+'Raw Data'!F36*(1-'Raw Data'!V36)-'Raw Data'!AB36
A17: Emami | B17: ='Raw Data'!S37+'Raw Data'!F37*(1-'Raw Data'!V37)-'Raw Data'!AB37 | C17: ='Raw Data'!S38+'Raw Data'!F38*(1-'Raw Data'!V38)-'Raw Data'!AB38 | D17: ='Raw Data'!S39+'Raw Data'!F39*(1-'Raw Data'!V39)-'Raw Data'!AB39 | E17: ='Raw Data'!S40+'Raw Data'!F40*(1-'Raw Data'!V40)-'Raw Data'!AB40 | F17: ='Raw Data'!S41+'Raw Data'!F41*(1-'Raw Data'!V41)-'Raw Data'!AB41
A20: Company | B20: Base FCFF | C20: Rev CAGR raw | D20: g used | E20: Rate | F20: Y1 | G20: Y2 | H20: Y3 | I20: Y4 | J20: Y5 | K20: PV(Y1..Y5) | L20: TV | M20: PV(TV) | N20: PV total | O20: Net debt | P20: Equity value | Q20: Shares (Cr) | R20: Value/share | S20: Mkt price | T20: Upside
A21: HUL | B21: =AVERAGE(D10:F10) | C21: =('Raw Data'!C6/'Raw Data'!C2)^(1/4)-1 | D21: =MIN(MAX(C21,$B$5),$B$6) | E21: ='WACC'!M10 | F21: =B21*(1+D21)^1 | G21: =B21*(1+D21)^2 | H21: =B21*(1+D21)^3 | I21: =B21*(1+D21)^4 | J21: =B21*(1+D21)^5 | K21: =SUMPRODUCT(F21:J21/POWER(1+E21,{1,2,3,4,5})) | L21: =IF(E21-$B$4<0.01,NA(),J21*(1+$B$4)/(E21-$B$4)) | M21: =L21/POWER(1+E21,5) | N21: =K21+M21 | O21: ='Raw Data'!M6-'Raw Data'!O6 | P21: =N21-O21 | Q21: ='Raw Data'!AD6 | R21: =P21/Q21 | S21: ='Market Data'!C2 | T21: =R21/S21-1
A22: ITC | B22: =AVERAGE(D11:F11) | C22: =('Raw Data'!C11/'Raw Data'!C7)^(1/4)-1 | D22: =MIN(MAX(C22,$B$5),$B$6) | E22: ='WACC'!M11 | F22: =B22*(1+D22)^1 | G22: =B22*(1+D22)^2 | H22: =B22*(1+D22)^3 | I22: =B22*(1+D22)^4 | J22: =B22*(1+D22)^5 | K22: =SUMPRODUCT(F22:J22/POWER(1+E22,{1,2,3,4,5})) | L22: =IF(E22-$B$4<0.01,NA(),J22*(1+$B$4)/(E22-$B$4)) | M22: =L22/POWER(1+E22,5) | N22: =K22+M22 | O22: ='Raw Data'!M11-'Raw Data'!O11 | P22: =N22-O22 | Q22: ='Raw Data'!AD11 | R22: =P22/Q22 | S22: ='Market Data'!C3 | T22: =R22/S22-1
A23: Dabur | B23: =AVERAGE(D12:F12) | C23: =('Raw Data'!C16/'Raw Data'!C12)^(1/4)-1 | D23: =MIN(MAX(C23,$B$5),$B$6) | E23: ='WACC'!M12 | F23: =B23*(1+D23)^1 | G23: =B23*(1+D23)^2 | H23: =B23*(1+D23)^3 | I23: =B23*(1+D23)^4 | J23: =B23*(1+D23)^5 | K23: =SUMPRODUCT(F23:J23/POWER(1+E23,{1,2,3,4,5})) | L23: =IF(E23-$B$4<0.01,NA(),J23*(1+$B$4)/(E23-$B$4)) | M23: =L23/POWER(1+E23,5) | N23: =K23+M23 | O23: ='Raw Data'!M16-'Raw Data'!O16 | P23: =N23-O23 | Q23: ='Raw Data'!AD16 | R23: =P23/Q23 | S23: ='Market Data'!C4 | T23: =R23/S23-1
A24: Marico | B24: =AVERAGE(D13:F13) | C24: =('Raw Data'!C21/'Raw Data'!C17)^(1/4)-1 | D24: =MIN(MAX(C24,$B$5),$B$6) | E24: ='WACC'!M13 | F24: =B24*(1+D24)^1 | G24: =B24*(1+D24)^2 | H24: =B24*(1+D24)^3 | I24: =B24*(1+D24)^4 | J24: =B24*(1+D24)^5 | K24: =SUMPRODUCT(F24:J24/POWER(1+E24,{1,2,3,4,5})) | L24: =IF(E24-$B$4<0.01,NA(),J24*(1+$B$4)/(E24-$B$4)) | M24: =L24/POWER(1+E24,5) | N24: =K24+M24 | O24: ='Raw Data'!M21-'Raw Data'!O21 | P24: =N24-O24 | Q24: ='Raw Data'!AD21 | R24: =P24/Q24 | S24: ='Market Data'!C5 | T24: =R24/S24-1
A25: Colgate | B25: =AVERAGE(D14:F14) | C25: =('Raw Data'!C26/'Raw Data'!C22)^(1/4)-1 | D25: =MIN(MAX(C25,$B$5),$B$6) | E25: ='WACC'!M14 | F25: =B25*(1+D25)^1 | G25: =B25*(1+D25)^2 | H25: =B25*(1+D25)^3 | I25: =B25*(1+D25)^4 | J25: =B25*(1+D25)^5 | K25: =SUMPRODUCT(F25:J25/POWER(1+E25,{1,2,3,4,5})) | L25: =IF(E25-$B$4<0.01,NA(),J25*(1+$B$4)/(E25-$B$4)) | M25: =L25/POWER(1+E25,5) | N25: =K25+M25 | O25: ='Raw Data'!M26-'Raw Data'!O26 | P25: =N25-O25 | Q25: ='Raw Data'!AD26 | R25: =P25/Q25 | S25: ='Market Data'!C6 | T25: =R25/S25-1
A26: Nestle | B26: =AVERAGE(D15:F15) | C26: =('Raw Data'!C31/'Raw Data'!C27)^(1/4)-1 | D26: =MIN(MAX(C26,$B$5),$B$6) | E26: ='WACC'!M15 | F26: =B26*(1+D26)^1 | G26: =B26*(1+D26)^2 | H26: =B26*(1+D26)^3 | I26: =B26*(1+D26)^4 | J26: =B26*(1+D26)^5 | K26: =SUMPRODUCT(F26:J26/POWER(1+E26,{1,2,3,4,5})) | L26: =IF(E26-$B$4<0.01,NA(),J26*(1+$B$4)/(E26-$B$4)) | M26: =L26/POWER(1+E26,5) | N26: =K26+M26 | O26: ='Raw Data'!M31-'Raw Data'!O31 | P26: =N26-O26 | Q26: ='Raw Data'!AD31 | R26: =P26/Q26 | S26: ='Market Data'!C7 | T26: =R26/S26-1
A27: Godrej | B27: =AVERAGE(D16:F16) | C27: =('Raw Data'!C36/'Raw Data'!C32)^(1/4)-1 | D27: =MIN(MAX(C27,$B$5),$B$6) | E27: ='WACC'!M16 | F27: =B27*(1+D27)^1 | G27: =B27*(1+D27)^2 | H27: =B27*(1+D27)^3 | I27: =B27*(1+D27)^4 | J27: =B27*(1+D27)^5 | K27: =SUMPRODUCT(F27:J27/POWER(1+E27,{1,2,3,4,5})) | L27: =IF(E27-$B$4<0.01,NA(),J27*(1+$B$4)/(E27-$B$4)) | M27: =L27/POWER(1+E27,5) | N27: =K27+M27 | O27: ='Raw Data'!M36-'Raw Data'!O36 | P27: =N27-O27 | Q27: ='Raw Data'!AD36 | R27: =P27/Q27 | S27: ='Market Data'!C8 | T27: =R27/S27-1
A28: Emami | B28: =AVERAGE(D17:F17) | C28: =('Raw Data'!C41/'Raw Data'!C37)^(1/4)-1 | D28: =MIN(MAX(C28,$B$5),$B$6) | E28: ='WACC'!M17 | F28: =B28*(1+D28)^1 | G28: =B28*(1+D28)^2 | H28: =B28*(1+D28)^3 | I28: =B28*(1+D28)^4 | J28: =B28*(1+D28)^5 | K28: =SUMPRODUCT(F28:J28/POWER(1+E28,{1,2,3,4,5})) | L28: =IF(E28-$B$4<0.01,NA(),J28*(1+$B$4)/(E28-$B$4)) | M28: =L28/POWER(1+E28,5) | N28: =K28+M28 | O28: ='Raw Data'!M41-'Raw Data'!O41 | P28: =N28-O28 | Q28: ='Raw Data'!AD41 | R28: =P28/Q28 | S28: ='Market Data'!C9 | T28: =R28/S28-1
A30: FCFF = CFO + Interest×(1−tax) − Capex (CFO already nets ΔWC and tax). Discounted at WACC; TV = Gordon at terminal g; EV − NetDebt = equity.

Sheet DCF - FCFE
A1: DCF - FCFE — 5-year projection, Gordon terminal value
A2: yellow = growth assumptions · flows/rates are formulas into Raw Data / WACC — nothing hardcoded
A4: Terminal growth g | B4: 0.04
A5: Forecast growth floor | B5: 0.03
A6: Forecast growth cap | B6: 0.15
A8: Historical FCFE per FY (formulas)
B9: FY2022 | C9: FY2023 | D9: FY2024 | E9: FY2025 | F9: FY2026
A10: HUL | B10: ='Raw Data'!S2-'Raw Data'!AB2+'Raw Data'!AC2 | C10: ='Raw Data'!S3-'Raw Data'!AB3+'Raw Data'!AC3 | D10: ='Raw Data'!S4-'Raw Data'!AB4+'Raw Data'!AC4 | E10: ='Raw Data'!S5-'Raw Data'!AB5+'Raw Data'!AC5 | F10: ='Raw Data'!S6-'Raw Data'!AB6+'Raw Data'!AC6
A11: ITC | B11: ='Raw Data'!S7-'Raw Data'!AB7+'Raw Data'!AC7 | C11: ='Raw Data'!S8-'Raw Data'!AB8+'Raw Data'!AC8 | D11: ='Raw Data'!S9-'Raw Data'!AB9+'Raw Data'!AC9 | E11: ='Raw Data'!S10-'Raw Data'!AB10+'Raw Data'!AC10 | F11: ='Raw Data'!S11-'Raw Data'!AB11+'Raw Data'!AC11
A12: Dabur | B12: ='Raw Data'!S12-'Raw Data'!AB12+'Raw Data'!AC12 | C12: ='Raw Data'!S13-'Raw Data'!AB13+'Raw Data'!AC13 | D12: ='Raw Data'!S14-'Raw Data'!AB14+'Raw Data'!AC14 | E12: ='Raw Data'!S15-'Raw Data'!AB15+'Raw Data'!AC15 | F12: ='Raw Data'!S16-'Raw Data'!AB16+'Raw Data'!AC16
A13: Marico | B13: ='Raw Data'!S17-'Raw Data'!AB17+'Raw Data'!AC17 | C13: ='Raw Data'!S18-'Raw Data'!AB18+'Raw Data'!AC18 | D13: ='Raw Data'!S19-'Raw Data'!AB19+'Raw Data'!AC19 | E13: ='Raw Data'!S20-'Raw Data'!AB20+'Raw Data'!AC20 | F13: ='Raw Data'!S21-'Raw Data'!AB21+'Raw Data'!AC21
A14: Colgate | B14: ='Raw Data'!S22-'Raw Data'!AB22+'Raw Data'!AC22 | C14: ='Raw Data'!S23-'Raw Data'!AB23+'Raw Data'!AC23 | D14: ='Raw Data'!S24-'Raw Data'!AB24+'Raw Data'!AC24 | E14: ='Raw Data'!S25-'Raw Data'!AB25+'Raw Data'!AC25 | F14: ='Raw Data'!S26-'Raw Data'!AB26+'Raw Data'!AC26
A15: Nestle | B15: ='Raw Data'!S27-'Raw Data'!AB27+'Raw Data'!AC27 | C15: ='Raw Data'!S28-'Raw Data'!AB28+'Raw Data'!AC28 | D15: ='Raw Data'!S29-'Raw Data'!AB29+'Raw Data'!AC29 | E15: ='Raw Data'!S30-'Raw Data'!AB30+'Raw Data'!AC30 | F15: ='Raw Data'!S31-'Raw Data'!AB31+'Raw Data'!AC31
A16: Godrej | B16: ='Raw Data'!S32-'Raw Data'!AB32+'Raw Data'!AC32 | C16: ='Raw Data'!S33-'Raw Data'!AB33+'Raw Data'!AC33 | D16: ='Raw Data'!S34-'Raw Data'!AB34+'Raw Data'!AC34 | E16: ='Raw Data'!S35-'Raw Data'!AB35+'Raw Data'!AC35 | F16: ='Raw Data'!S36-'Raw Data'!AB36+'Raw Data'!AC36
A17: Emami | B17: ='Raw Data'!S37-'Raw Data'!AB37+'Raw Data'!AC37 | C17: ='Raw Data'!S38-'Raw Data'!AB38+'Raw Data'!AC38 | D17: ='Raw Data'!S39-'Raw Data'!AB39+'Raw Data'!AC39 | E17: ='Raw Data'!S40-'Raw Data'!AB40+'Raw Data'!AC40 | F17: ='Raw Data'!S41-'Raw Data'!AB41+'Raw Data'!AC41
A20: Company | B20: Base FCFE | C20: Rev CAGR raw | D20: g used | E20: Rate | F20: Y1 | G20: Y2 | H20: Y3 | I20: Y4 | J20: Y5 | K20: PV(Y1..Y5) | L20: TV | M20: PV(TV) | N20: PV total | O20: Net debt | P20: Equity value | Q20: Shares (Cr) | R20: Value/share | S20: Mkt price | T20: Upside
A21: HUL | B21: =AVERAGE(D10:F10) | C21: =('Raw Data'!C6/'Raw Data'!C2)^(1/4)-1 | D21: =MIN(MAX(C21,$B$5),$B$6) | E21: ='WACC'!C10 | F21: =B21*(1+D21)^1 | G21: =B21*(1+D21)^2 | H21: =B21*(1+D21)^3 | I21: =B21*(1+D21)^4 | J21: =B21*(1+D21)^5 | K21: =SUMPRODUCT(F21:J21/POWER(1+E21,{1,2,3,4,5})) | L21: =IF(E21-$B$4<0.01,NA(),J21*(1+$B$4)/(E21-$B$4)) | M21: =L21/POWER(1+E21,5) | N21: =K21+M21 | O21: n/a (equity-direct) | P21: =N21 | Q21: ='Raw Data'!AD6 | R21: =P21/Q21 | S21: ='Market Data'!C2 | T21: =R21/S21-1
A22: ITC | B22: =AVERAGE(D11:F11) | C22: =('Raw Data'!C11/'Raw Data'!C7)^(1/4)-1 | D22: =MIN(MAX(C22,$B$5),$B$6) | E22: ='WACC'!C11 | F22: =B22*(1+D22)^1 | G22: =B22*(1+D22)^2 | H22: =B22*(1+D22)^3 | I22: =B22*(1+D22)^4 | J22: =B22*(1+D22)^5 | K22: =SUMPRODUCT(F22:J22/POWER(1+E22,{1,2,3,4,5})) | L22: =IF(E22-$B$4<0.01,NA(),J22*(1+$B$4)/(E22-$B$4)) | M22: =L22/POWER(1+E22,5) | N22: =K22+M22 | O22: n/a (equity-direct) | P22: =N22 | Q22: ='Raw Data'!AD11 | R22: =P22/Q22 | S22: ='Market Data'!C3 | T22: =R22/S22-1
A23: Dabur | B23: =AVERAGE(D12:F12) | C23: =('Raw Data'!C16/'Raw Data'!C12)^(1/4)-1 | D23: =MIN(MAX(C23,$B$5),$B$6) | E23: ='WACC'!C12 | F23: =B23*(1+D23)^1 | G23: =B23*(1+D23)^2 | H23: =B23*(1+D23)^3 | I23: =B23*(1+D23)^4 | J23: =B23*(1+D23)^5 | K23: =SUMPRODUCT(F23:J23/POWER(1+E23,{1,2,3,4,5})) | L23: =IF(E23-$B$4<0.01,NA(),J23*(1+$B$4)/(E23-$B$4)) | M23: =L23/POWER(1+E23,5) | N23: =K23+M23 | O23: n/a (equity-direct) | P23: =N23 | Q23: ='Raw Data'!AD16 | R23: =P23/Q23 | S23: ='Market Data'!C4 | T23: =R23/S23-1
A24: Marico | B24: =AVERAGE(D13:F13) | C24: =('Raw Data'!C21/'Raw Data'!C17)^(1/4)-1 | D24: =MIN(MAX(C24,$B$5),$B$6) | E24: ='WACC'!C13 | F24: =B24*(1+D24)^1 | G24: =B24*(1+D24)^2 | H24: =B24*(1+D24)^3 | I24: =B24*(1+D24)^4 | J24: =B24*(1+D24)^5 | K24: =SUMPRODUCT(F24:J24/POWER(1+E24,{1,2,3,4,5})) | L24: =IF(E24-$B$4<0.01,NA(),J24*(1+$B$4)/(E24-$B$4)) | M24: =L24/POWER(1+E24,5) | N24: =K24+M24 | O24: n/a (equity-direct) | P24: =N24 | Q24: ='Raw Data'!AD21 | R24: =P24/Q24 | S24: ='Market Data'!C5 | T24: =R24/S24-1
A25: Colgate | B25: =AVERAGE(D14:F14) | C25: =('Raw Data'!C26/'Raw Data'!C22)^(1/4)-1 | D25: =MIN(MAX(C25,$B$5),$B$6) | E25: ='WACC'!C14 | F25: =B25*(1+D25)^1 | G25: =B25*(1+D25)^2 | H25: =B25*(1+D25)^3 | I25: =B25*(1+D25)^4 | J25: =B25*(1+D25)^5 | K25: =SUMPRODUCT(F25:J25/POWER(1+E25,{1,2,3,4,5})) | L25: =IF(E25-$B$4<0.01,NA(),J25*(1+$B$4)/(E25-$B$4)) | M25: =L25/POWER(1+E25,5) | N25: =K25+M25 | O25: n/a (equity-direct) | P25: =N25 | Q25: ='Raw Data'!AD26 | R25: =P25/Q25 | S25: ='Market Data'!C6 | T25: =R25/S25-1
A26: Nestle | B26: =AVERAGE(D15:F15) | C26: =('Raw Data'!C31/'Raw Data'!C27)^(1/4)-1 | D26: =MIN(MAX(C26,$B$5),$B$6) | E26: ='WACC'!C15 | F26: =B26*(1+D26)^1 | G26: =B26*(1+D26)^2 | H26: =B26*(1+D26)^3 | I26: =B26*(1+D26)^4 | J26: =B26*(1+D26)^5 | K26: =SUMPRODUCT(F26:J26/POWER(1+E26,{1,2,3,4,5})) | L26: =IF(E26-$B$4<0.01,NA(),J26*(1+$B$4)/(E26-$B$4)) | M26: =L26/POWER(1+E26,5) | N26: =K26+M26 | O26: n/a (equity-direct) | P26: =N26 | Q26: ='Raw Data'!AD31 | R26: =P26/Q26 | S26: ='Market Data'!C7 | T26: =R26/S26-1
A27: Godrej | B27: =AVERAGE(D16:F16) | C27: =('Raw Data'!C36/'Raw Data'!C32)^(1/4)-1 | D27: =MIN(MAX(C27,$B$5),$B$6) | E27: ='WACC'!C16 | F27: =B27*(1+D27)^1 | G27: =B27*(1+D27)^2 | H27: =B27*(1+D27)^3 | I27: =B27*(1+D27)^4 | J27: =B27*(1+D27)^5 | K27: =SUMPRODUCT(F27:J27/POWER(1+E27,{1,2,3,4,5})) | L27: =IF(E27-$B$4<0.01,NA(),J27*(1+$B$4)/(E27-$B$4)) | M27: =L27/POWER(1+E27,5) | N27: =K27+M27 | O27: n/a (equity-direct) | P27: =N27 | Q27: ='Raw Data'!AD36 | R27: =P27/Q27 | S27: ='Market Data'!C8 | T27: =R27/S27-1
A28: Emami | B28: =AVERAGE(D17:F17) | C28: =('Raw Data'!C41/'Raw Data'!C37)^(1/4)-1 | D28: =MIN(MAX(C28,$B$5),$B$6) | E28: ='WACC'!C17 | F28: =B28*(1+D28)^1 | G28: =B28*(1+D28)^2 | H28: =B28*(1+D28)^3 | I28: =B28*(1+D28)^4 | J28: =B28*(1+D28)^5 | K28: =SUMPRODUCT(F28:J28/POWER(1+E28,{1,2,3,4,5})) | L28: =IF(E28-$B$4<0.01,NA(),J28*(1+$B$4)/(E28-$B$4)) | M28: =L28/POWER(1+E28,5) | N28: =K28+M28 | O28: n/a (equity-direct) | P28: =N28 | Q28: ='Raw Data'!AD41 | R28: =P28/Q28 | S28: ='Market Data'!C9 | T28: =R28/S28-1
A31: FCFE vs FCFF equity value — the leverage wedge
A32: Company | B32: Equity (FCFF) | C32: Equity (FCFE) | D32: Gap %
A33: HUL | B33: ='DCF - FCFF'!P21 | C33: =P21 | D33: =C33/B33-1
A34: ITC | B34: ='DCF - FCFF'!P22 | C34: =P22 | D34: =C34/B34-1
A35: Dabur | B35: ='DCF - FCFF'!P23 | C35: =P23 | D35: =C35/B35-1
A36: Marico | B36: ='DCF - FCFF'!P24 | C36: =P24 | D36: =C36/B36-1
A37: Colgate | B37: ='DCF - FCFF'!P25 | C37: =P25 | D37: =C37/B37-1
A38: Nestle | B38: ='DCF - FCFF'!P26 | C38: =P26 | D38: =C38/B38-1
A39: Godrej | B39: ='DCF - FCFF'!P27 | C39: =P27 | D39: =C39/B39-1
A40: Emami | B40: ='DCF - FCFF'!P28 | C40: =P28 | D40: =C40/B40-1
A42: FCFE = CFO − Capex + NetBorrowing, discounted at Ke — equity value directly. At near-zero debt the two methods converge; the gap widens exactly where borrowing is material (the Phase-2 leverage story).

Sheet Comps
A1: Comparable company analysis — EV/EBITDA vs sector median
A2: EV = MarketCap + TotalDebt − Cash (latest FY) · all live formulas
A4: Company | B4: MarketCap | C4: TotalDebt | D4: Cash | E4: EV | F4: EBITDA | G4: EV/EBITDA | H4: Stock P/E | I4: Sector median | J4: Implied EV | K4: Premium
A5: HUL | B5: ='Market Data'!B2 | C5: ='Raw Data'!M6 | D5: ='Raw Data'!O6 | E5: =B5+C5-D5 | F5: ='Raw Data'!X6 | G5: =E5/F5 | H5: ='Market Data'!E2 | I5: =MEDIAN($G$5:$G$12) | J5: =F5*I5 | K5: =E5/J5-1
A6: ITC | B6: ='Market Data'!B3 | C6: ='Raw Data'!M11 | D6: ='Raw Data'!O11 | E6: =B6+C6-D6 | F6: ='Raw Data'!X11 | G6: =E6/F6 | H6: ='Market Data'!E3 | I6: =MEDIAN($G$5:$G$12) | J6: =F6*I6 | K6: =E6/J6-1
A7: Dabur | B7: ='Market Data'!B4 | C7: ='Raw Data'!M16 | D7: ='Raw Data'!O16 | E7: =B7+C7-D7 | F7: ='Raw Data'!X16 | G7: =E7/F7 | H7: ='Market Data'!E4 | I7: =MEDIAN($G$5:$G$12) | J7: =F7*I7 | K7: =E7/J7-1
A8: Marico | B8: ='Market Data'!B5 | C8: ='Raw Data'!M21 | D8: ='Raw Data'!O21 | E8: =B8+C8-D8 | F8: ='Raw Data'!X21 | G8: =E8/F8 | H8: ='Market Data'!E5 | I8: =MEDIAN($G$5:$G$12) | J8: =F8*I8 | K8: =E8/J8-1
A9: Colgate | B9: ='Market Data'!B6 | C9: ='Raw Data'!M26 | D9: ='Raw Data'!O26 | E9: =B9+C9-D9 | F9: ='Raw Data'!X26 | G9: =E9/F9 | H9: ='Market Data'!E6 | I9: =MEDIAN($G$5:$G$12) | J9: =F9*I9 | K9: =E9/J9-1
A10: Nestle | B10: ='Market Data'!B7 | C10: ='Raw Data'!M31 | D10: ='Raw Data'!O31 | E10: =B10+C10-D10 | F10: ='Raw Data'!X31 | G10: =E10/F10 | H10: ='Market Data'!E7 | I10: =MEDIAN($G$5:$G$12) | J10: =F10*I10 | K10: =E10/J10-1
A11: Godrej | B11: ='Market Data'!B8 | C11: ='Raw Data'!M36 | D11: ='Raw Data'!O36 | E11: =B11+C11-D11 | F11: ='Raw Data'!X36 | G11: =E11/F11 | H11: ='Market Data'!E8 | I11: =MEDIAN($G$5:$G$12) | J11: =F11*I11 | K11: =E11/J11-1
A12: Emami | B12: ='Market Data'!B9 | C12: ='Raw Data'!M41 | D12: ='Raw Data'!O41 | E12: =B12+C12-D12 | F12: ='Raw Data'!X41 | G12: =E12/F12 | H12: ='Market Data'!E9 | I12: =MEDIAN($G$5:$G$12) | J12: =F12*I12 | K12: =E12/J12-1
A34: Green premium column = trading BELOW the implied sector-median EV (relative value); red = above. P/E from the July-2026 snapshot as a secondary multiple. Historical multiples would need historical market caps — out of scope for the snapshot dataset.

Sheet Sensitivity Analysis
A1: DCF sensitivity — value per share across WACC × terminal growth
A2: each cell re-runs the full FCFF DCF via formula · green = above market price (undervalued at that combo) · border = base case
A4: HUL | B4: ='Market Data'!$C$2 | C4: ← market price · rows: WACC · cols: terminal g
B5: 0.01 | C5: 0.015 | D5: 0.02 | E5: 0.025 | F5: 0.03 | G5: 0.035 | H5: 0.04 | I5: 0.045 | J5: 0.05
A6: ='DCF - FCFF'!$E$21-0.02 | B6: =IF($A6-B$5<0.01,NA(),('DCF - FCFF'!$B$21*SUMPRODUCT(POWER(1+'DCF - FCFF'!$D$21,{1,2,3,4,5})/POWER(1+$A6,{1,2,3,4,5}))+'DCF - FCFF'!$B$21*POWER(1+'DCF - FCFF'!$D$21,5)*(1+B$5)/($A6-B$5)/POWER(1+$A6,5)-'DCF - FCFF'!$O$21)/'DCF - FCFF'!$Q$21) | C6: =IF($A6-C$5<0.01,NA(),('DCF - FCFF'!$B$21*SUMPRODUCT(POWER(1+'DCF - FCFF'!$D$21,{1,2,3,4,5})/POWER(1+$A6,{1,2,3,4,5}))+'DCF - FCFF'!$B$21*POWER(1+'DCF - FCFF'!$D$21,5)*(1+C$5)/($A6-C$5)/POWER(1+$A6,5)-'DCF - FCFF'!$O$21)/'DCF - FCFF'!$Q$21) | D6: =IF($A6-D$5<0.01,NA(),('DCF - FCFF'!$B$21*SUMPRODUCT(POWER(1+'DCF - FCFF'!$D$21,{1,2,3,4,5})/POWER(1+$A6,{1,2,3,4,5}))+'DCF - FCFF'!$B$21*POWER(1+'DCF - FCFF'!$D$21,5)*(1+D$5)/($A6-D$5)/POWER(1+$A6,5)-'DCF - FCFF'!$O$21)/'DCF - FCFF'!$Q$21) | E6: =IF($A6-E$5<0.01,NA(),('DCF - FCFF'!$B$21*SUMPRODUCT(POWER(1+'DCF - FCFF'!$D$21,{1,2,3,4,5})/POWER(1+$A6,{1,2,3,4,5}))+'DCF - FCFF'!$B$21*POWER(1+'DCF - FCFF'!$D$21,5)*(1+E$5)/($A6-E$5)/POWER(1+$A6,5)-'DCF - FCFF'!$O$21)/'DCF - FCFF'!$Q$21) | F6: =IF($A6-F$5<0.01,NA(),('DCF - FCFF'!$B$21*SUMPRODUCT(POWER(1+'DCF - FCFF'!$D$21,{1,2,3,4,5})/POWER(1+$A6,{1,2,3,4,5}))+'DCF - FCFF'!$B$21*POWER(1+'DCF - FCFF'!$D$21,5)*(1+F$5)/($A6-F$5)/POWER(1+$A6,5)-'DCF - FCFF'!$O$21)/'DCF - FCFF'!$Q$21) | G6: =IF($A6-G$5<0.01,NA(),('DCF - FCFF'!$B$21*SUMPRODUCT(POWER(1+'DCF - FCFF'!$D$21,{1,2,3,4,5})/POWER(1+$A6,{1,2,3,4,5}))+'DCF - FCFF'!$B$21*POWER(1+'DCF - FCFF'!$D$21,5)*(1+G$5)/($A6-G$5)/POWER(1+$A6,5)-'DCF - FCFF'!$O$21)/'DCF - FCFF'!$Q$21) | H6: =IF($A6-H$5<0.01,NA(),('DCF - FCFF'!$B$21*SUMPRODUCT(POWER(1+'DCF - FCFF'!$D$21,{1,2,3,4,5})/POWER(1+$A6,{1,2,3,4,5}))+'DCF - FCFF'!$B$21*POWER(1+'DCF - FCFF'!$D$21,5)*(1+H$5)/($A6-H$5)/POWER(1+$A6,5)-'DCF - FCFF'!$O$21)/'DCF - FCFF'!$Q$21) | I6: =IF($A6-I$5<0.01,NA(),('DCF - FCFF'!$B$21*SUMPRODUCT(POWER(1+'DCF - FCFF'!$D$21,{1,2,3,4,5})/POWER(1+$A6,{1,2,3,4,5}))+'DCF - FCFF'!$B$21*POWER(1+'DCF - FCFF'!$D$21,5)*(1+I$5)/($A6-I$5)/POWER(1+$A6,5)-'DCF - FCFF'!$O$21)/'DCF - FCFF'!$Q$21) | J6: =IF($A6-J$5<0.01,NA(),('DCF - FCFF'!$B$21*SUMPRODUCT(POWER(1+'DCF - FCFF'!$D$21,{1,2,3,4,5})/POWER(1+$A6,{1,2,3,4,5}))+'DCF - FCFF'!$B$21*POWER(1+'DCF - FCFF'!$D$21,5)*(1+J$5)/($A6-J$5)/POWER(1+$A6,5)-'DCF - FCFF'!$O$21)/'DCF - FCFF'!$Q$21)
A7: ='DCF - FCFF'!$E$21-0.015 | B7: =IF($A7-B$5<0.01,NA(),('DCF - FCFF'!$B$21*SUMPRODUCT(POWER(1+'DCF - FCFF'!$D$21,{1,2,3,4,5})/POWER(1+$A7,{1,2,3,4,5}))+'DCF - FCFF'!$B$21*POWER(1+'DCF - FCFF'!$D$21,5)*(1+B$5)/($A7-B$5)/POWER(1+$A7,5)-'DCF - FCFF'!$O$21)/'DCF - FCFF'!$Q$21) | C7: =IF($A7-C$5<0.01,NA(),('DCF - FCFF'!$B$21*SUMPRODUCT(POWER(1+'DCF - FCFF'!$D$21,{1,2,3,4,5})/POWER(1+$A7,{1,2,3,4,5}))+'DCF - FCFF'!$B$21*POWER(1+'DCF - FCFF'!$D$21,5)*(1+C$5)/($A7-C$5)/POWER(1+$A7,5)-'DCF - FCFF'!$O$21)/'DCF - FCFF'!$Q$21) | D7: =IF($A7-D$5<0.01,NA(),('DCF - FCFF'!$B$21*SUMPRODUCT(POWER(1+'DCF - FCFF'!$D$21,{1,2,3,4,5})/POWER(1+$A7,{1,2,3,4,5}))+'DCF - FCFF'!$B$21*POWER(1+'DCF - FCFF'!$D$21,5)*(1+D$5)/($A7-D$5)/POWER(1+$A7,5)-'DCF - FCFF'!$O$21)/'DCF - FCFF'!$Q$21) | E7: =IF($A7-E$5<0.01,NA(),('DCF - FCFF'!$B$21*SUMPRODUCT(POWER(1+'DCF - FCFF'!$D$21,{1,2,3,4,5})/POWER(1+$A7,{1,2,3,4,5}))+'DCF - FCFF'!$B$21*POWER(1+'DCF - FCFF'!$D$21,5)*(1+E$5)/($A7-E$5)/POWER(1+$A7,5)-'DCF - FCFF'!$O$21)/'DCF - FCFF'!$Q$21) | F7: =IF($A7-F$5<0.01,NA(),('DCF - FCFF'!$B$21*SUMPRODUCT(POWER(1+'DCF - FCFF'!$D$21,{1,2,3,4,5})/POWER(1+$A7,{1,2,3,4,5}))+'DCF - FCFF'!$B$21*POWER(1+'DCF - FCFF'!$D$21,5)*(1+F$5)/($A7-F$5)/POWER(1+$A7,5)-'DCF - FCFF'!$O$21)/'DCF - FCFF'!$Q$21) | G7: =IF($A7-G$5<0.01,NA(),('DCF - FCFF'!$B$21*SUMPRODUCT(POWER(1+'DCF - FCFF'!$D$21,{1,2,3,4,5})/POWER(1+$A7,{1,2,3,4,5}))+'DCF - FCFF'!$B$21*POWER(1+'DCF - FCFF'!$D$21,5)*(1+G$5)/($A7-G$5)/POWER(1+$A7,5)-'DCF - FCFF'!$O$21)/'DCF - FCFF'!$Q$21) | H7: =IF($A7-H$5<0.01,NA(),('DCF - FCFF'!$B$21*SUMPRODUCT(POWER(1+'DCF - FCFF'!$D$21,{1,2,3,4,5})/POWER(1+$A7,{1,2,3,4,5}))+'DCF - FCFF'!$B$21*POWER(1+'DCF - FCFF'!$D$21,5)*(1+H$5)/($A7-H$5)/POWER(1+$A7,5)-'DCF - FCFF'!$O$21)/'DCF - FCFF'!$Q$21) | I7: =IF($A7-I$5<0.01,NA(),('DCF - FCFF'!$B$21*SUMPRODUCT(POWER(1+'DCF - FCFF'!$D$21,{1,2,3,4,5})/POWER(1+$A7,{1,2,3,4,5}))+'DCF - FCFF'!$B$21*POWER(1+'DCF - FCFF'!$D$21,5)*(1+I$5)/($A7-I$5)/POWER(1+$A7,5)-'DCF - FCFF'!$O$21)/'DCF - FCFF'!$Q$21) | J7: =IF($A7-J$5<0.01,NA(),('DCF - FCFF'!$B$21*SUMPRODUCT(POWER(1+'DCF - FCFF'!$D$21,{1,2,3,4,5})/POWER(1+$A7,{1,2,3,4,5}))+'DCF - FCFF'!$B$21*POWER(1+'DCF - FCFF'!$D$21,5)*(1+J$5)/($A7-J$5)/POWER(1+$A7,5)-'DCF - FCFF'!$O$21)/'DCF - FCFF'!$Q$21)
A8: ='DCF - FCFF'!$E$21-0.01 | B8: =IF($A8-B$5<0.01,NA(),('DCF - FCFF'!$B$21*SUMPRODUCT(POWER(1+'DCF - FCFF'!$D$21,{1,2,3,4,5})/POWER(1+$A8,{1,2,3,4,5}))+'DCF - FCFF'!$B$21*POWER(1+'DCF - FCFF'!$D$21,5)*(1+B$5)/($A8-B$5)/POWER(1+$A8,5)-'DCF - FCFF'!$O$21)/'DCF - FCFF'!$Q$21) | C8: =IF($A8-C$5<0.01,NA(),('DCF - FCFF'!$B$21*SUMPRODUCT(POWER(1+'DCF - FCFF'!$D$21,{1,2,3,4,5})/POWER(1+$A8,{1,2,3,4,5}))+'DCF - FCFF'!$B$21*POWER(1+'DCF - FCFF'!$D$21,5)*(1+C$5)/($A8-C$5)/POWER(1+$A8,5)-'DCF - FCFF'!$O$21)/'DCF - FCFF'!$Q$21) | D8: =IF($A8-D$5<0.01,NA(),('DCF - FCFF'!$B$21*SUMPRODUCT(POWER(1+'DCF - FCFF'!$D$21,{1,2,3,4,5})/POWER(1+$A8,{1,2,3,4,5}))+'DCF - FCFF'!$B$21*POWER(1+'DCF - FCFF'!$D$21,5)*(1+D$5)/($A8-D$5)/POWER(1+$A8,5)-'DCF - FCFF'!$O$21)/'DCF - FCFF'!$Q$21) | E8: =IF($A8-E$5<0.01,NA(),('DCF - FCFF'!$B$21*SUMPRODUCT(POWER(1+'DCF - FCFF'!$D$21,{1,2,3,4,5})/POWER(1+$A8,{1,2,3,4,5}))+'DCF - FCFF'!$B$21*POWER(1+'DCF - FCFF'!$D$21,5)*(1+E$5)/($A8-E$5)/POWER(1+$A8,5)-'DCF - FCFF'!$O$21)/'DCF - FCFF'!$Q$21) | F8: =IF($A8-F$5<0.01,NA(),('DCF - FCFF'!$B$21*SUMPRODUCT(POWER(1+'DCF - FCFF'!$D$21,{1,2,3,4,5})/POWER(1+$A8,{1,2,3,4,5}))+'DCF - FCFF'!$B$21*POWER(1+'DCF - FCFF'!$D$21,5)*(1+F$5)/($A8-F$5)/POWER(1+$A8,5)-'DCF - FCFF'!$O$21)/'DCF - FCFF'!$Q$21) | G8: =IF($A8-G$5<0.01,NA(),('DCF - FCFF'!$B$21*SUMPRODUCT(POWER(1+'DCF - FCFF'!$D$21,{1,2,3,4,5})/POWER(1+$A8,{1,2,3,4,5}))+'DCF - FCFF'!$B$21*POWER(1+'DCF - FCFF'!$D$21,5)*(1+G$5)/($A8-G$5)/POWER(1+$A8,5)-'DCF - FCFF'!$O$21)/'DCF - FCFF'!$Q$21) | H8: =IF($A8-H$5<0.01,NA(),('DCF - FCFF'!$B$21*SUMPRODUCT(POWER(1+'DCF - FCFF'!$D$21,{1,2,3,4,5})/POWER(1+$A8,{1,2,3,4,5}))+'DCF - FCFF'!$B$21*POWER(1+'DCF - FCFF'!$D$21,5)*(1+H$5)/($A8-H$5)/POWER(1+$A8,5)-'DCF - FCFF'!$O$21)/'DCF - FCFF'!$Q$21) | I8: =IF($A8-I$5<0.01,NA(),('DCF - FCFF'!$B$21*SUMPRODUCT(POWER(1+'DCF - FCFF'!$D$21,{1,2,3,4,5})/POWER(1+$A8,{1,2,3,4,5}))+'DCF - FCFF'!$B$21*POWER(1+'DCF - FCFF'!$D$21,5)*(1+I$5)/($A8-I$5)/POWER(1+$A8,5)-'DCF - FCFF'!$O$21)/'DCF - FCFF'!$Q$21) | J8: =IF($A8-J$5<0.01,NA(),('DCF - FCFF'!$B$21*SUMPRODUCT(POWER(1+'DCF - FCFF'!$D$21,{1,2,3,4,5})/POWER(1+$A8,{1,2,3,4,5}))+'DCF - FCFF'!$B$21*POWER(1+'DCF - FCFF'!$D$21,5)*(1+J$5)/($A8-J$5)/POWER(1+$A8,5)-'DCF - FCFF'!$O$21)/'DCF - FCFF'!$Q$21)
A9: ='DCF - FCFF'!$E$21-0.005 | B9: =IF($A9-B$5<0.01,NA(),('DCF - FCFF'!$B$21*SUMPRODUCT(POWER(1+'DCF - FCFF'!$D$21,{1,2,3,4,5})/POWER(1+$A9,{1,2,3,4,5}))+'DCF - FCFF'!$B$21*POWER(1+'DCF - FCFF'!$D$21,5)*(1+B$5)/($A9-B$5)/POWER(1+$A9,5)-'DCF - FCFF'!$O$21)/'DCF - FCFF'!$Q$21) | C9: =IF($A9-C$5<0.01,NA(),('DCF - FCFF'!$B$21*SUMPRODUCT(POWER(1+'DCF - FCFF'!$D$21,{1,2,3,4,5})/POWER(1+$A9,{1,2,3,4,5}))+'DCF - FCFF'!$B$21*POWER(1+'DCF - FCFF'!$D$21,5)*(1+C$5)/($A9-C$5)/POWER(1+$A9,5)-'DCF - FCFF'!$O$21)/'DCF - FCFF'!$Q$21) | D9: =IF($A9-D$5<0.01,NA(),('DCF - FCFF'!$B$21*SUMPRODUCT(POWER(1+'DCF - FCFF'!$D$21,{1,2,3,4,5})/POWER(1+$A9,{1,2,3,4,5}))+'DCF - FCFF'!$B$21*POWER(1+'DCF - FCFF'!$D$21,5)*(1+D$5)/($A9-D$5)/POWER(1+$A9,5)-'DCF - FCFF'!$O$21)/'DCF - FCFF'!$Q$21) | E9: =IF($A9-E$5<0.01,NA(),('DCF - FCFF'!$B$21*SUMPRODUCT(POWER(1+'DCF - FCFF'!$D$21,{1,2,3,4,5})/POWER(1+$A9,{1,2,3,4,5}))+'DCF - FCFF'!$B$21*POWER(1+'DCF - FCFF'!$D$21,5)*(1+E$5)/($A9-E$5)/POWER(1+$A9,5)-'DCF - FCFF'!$O$21)/'DCF - FCFF'!$Q$21) | F9: =IF($A9-F$5<0.01,NA(),('DCF - FCFF'!$B$21*SUMPRODUCT(POWER(1+'DCF - FCFF'!$D$21,{1,2,3,4,5})/POWER(1+$A9,{1,2,3,4,5}))+'DCF - FCFF'!$B$21*POWER(1+'DCF - FCFF'!$D$21,5)*(1+F$5)/($A9-F$5)/POWER(1+$A9,5)-'DCF - FCFF'!$O$21)/'DCF - FCFF'!$Q$21) | G9: =IF($A9-G$5<0.01,NA(),('DCF - FCFF'!$B$21*SUMPRODUCT(POWER(1+'DCF - FCFF'!$D$21,{1,2,3,4,5})/POWER(1+$A9,{1,2,3,4,5}))+'DCF - FCFF'!$B$21*POWER(1+'DCF - FCFF'!$D$21,5)*(1+G$5)/($A9-G$5)/POWER(1+$A9,5)-'DCF - FCFF'!$O$21)/'DCF - FCFF'!$Q$21) | H9: =IF($A9-H$5<0.01,NA(),('DCF - FCFF'!$B$21*SUMPRODUCT(POWER(1+'DCF - FCFF'!$D$21,{1,2,3,4,5})/POWER(1+$A9,{1,2,3,4,5}))+'DCF - FCFF'!$B$21*POWER(1+'DCF - FCFF'!$D$21,5)*(1+H$5)/($A9-H$5)/POWER(1+$A9,5)-'DCF - FCFF'!$O$21)/'DCF - FCFF'!$Q$21) | I9: =IF($A9-I$5<0.01,NA(),('DCF - FCFF'!$B$21*SUMPRODUCT(POWER(1+'DCF - FCFF'!$D$21,{1,2,3,4,5})/POWER(1+$A9,{1,2,3,4,5}))+'DCF - FCFF'!$B$21*POWER(1+'DCF - FCFF'!$D$21,5)*(1+I$5)/($A9-I$5)/POWER(1+$A9,5)-'DCF - FCFF'!$O$21)/'DCF - FCFF'!$Q$21) | J9: =IF($A9-J$5<0.01,NA(),('DCF - FCFF'!$B$21*SUMPRODUCT(POWER(1+'DCF - FCFF'!$D$21,{1,2,3,4,5})/POWER(1+$A9,{1,2,3,4,5}))+'DCF - FCFF'!$B$21*POWER(1+'DCF - FCFF'!$D$21,5)*(1+J$5)/($A9-J$5)/POWER(1+$A9,5)-'DCF - FCFF'!$O$21)/'DCF - FCFF'!$Q$21)
A10: ='DCF - FCFF'!$E$21+0.0 | B10: =IF($A10-B$5<0.01,NA(),('DCF - FCFF'!$B$21*SUMPRODUCT(POWER(1+'DCF - FCFF'!$D$21,{1,2,3,4,5})/POWER(1+$A10,{1,2,3,4,5}))+'DCF - FCFF'!$B$21*POWER(1+'DCF - FCFF'!$D$21,5)*(1+B$5)/($A10-B$5)/POWER(1+$A10,5)-'DCF - FCFF'!$O$21)/'DCF - FCFF'!$Q$21) | C10: =IF($A10-C$5<0.01,NA(),('DCF - FCFF'!$B$21*SUMPRODUCT(POWER(1+'DCF - FCFF'!$D$21,{1,2,3,4,5})/POWER(1+$A10,{1,2,3,4,5}))+'DCF - FCFF'!$B$21*POWER(1+'DCF - FCFF'!$D$21,5)*(1+C$5)/($A10-C$5)/POWER(1+$A10,5)-'DCF - FCFF'!$O$21)/'DCF - FCFF'!$Q$21) | D10: =IF($A10-D$5<0.01,NA(),('DCF - FCFF'!$B$21*SUMPRODUCT(POWER(1+'DCF - FCFF'!$D$21,{1,2,3,4,5})/POWER(1+$A10,{1,2,3,4,5}))+'DCF - FCFF'!$B$21*POWER(1+'DCF - FCFF'!$D$21,5)*(1+D$5)/($A10-D$5)/POWER(1+$A10,5)-'DCF - FCFF'!$O$21)/'DCF - FCFF'!$Q$21) | E10: =IF($A10-E$5<0.01,NA(),('DCF - FCFF'!$B$21*SUMPRODUCT(POWER(1+'DCF - FCFF'!$D$21,{1,2,3,4,5})/POWER(1+$A10,{1,2,3,4,5}))+'DCF - FCFF'!$B$21*POWER(1+'DCF - FCFF'!$D$21,5)*(1+E$5)/($A10-E$5)/POWER(1+$A10,5)-'DCF - FCFF'!$O$21)/'DCF - FCFF'!$Q$21) | F10: =IF($A10-F$5<0.01,NA(),('DCF - FCFF'!$B$21*SUMPRODUCT(POWER(1+'DCF - FCFF'!$D$21,{1,2,3,4,5})/POWER(1+$A10,{1,2,3,4,5}))+'DCF - FCFF'!$B$21*POWER(1+'DCF - FCFF'!$D$21,5)*(1+F$5)/($A10-F$5)/POWER(1+$A10,5)-'DCF - FCFF'!$O$21)/'DCF - FCFF'!$Q$21) | G10: =IF($A10-G$5<0.01,NA(),('DCF - FCFF'!$B$21*SUMPRODUCT(POWER(1+'DCF - FCFF'!$D$21,{1,2,3,4,5})/POWER(1+$A10,{1,2,3,4,5}))+'DCF - FCFF'!$B$21*POWER(1+'DCF - FCFF'!$D$21,5)*(1+G$5)/($A10-G$5)/POWER(1+$A10,5)-'DCF - FCFF'!$O$21)/'DCF - FCFF'!$Q$21) | H10: =IF($A10-H$5<0.01,NA(),('DCF - FCFF'!$B$21*SUMPRODUCT(POWER(1+'DCF - FCFF'!$D$21,{1,2,3,4,5})/POWER(1+$A10,{1,2,3,4,5}))+'DCF - FCFF'!$B$21*POWER(1+'DCF - FCFF'!$D$21,5)*(1+H$5)/($A10-H$5)/POWER(1+$A10,5)-'DCF - FCFF'!$O$21)/'DCF - FCFF'!$Q$21) | I10: =IF($A10-I$5<0.01,NA(),('DCF - FCFF'!$B$21*SUMPRODUCT(POWER(1+'DCF - FCFF'!$D$21,{1,2,3,4,5})/POWER(1+$A10,{1,2,3,4,5}))+'DCF - FCFF'!$B$21*POWER(1+'DCF - FCFF'!$D$21,5)*(1+I$5)/($A10-I$5)/POWER(1+$A10,5)-'DCF - FCFF'!$O$21)/'DCF - FCFF'!$Q$21) | J10: =IF($A10-J$5<0.01,NA(),('DCF - FCFF'!$B$21*SUMPRODUCT(POWER(1+'DCF - FCFF'!$D$21,{1,2,3,4,5})/POWER(1+$A10,{1,2,3,4,5}))+'DCF - FCFF'!$B$21*POWER(1+'DCF - FCFF'!$D$21,5)*(1+J$5)/($A10-J$5)/POWER(1+$A10,5)-'DCF - FCFF'!$O$21)/'DCF - FCFF'!$Q$21)
A11: ='DCF - FCFF'!$E$21+0.005 | B11: =IF($A11-B$5<0.01,NA(),('DCF - FCFF'!$B$21*SUMPRODUCT(POWER(1+'DCF - FCFF'!$D$21,{1,2,3,4,5})/POWER(1+$A11,{1,2,3,4,5}))+'DCF - FCFF'!$B$21*POWER(1+'DCF - FCFF'!$D$21,5)*(1+B$5)/($A11-B$5)/POWER(1+$A11,5)-'DCF - FCFF'!$O$21)/'DCF - FCFF'!$Q$21) | C11: =IF($A11-C$5<0.01,NA(),('DCF - FCFF'!$B$21*SUMPRODUCT(POWER(1+'DCF - FCFF'!$D$21,{1,2,3,4,5})/POWER(1+$A11,{1,2,3,4,5}))+'DCF - FCFF'!$B$21*POWER(1+'DCF - FCFF'!$D$21,5)*(1+C$5)/($A11-C$5)/POWER(1+$A11,5)-'DCF - FCFF'!$O$21)/'DCF - FCFF'!$Q$21) | D11: =IF($A11-D$5<0.01,NA(),('DCF - FCFF'!$B$21*SUMPRODUCT(POWER(1+'DCF - FCFF'!$D$21,{1,2,3,4,5})/POWER(1+$A11,{1,2,3,4,5}))+'DCF - FCFF'!$B$21*POWER(1+'DCF - FCFF'!$D$21,5)*(1+D$5)/($A11-D$5)/POWER(1+$A11,5)-'DCF - FCFF'!$O$21)/'DCF - FCFF'!$Q$21) | E11: =IF($A11-E$5<0.01,NA(),('DCF - FCFF'!$B$21*SUMPRODUCT(POWER(1+'DCF - FCFF'!$D$21,{1,2,3,4,5})/POWER(1+$A11,{1,2,3,4,5}))+'DCF - FCFF'!$B$21*POWER(1+'DCF - FCFF'!$D$21,5)*(1+E$5)/($A11-E$5)/POWER(1+$A11,5)-'DCF - FCFF'!$O$21)/'DCF - FCFF'!$Q$21) | F11: =IF($A11-F$5<0.01,NA(),('DCF - FCFF'!$B$21*SUMPRODUCT(POWER(1+'DCF - FCFF'!$D$21,{1,2,3,4,5})/POWER(1+$A11,{1,2,3,4,5}))+'DCF - FCFF'!$B$21*POWER(1+'DCF - FCFF'!$D$21,5)*(1+F$5)/($A11-F$5)/POWER(1+$A11,5)-'DCF - FCFF'!$O$21)/'DCF - FCFF'!$Q$21) | G11: =IF($A11-G$5<0.01,NA(),('DCF - FCFF'!$B$21*SUMPRODUCT(POWER(1+'DCF - FCFF'!$D$21,{1,2,3,4,5})/POWER(1+$A11,{1,2,3,4,5}))+'DCF - FCFF'!$B$21*POWER(1+'DCF - FCFF'!$D$21,5)*(1+G$5)/($A11-G$5)/POWER(1+$A11,5)-'DCF - FCFF'!$O$21)/'DCF - FCFF'!$Q$21) | H11: =IF($A11-H$5<0.01,NA(),('DCF - FCFF'!$B$21*SUMPRODUCT(POWER(1+'DCF - FCFF'!$D$21,{1,2,3,4,5})/POWER(1+$A11,{1,2,3,4,5}))+'DCF - FCFF'!$B$21*POWER(1+'DCF - FCFF'!$D$21,5)*(1+H$5)/($A11-H$5)/POWER(1+$A11,5)-'DCF - FCFF'!$O$21)/'DCF - FCFF'!$Q$21) | I11: =IF($A11-I$5<0.01,NA(),('DCF - FCFF'!$B$21*SUMPRODUCT(POWER(1+'DCF - FCFF'!$D$21,{1,2,3,4,5})/POWER(1+$A11,{1,2,3,4,5}))+'DCF - FCFF'!$B$21*POWER(1+'DCF - FCFF'!$D$21,5)*(1+I$5)/($A11-I$5)/POWER(1+$A11,5)-'DCF - FCFF'!$O$21)/'DCF - FCFF'!$Q$21) | J11: =IF($A11-J$5<0.01,NA(),('DCF - FCFF'!$B$21*SUMPRODUCT(POWER(1+'DCF - FCFF'!$D$21,{1,2,3,4,5})/POWER(1+$A11,{1,2,3,4,5}))+'DCF - FCFF'!$B$21*POWER(1+'DCF - FCFF'!$D$21,5)*(1+J$5)/($A11-J$5)/POWER(1+$A11,5)-'DCF - FCFF'!$O$21)/'DCF - FCFF'!$Q$21)
A12: ='DCF - FCFF'!$E$21+0.01 | B12: =IF($A12-B$5<0.01,NA(),('DCF - FCFF'!$B$21*SUMPRODUCT(POWER(1+'DCF - FCFF'!$D$21,{1,2,3,4,5})/POWER(1+$A12,{1,2,3,4,5}))+'DCF - FCFF'!$B$21*POWER(1+'DCF - FCFF'!$D$21,5)*(1+B$5)/($A12-B$5)/POWER(1+$A12,5)-'DCF - FCFF'!$O$21)/'DCF - FCFF'!$Q$21) | C12: =IF($A12-C$5<0.01,NA(),('DCF - FCFF'!$B$21*SUMPRODUCT(POWER(1+'DCF - FCFF'!$D$21,{1,2,3,4,5})/POWER(1+$A12,{1,2,3,4,5}))+'DCF - FCFF'!$B$21*POWER(1+'DCF - FCFF'!$D$21,5)*(1+C$5)/($A12-C$5)/POWER(1+$A12,5)-'DCF - FCFF'!$O$21)/'DCF - FCFF'!$Q$21) | D12: =IF($A12-D$5<0.01,NA(),('DCF - FCFF'!$B$21*SUMPRODUCT(POWER(1+'DCF - FCFF'!$D$21,{1,2,3,4,5})/POWER(1+$A12,{1,2,3,4,5}))+'DCF - FCFF'!$B$21*POWER(1+'DCF - FCFF'!$D$21,5)*(1+D$5)/($A12-D$5)/POWER(1+$A12,5)-'DCF - FCFF'!$O$21)/'DCF - FCFF'!$Q$21) | E12: =IF($A12-E$5<0.01,NA(),('DCF - FCFF'!$B$21*SUMPRODUCT(POWER(1+'DCF - FCFF'!$D$21,{1,2,3,4,5})/POWER(1+$A12,{1,2,3,4,5}))+'DCF - FCFF'!$B$21*POWER(1+'DCF - FCFF'!$D$21,5)*(1+E$5)/($A12-E$5)/POWER(1+$A12,5)-'DCF - FCFF'!$O$21)/'DCF - FCFF'!$Q$21) | F12: =IF($A12-F$5<0.01,NA(),('DCF - FCFF'!$B$21*SUMPRODUCT(POWER(1+'DCF - FCFF'!$D$21,{1,2,3,4,5})/POWER(1+$A12,{1,2,3,4,5}))+'DCF - FCFF'!$B$21*POWER(1+'DCF - FCFF'!$D$21,5)*(1+F$5)/($A12-F$5)/POWER(1+$A12,5)-'DCF - FCFF'!$O$21)/'DCF - FCFF'!$Q$21) | G12: =IF($A12-G$5<0.01,NA(),('DCF - FCFF'!$B$21*SUMPRODUCT(POWER(1+'DCF - FCFF'!$D$21,{1,2,3,4,5})/POWER(1+$A12,{1,2,3,4,5}))+'DCF - FCFF'!$B$21*POWER(1+'DCF - FCFF'!$D$21,5)*(1+G$5)/($A12-G$5)/POWER(1+$A12,5)-'DCF - FCFF'!$O$21)/'DCF - FCFF'!$Q$21) | H12: =IF($A12-H$5<0.01,NA(),('DCF - FCFF'!$B$21*SUMPRODUCT(POWER(1+'DCF - FCFF'!$D$21,{1,2,3,4,5})/POWER(1+$A12,{1,2,3,4,5}))+'DCF - FCFF'!$B$21*POWER(1+'DCF - FCFF'!$D$21,5)*(1+H$5)/($A12-H$5)/POWER(1+$A12,5)-'DCF - FCFF'!$O$21)/'DCF - FCFF'!$Q$21) | I12: =IF($A12-I$5<0.01,NA(),('DCF - FCFF'!$B$21*SUMPRODUCT(POWER(1+'DCF - FCFF'!$D$21,{1,2,3,4,5})/POWER(1+$A12,{1,2,3,4,5}))+'DCF - FCFF'!$B$21*POWER(1+'DCF - FCFF'!$D$21,5)*(1+I$5)/($A12-I$5)/POWER(1+$A12,5)-'DCF - FCFF'!$O$21)/'DCF - FCFF'!$Q$21) | J12: =IF($A12-J$5<0.01,NA(),('DCF - FCFF'!$B$21*SUMPRODUCT(POWER(1+'DCF - FCFF'!$D$21,{1,2,3,4,5})/POWER(1+$A12,{1,2,3,4,5}))+'DCF - FCFF'!$B$21*POWER(1+'DCF - FCFF'!$D$21,5)*(1+J$5)/($A12-J$5)/POWER(1+$A12,5)-'DCF - FCFF'!$O$21)/'DCF - FCFF'!$Q$21)
A13: ='DCF - FCFF'!$E$21+0.015 | B13: =IF($A13-B$5<0.01,NA(),('DCF - FCFF'!$B$21*SUMPRODUCT(POWER(1+'DCF - FCFF'!$D$21,{1,2,3,4,5})/POWER(1+$A13,{1,2,3,4,5}))+'DCF - FCFF'!$B$21*POWER(1+'DCF - FCFF'!$D$21,5)*(1+B$5)/($A13-B$5)/POWER(1+$A13,5)-'DCF - FCFF'!$O$21)/'DCF - FCFF'!$Q$21) | C13: =IF($A13-C$5<0.01,NA(),('DCF - FCFF'!$B$21*SUMPRODUCT(POWER(1+'DCF - FCFF'!$D$21,{1,2,3,4,5})/POWER(1+$A13,{1,2,3,4,5}))+'DCF - FCFF'!$B$21*POWER(1+'DCF - FCFF'!$D$21,5)*(1+C$5)/($A13-C$5)/POWER(1+$A13,5)-'DCF - FCFF'!$O$21)/'DCF - FCFF'!$Q$21) | D13: =IF($A13-D$5<0.01,NA(),('DCF - FCFF'!$B$21*SUMPRODUCT(POWER(1+'DCF - FCFF'!$D$21,{1,2,3,4,5})/POWER(1+$A13,{1,2,3,4,5}))+'DCF - FCFF'!$B$21*POWER(1+'DCF - FCFF'!$D$21,5)*(1+D$5)/($A13-D$5)/POWER(1+$A13,5)-'DCF - FCFF'!$O$21)/'DCF - FCFF'!$Q$21) | E13: =IF($A13-E$5<0.01,NA(),('DCF - FCFF'!$B$21*SUMPRODUCT(POWER(1+'DCF - FCFF'!$D$21,{1,2,3,4,5})/POWER(1+$A13,{1,2,3,4,5}))+'DCF - FCFF'!$B$21*POWER(1+'DCF - FCFF'!$D$21,5)*(1+E$5)/($A13-E$5)/POWER(1+$A13,5)-'DCF - FCFF'!$O$21)/'DCF - FCFF'!$Q$21) | F13: =IF($A13-F$5<0.01,NA(),('DCF - FCFF'!$B$21*SUMPRODUCT(POWER(1+'DCF - FCFF'!$D$21,{1,2,3,4,5})/POWER(1+$A13,{1,2,3,4,5}))+'DCF - FCFF'!$B$21*POWER(1+'DCF - FCFF'!$D$21,5)*(1+F$5)/($A13-F$5)/POWER(1+$A13,5)-'DCF - FCFF'!$O$21)/'DCF - FCFF'!$Q$21) | G13: =IF($A13-G$5<0.01,NA(),('DCF - FCFF'!$B$21*SUMPRODUCT(POWER(1+'DCF - FCFF'!$D$21,{1,2,3,4,5})/POWER(1+$A13,{1,2,3,4,5}))+'DCF - FCFF'!$B$21*POWER(1+'DCF - FCFF'!$D$21,5)*(1+G$5)/($A13-G$5)/POWER(1+$A13,5)-'DCF - FCFF'!$O$21)/'DCF - FCFF'!$Q$21) | H13: =IF($A13-H$5<0.01,NA(),('DCF - FCFF'!$B$21*SUMPRODUCT(POWER(1+'DCF - FCFF'!$D$21,{1,2,3,4,5})/POWER(1+$A13,{1,2,3,4,5}))+'DCF - FCFF'!$B$21*POWER(1+'DCF - FCFF'!$D$21,5)*(1+H$5)/($A13-H$5)/POWER(1+$A13,5)-'DCF - FCFF'!$O$21)/'DCF - FCFF'!$Q$21) | I13: =IF($A13-I$5<0.01,NA(),('DCF - FCFF'!$B$21*SUMPRODUCT(POWER(1+'DCF - FCFF'!$D$21,{1,2,3,4,5})/POWER(1+$A13,{1,2,3,4,5}))+'DCF - FCFF'!$B$21*POWER(1+'DCF - FCFF'!$D$21,5)*(1+I$5)/($A13-I$5)/POWER(1+$A13,5)-'DCF - FCFF'!$O$21)/'DCF - FCFF'!$Q$21) | J13: =IF($A13-J$5<0.01,NA(),('DCF - FCFF'!$B$21*SUMPRODUCT(POWER(1+'DCF - FCFF'!$D$21,{1,2,3,4,5})/POWER(1+$A13,{1,2,3,4,5}))+'DCF - FCFF'!$B$21*POWER(1+'DCF - FCFF'!$D$21,5)*(1+J$5)/($A13-J$5)/POWER(1+$A13,5)-'DCF - FCFF'!$O$21)/'DCF - FCFF'!$Q$21)
A14: ='DCF - FCFF'!$E$21+0.02 | B14: =IF($A14-B$5<0.01,NA(),('DCF - FCFF'!$B$21*SUMPRODUCT(POWER(1+'DCF - FCFF'!$D$21,{1,2,3,4,5})/POWER(1+$A14,{1,2,3,4,5}))+'DCF - FCFF'!$B$21*POWER(1+'DCF - FCFF'!$D$21,5)*(1+B$5)/($A14-B$5)/POWER(1+$A14,5)-'DCF - FCFF'!$O$21)/'DCF - FCFF'!$Q$21) | C14: =IF($A14-C$5<0.01,NA(),('DCF - FCFF'!$B$21*SUMPRODUCT(POWER(1+'DCF - FCFF'!$D$21,{1,2,3,4,5})/POWER(1+$A14,{1,2,3,4,5}))+'DCF - FCFF'!$B$21*POWER(1+'DCF - FCFF'!$D$21,5)*(1+C$5)/($A14-C$5)/POWER(1+$A14,5)-'DCF - FCFF'!$O$21)/'DCF - FCFF'!$Q$21) | D14: =IF($A14-D$5<0.01,NA(),('DCF - FCFF'!$B$21*SUMPRODUCT(POWER(1+'DCF - FCFF'!$D$21,{1,2,3,4,5})/POWER(1+$A14,{1,2,3,4,5}))+'DCF - FCFF'!$B$21*POWER(1+'DCF - FCFF'!$D$21,5)*(1+D$5)/($A14-D$5)/POWER(1+$A14,5)-'DCF - FCFF'!$O$21)/'DCF - FCFF'!$Q$21) | E14: =IF($A14-E$5<0.01,NA(),('DCF - FCFF'!$B$21*SUMPRODUCT(POWER(1+'DCF - FCFF'!$D$21,{1,2,3,4,5})/POWER(1+$A14,{1,2,3,4,5}))+'DCF - FCFF'!$B$21*POWER(1+'DCF - FCFF'!$D$21,5)*(1+E$5)/($A14-E$5)/POWER(1+$A14,5)-'DCF - FCFF'!$O$21)/'DCF - FCFF'!$Q$21) | F14: =IF($A14-F$5<0.01,NA(),('DCF - FCFF'!$B$21*SUMPRODUCT(POWER(1+'DCF - FCFF'!$D$21,{1,2,3,4,5})/POWER(1+$A14,{1,2,3,4,5}))+'DCF - FCFF'!$B$21*POWER(1+'DCF - FCFF'!$D$21,5)*(1+F$5)/($A14-F$5)/POWER(1+$A14,5)-'DCF - FCFF'!$O$21)/'DCF - FCFF'!$Q$21) | G14: =IF($A14-G$5<0.01,NA(),('DCF - FCFF'!$B$21*SUMPRODUCT(POWER(1+'DCF - FCFF'!$D$21,{1,2,3,4,5})/POWER(1+$A14,{1,2,3,4,5}))+'DCF - FCFF'!$B$21*POWER(1+'DCF - FCFF'!$D$21,5)*(1+G$5)/($A14-G$5)/POWER(1+$A14,5)-'DCF - FCFF'!$O$21)/'DCF - FCFF'!$Q$21) | H14: =IF($A14-H$5<0.01,NA(),('DCF - FCFF'!$B$21*SUMPRODUCT(POWER(1+'DCF - FCFF'!$D$21,{1,2,3,4,5})/POWER(1+$A14,{1,2,3,4,5}))+'DCF - FCFF'!$B$21*POWER(1+'DCF - FCFF'!$D$21,5)*(1+H$5)/($A14-H$5)/POWER(1+$A14,5)-'DCF - FCFF'!$O$21)/'DCF - FCFF'!$Q$21) | I14: =IF($A14-I$5<0.01,NA(),('DCF - FCFF'!$B$21*SUMPRODUCT(POWER(1+'DCF - FCFF'!$D$21,{1,2,3,4,5})/POWER(1+$A14,{1,2,3,4,5}))+'DCF - FCFF'!$B$21*POWER(1+'DCF - FCFF'!$D$21,5)*(1+I$5)/($A14-I$5)/POWER(1+$A14,5)-'DCF - FCFF'!$O$21)/'DCF - FCFF'!$Q$21) | J14: =IF($A14-J$5<0.01,NA(),('DCF - FCFF'!$B$21*SUMPRODUCT(POWER(1+'DCF - FCFF'!$D$21,{1,2,3,4,5})/POWER(1+$A14,{1,2,3,4,5}))+'DCF - FCFF'!$B$21*POWER(1+'DCF - FCFF'!$D$21,5)*(1+J$5)/($A14-J$5)/POWER(1+$A14,5)-'DCF - FCFF'!$O$21)/'DCF - FCFF'!$Q$21)
A16: ITC | B16: ='Market Data'!$C$3 | C16: ← market price · rows: WACC · cols: terminal g
B17: 0.01 | C17: 0.015 | D17: 0.02 | E17: 0.025 | F17: 0.03 | G17: 0.035 | H17: 0.04 | I17: 0.045 | J17: 0.05
A18: ='DCF - FCFF'!$E$22-0.02 | B18: =IF($A18-B$17<0.01,NA(),('DCF - FCFF'!$B$22*SUMPRODUCT(POWER(1+'DCF - FCFF'!$D$22,{1,2,3,4,5})/POWER(1+$A18,{1,2,3,4,5}))+'DCF - FCFF'!$B$22*POWER(1+'DCF - FCFF'!$D$22,5)*(1+B$17)/($A18-B$17)/POWER(1+$A18,5)-'DCF - FCFF'!$O$22)/'DCF - FCFF'!$Q$22) | C18: =IF($A18-C$17<0.01,NA(),('DCF - FCFF'!$B$22*SUMPRODUCT(POWER(1+'DCF - FCFF'!$D$22,{1,2,3,4,5})/POWER(1+$A18,{1,2,3,4,5}))+'DCF - FCFF'!$B$22*POWER(1+'DCF - FCFF'!$D$22,5)*(1+C$17)/($A18-C$17)/POWER(1+$A18,5)-'DCF - FCFF'!$O$22)/'DCF - FCFF'!$Q$22) | D18: =IF($A18-D$17<0.01,NA(),('DCF - FCFF'!$B$22*SUMPRODUCT(POWER(1+'DCF - FCFF'!$D$22,{1,2,3,4,5})/POWER(1+$A18,{1,2,3,4,5}))+'DCF - FCFF'!$B$22*POWER(1+'DCF - FCFF'!$D$22,5)*(1+D$17)/($A18-D$17)/POWER(1+$A18,5)-'DCF - FCFF'!$O$22)/'DCF - FCFF'!$Q$22) | E18: =IF($A18-E$17<0.01,NA(),('DCF - FCFF'!$B$22*SUMPRODUCT(POWER(1+'DCF - FCFF'!$D$22,{1,2,3,4,5})/POWER(1+$A18,{1,2,3,4,5}))+'DCF - FCFF'!$B$22*POWER(1+'DCF - FCFF'!$D$22,5)*(1+E$17)/($A18-E$17)/POWER(1+$A18,5)-'DCF - FCFF'!$O$22)/'DCF - FCFF'!$Q$22) | F18: =IF($A18-F$17<0.01,NA(),('DCF - FCFF'!$B$22*SUMPRODUCT(POWER(1+'DCF - FCFF'!$D$22,{1,2,3,4,5})/POWER(1+$A18,{1,2,3,4,5}))+'DCF - FCFF'!$B$22*POWER(1+'DCF - FCFF'!$D$22,5)*(1+F$17)/($A18-F$17)/POWER(1+$A18,5)-'DCF - FCFF'!$O$22)/'DCF - FCFF'!$Q$22) | G18: =IF($A18-G$17<0.01,NA(),('DCF - FCFF'!$B$22*SUMPRODUCT(POWER(1+'DCF - FCFF'!$D$22,{1,2,3,4,5})/POWER(1+$A18,{1,2,3,4,5}))+'DCF - FCFF'!$B$22*POWER(1+'DCF - FCFF'!$D$22,5)*(1+G$17)/($A18-G$17)/POWER(1+$A18,5)-'DCF - FCFF'!$O$22)/'DCF - FCFF'!$Q$22) | H18: =IF($A18-H$17<0.01,NA(),('DCF - FCFF'!$B$22*SUMPRODUCT(POWER(1+'DCF - FCFF'!$D$22,{1,2,3,4,5})/POWER(1+$A18,{1,2,3,4,5}))+'DCF - FCFF'!$B$22*POWER(1+'DCF - FCFF'!$D$22,5)*(1+H$17)/($A18-H$17)/POWER(1+$A18,5)-'DCF - FCFF'!$O$22)/'DCF - FCFF'!$Q$22) | I18: =IF($A18-I$17<0.01,NA(),('DCF - FCFF'!$B$22*SUMPRODUCT(POWER(1+'DCF - FCFF'!$D$22,{1,2,3,4,5})/POWER(1+$A18,{1,2,3,4,5}))+'DCF - FCFF'!$B$22*POWER(1+'DCF - FCFF'!$D$22,5)*(1+I$17)/($A18-I$17)/POWER(1+$A18,5)-'DCF - FCFF'!$O$22)/'DCF - FCFF'!$Q$22) | J18: =IF($A18-J$17<0.01,NA(),('DCF - FCFF'!$B$22*SUMPRODUCT(POWER(1+'DCF - FCFF'!$D$22,{1,2,3,4,5})/POWER(1+$A18,{1,2,3,4,5}))+'DCF - FCFF'!$B$22*POWER(1+'DCF - FCFF'!$D$22,5)*(1+J$17)/($A18-J$17)/POWER(1+$A18,5)-'DCF - FCFF'!$O$22)/'DCF - FCFF'!$Q$22)
A19: ='DCF - FCFF'!$E$22-0.015 | B19: =IF($A19-B$17<0.01,NA(),('DCF - FCFF'!$B$22*SUMPRODUCT(POWER(1+'DCF - FCFF'!$D$22,{1,2,3,4,5})/POWER(1+$A19,{1,2,3,4,5}))+'DCF - FCFF'!$B$22*POWER(1+'DCF - FCFF'!$D$22,5)*(1+B$17)/($A19-B$17)/POWER(1+$A19,5)-'DCF - FCFF'!$O$22)/'DCF - FCFF'!$Q$22) | C19: =IF($A19-C$17<0.01,NA(),('DCF - FCFF'!$B$22*SUMPRODUCT(POWER(1+'DCF - FCFF'!$D$22,{1,2,3,4,5})/POWER(1+$A19,{1,2,3,4,5}))+'DCF - FCFF'!$B$22*POWER(1+'DCF - FCFF'!$D$22,5)*(1+C$17)/($A19-C$17)/POWER(1+$A19,5)-'DCF - FCFF'!$O$22)/'DCF - FCFF'!$Q$22) | D19: =IF($A19-D$17<0.01,NA(),('DCF - FCFF'!$B$22*SUMPRODUCT(POWER(1+'DCF - FCFF'!$D$22,{1,2,3,4,5})/POWER(1+$A19,{1,2,3,4,5}))+'DCF - FCFF'!$B$22*POWER(1+'DCF - FCFF'!$D$22,5)*(1+D$17)/($A19-D$17)/POWER(1+$A19,5)-'DCF - FCFF'!$O$22)/'DCF - FCFF'!$Q$22) | E19: =IF($A19-E$17<0.01,NA(),('DCF - FCFF'!$B$22*SUMPRODUCT(POWER(1+'DCF - FCFF'!$D$22,{1,2,3,4,5})/POWER(1+$A19,{1,2,3,4,5}))+'DCF - FCFF'!$B$22*POWER(1+'DCF - FCFF'!$D$22,5)*(1+E$17)/($A19-E$17)/POWER(1+$A19,5)-'DCF - FCFF'!$O$22)/'DCF - FCFF'!$Q$22) | F19: =IF($A19-F$17<0.01,NA(),('DCF - FCFF'!$B$22*SUMPRODUCT(POWER(1+'DCF - FCFF'!$D$22,{1,2,3,4,5})/POWER(1+$A19,{1,2,3,4,5}))+'DCF - FCFF'!$B$22*POWER(1+'DCF - FCFF'!$D$22,5)*(1+F$17)/($A19-F$17)/POWER(1+$A19,5)-'DCF - FCFF'!$O$22)/'DCF - FCFF'!$Q$22) | G19: =IF($A19-G$17<0.01,NA(),('DCF - FCFF'!$B$22*SUMPRODUCT(POWER(1+'DCF - FCFF'!$D$22,{1,2,3,4,5})/POWER(1+$A19,{1,2,3,4,5}))+'DCF - FCFF'!$B$22*POWER(1+'DCF - FCFF'!$D$22,5)*(1+G$17)/($A19-G$17)/POWER(1+$A19,5)-'DCF - FCFF'!$O$22)/'DCF - FCFF'!$Q$22) | H19: =IF($A19-H$17<0.01,NA(),('DCF - FCFF'!$B$22*SUMPRODUCT(POWER(1+'DCF - FCFF'!$D$22,{1,2,3,4,5})/POWER(1+$A19,{1,2,3,4,5}))+'DCF - FCFF'!$B$22*POWER(1+'DCF - FCFF'!$D$22,5)*(1+H$17)/($A19-H$17)/POWER(1+$A19,5)-'DCF - FCFF'!$O$22)/'DCF - FCFF'!$Q$22) | I19: =IF($A19-I$17<0.01,NA(),('DCF - FCFF'!$B$22*SUMPRODUCT(POWER(1+'DCF - FCFF'!$D$22,{1,2,3,4,5})/POWER(1+$A19,{1,2,3,4,5}))+'DCF - FCFF'!$B$22*POWER(1+'DCF - FCFF'!$D$22,5)*(1+I$17)/($A19-I$17)/POWER(1+$A19,5)-'DCF - FCFF'!$O$22)/'DCF - FCFF'!$Q$22) | J19: =IF($A19-J$17<0.01,NA(),('DCF - FCFF'!$B$22*SUMPRODUCT(POWER(1+'DCF - FCFF'!$D$22,{1,2,3,4,5})/POWER(1+$A19,{1,2,3,4,5}))+'DCF - FCFF'!$B$22*POWER(1+'DCF - FCFF'!$D$22,5)*(1+J$17)/($A19-J$17)/POWER(1+$A19,5)-'DCF - FCFF'!$O$22)/'DCF - FCFF'!$Q$22)
A20: ='DCF - FCFF'!$E$22-0.01 | B20: =IF($A20-B$17<0.01,NA(),('DCF - FCFF'!$B$22*SUMPRODUCT(POWER(1+'DCF - FCFF'!$D$22,{1,2,3,4,5})/POWER(1+$A20,{1,2,3,4,5}))+'DCF - FCFF'!$B$22*POWER(1+'DCF - FCFF'!$D$22,5)*(1+B$17)/($A20-B$17)/POWER(1+$A20,5)-'DCF - FCFF'!$O$22)/'DCF - FCFF'!$Q$22) | C20: =IF($A20-C$17<0.01,NA(),('DCF - FCFF'!$B$22*SUMPRODUCT(POWER(1+'DCF - FCFF'!$D$22,{1,2,3,4,5})/POWER(1+$A20,{1,2,3,4,5}))+'DCF - FCFF'!$B$22*POWER(1+'DCF - FCFF'!$D$22,5)*(1+C$17)/($A20-C$17)/POWER(1+$A20,5)-'DCF - FCFF'!$O$22)/'DCF - FCFF'!$Q$22) | D20: =IF($A20-D$17<0.01,NA(),('DCF - FCFF'!$B$22*SUMPRODUCT(POWER(1+'DCF - FCFF'!$D$22,{1,2,3,4,5})/POWER(1+$A20,{1,2,3,4,5}))+'DCF - FCFF'!$B$22*POWER(1+'DCF - FCFF'!$D$22,5)*(1+D$17)/($A20-D$17)/POWER(1+$A20,5)-'DCF - FCFF'!$O$22)/'DCF - FCFF'!$Q$22) | E20: =IF($A20-E$17<0.01,NA(),('DCF - FCFF'!$B$22*SUMPRODUCT(POWER(1+'DCF - FCFF'!$D$22,{1,2,3,4,5})/POWER(1+$A20,{1,2,3,4,5}))+'DCF - FCFF'!$B$22*POWER(1+'DCF - FCFF'!$D$22,5)*(1+E$17)/($A20-E$17)/POWER(1+$A20,5)-'DCF - FCFF'!$O$22)/'DCF - FCFF'!$Q$22) | F20: =IF($A20-F$17<0.01,NA(),('DCF - FCFF'!$B$22*SUMPRODUCT(POWER(1+'DCF - FCFF'!$D$22,{1,2,3,4,5})/POWER(1+$A20,{1,2,3,4,5}))+'DCF - FCFF'!$B$22*POWER(1+'DCF - FCFF'!$D$22,5)*(1+F$17)/($A20-F$17)/POWER(1+$A20,5)-'DCF - FCFF'!$O$22)/'DCF - FCFF'!$Q$22) | G20: =IF($A20-G$17<0.01,NA(),('DCF - FCFF'!$B$22*SUMPRODUCT(POWER(1+'DCF - FCFF'!$D$22,{1,2,3,4,5})/POWER(1+$A20,{1,2,3,4,5}))+'DCF - FCFF'!$B$22*POWER(1+'DCF - FCFF'!$D$22,5)*(1+G$17)/($A20-G$17)/POWER(1+$A20,5)-'DCF - FCFF'!$O$22)/'DCF - FCFF'!$Q$22) | H20: =IF($A20-H$17<0.01,NA(),('DCF - FCFF'!$B$22*SUMPRODUCT(POWER(1+'DCF - FCFF'!$D$22,{1,2,3,4,5})/POWER(1+$A20,{1,2,3,4,5}))+'DCF - FCFF'!$B$22*POWER(1+'DCF - FCFF'!$D$22,5)*(1+H$17)/($A20-H$17)/POWER(1+$A20,5)-'DCF - FCFF'!$O$22)/'DCF - FCFF'!$Q$22) | I20: =IF($A20-I$17<0.01,NA(),('DCF - FCFF'!$B$22*SUMPRODUCT(POWER(1+'DCF - FCFF'!$D$22,{1,2,3,4,5})/POWER(1+$A20,{1,2,3,4,5}))+'DCF - FCFF'!$B$22*POWER(1+'DCF - FCFF'!$D$22,5)*(1+I$17)/($A20-I$17)/POWER(1+$A20,5)-'DCF - FCFF'!$O$22)/'DCF - FCFF'!$Q$22) | J20: =IF($A20-J$17<0.01,NA(),('DCF - FCFF'!$B$22*SUMPRODUCT(POWER(1+'DCF - FCFF'!$D$22,{1,2,3,4,5})/POWER(1+$A20,{1,2,3,4,5}))+'DCF - FCFF'!$B$22*POWER(1+'DCF - FCFF'!$D$22,5)*(1+J$17)/($A20-J$17)/POWER(1+$A20,5)-'DCF - FCFF'!$O$22)/'DCF - FCFF'!$Q$22)
A21: ='DCF - FCFF'!$E$22-0.005 | B21: =IF($A21-B$17<0.01,NA(),('DCF - FCFF'!$B$22*SUMPRODUCT(POWER(1+'DCF - FCFF'!$D$22,{1,2,3,4,5})/POWER(1+$A21,{1,2,3,4,5}))+'DCF - FCFF'!$B$22*POWER(1+'DCF - FCFF'!$D$22,5)*(1+B$17)/($A21-B$17)/POWER(1+$A21,5)-'DCF - FCFF'!$O$22)/'DCF - FCFF'!$Q$22) | C21: =IF($A21-C$17<0.01,NA(),('DCF - FCFF'!$B$22*SUMPRODUCT(POWER(1+'DCF - FCFF'!$D$22,{1,2,3,4,5})/POWER(1+$A21,{1,2,3,4,5}))+'DCF - FCFF'!$B$22*POWER(1+'DCF - FCFF'!$D$22,5)*(1+C$17)/($A21-C$17)/POWER(1+$A21,5)-'DCF - FCFF'!$O$22)/'DCF - FCFF'!$Q$22) | D21: =IF($A21-D$17<0.01,NA(),('DCF - FCFF'!$B$22*SUMPRODUCT(POWER(1+'DCF - FCFF'!$D$22,{1,2,3,4,5})/POWER(1+$A21,{1,2,3,4,5}))+'DCF - FCFF'!$B$22*POWER(1+'DCF - FCFF'!$D$22,5)*(1+D$17)/($A21-D$17)/POWER(1+$A21,5)-'DCF - FCFF'!$O$22)/'DCF - FCFF'!$Q$22) | E21: =IF($A21-E$17<0.01,NA(),('DCF - FCFF'!$B$22*SUMPRODUCT(POWER(1+'DCF - FCFF'!$D$22,{1,2,3,4,5})/POWER(1+$A21,{1,2,3,4,5}))+'DCF - FCFF'!$B$22*POWER(1+'DCF - FCFF'!$D$22,5)*(1+E$17)/($A21-E$17)/POWER(1+$A21,5)-'DCF - FCFF'!$O$22)/'DCF - FCFF'!$Q$22) | F21: =IF($A21-F$17<0.01,NA(),('DCF - FCFF'!$B$22*SUMPRODUCT(POWER(1+'DCF - FCFF'!$D$22,{1,2,3,4,5})/POWER(1+$A21,{1,2,3,4,5}))+'DCF - FCFF'!$B$22*POWER(1+'DCF - FCFF'!$D$22,5)*(1+F$17)/($A21-F$17)/POWER(1+$A21,5)-'DCF - FCFF'!$O$22)/'DCF - FCFF'!$Q$22) | G21: =IF($A21-G$17<0.01,NA(),('DCF - FCFF'!$B$22*SUMPRODUCT(POWER(1+'DCF - FCFF'!$D$22,{1,2,3,4,5})/POWER(1+$A21,{1,2,3,4,5}))+'DCF - FCFF'!$B$22*POWER(1+'DCF - FCFF'!$D$22,5)*(1+G$17)/($A21-G$17)/POWER(1+$A21,5)-'DCF - FCFF'!$O$22)/'DCF - FCFF'!$Q$22) | H21: =IF($A21-H$17<0.01,NA(),('DCF - FCFF'!$B$22*SUMPRODUCT(POWER(1+'DCF - FCFF'!$D$22,{1,2,3,4,5})/POWER(1+$A21,{1,2,3,4,5}))+'DCF - FCFF'!$B$22*POWER(1+'DCF - FCFF'!$D$22,5)*(1+H$17)/($A21-H$17)/POWER(1+$A21,5)-'DCF - FCFF'!$O$22)/'DCF - FCFF'!$Q$22) | I21: =IF($A21-I$17<0.01,NA(),('DCF - FCFF'!$B$22*SUMPRODUCT(POWER(1+'DCF - FCFF'!$D$22,{1,2,3,4,5})/POWER(1+$A21,{1,2,3,4,5}))+'DCF - FCFF'!$B$22*POWER(1+'DCF - FCFF'!$D$22,5)*(1+I$17)/($A21-I$17)/POWER(1+$A21,5)-'DCF - FCFF'!$O$22)/'DCF - FCFF'!$Q$22) | J21: =IF($A21-J$17<0.01,NA(),('DCF - FCFF'!$B$22*SUMPRODUCT(POWER(1+'DCF - FCFF'!$D$22,{1,2,3,4,5})/POWER(1+$A21,{1,2,3,4,5}))+'DCF - FCFF'!$B$22*POWER(1+'DCF - FCFF'!$D$22,5)*(1+J$17)/($A21-J$17)/POWER(1+$A21,5)-'DCF - FCFF'!$O$22)/'DCF - FCFF'!$Q$22)
A22: ='DCF - FCFF'!$E$22+0.0 | B22: =IF($A22-B$17<0.01,NA(),('DCF - FCFF'!$B$22*SUMPRODUCT(POWER(1+'DCF - FCFF'!$D$22,{1,2,3,4,5})/POWER(1+$A22,{1,2,3,4,5}))+'DCF - FCFF'!$B$22*POWER(1+'DCF - FCFF'!$D$22,5)*(1+B$17)/($A22-B$17)/POWER(1+$A22,5)-'DCF - FCFF'!$O$22)/'DCF - FCFF'!$Q$22) | C22: =IF($A22-C$17<0.01,NA(),('DCF - FCFF'!$B$22*SUMPRODUCT(POWER(1+'DCF - FCFF'!$D$22,{1,2,3,4,5})/POWER(1+$A22,{1,2,3,4,5}))+'DCF - FCFF'!$B$22*POWER(1+'DCF - FCFF'!$D$22,5)*(1+C$17)/($A22-C$17)/POWER(1+$A22,5)-'DCF - FCFF'!$O$22)/'DCF - FCFF'!$Q$22) | D22: =IF($A22-D$17<0.01,NA(),('DCF - FCFF'!$B$22*SUMPRODUCT(POWER(1+'DCF - FCFF'!$D$22,{1,2,3,4,5})/POWER(1+$A22,{1,2,3,4,5}))+'DCF - FCFF'!$B$22*POWER(1+'DCF - FCFF'!$D$22,5)*(1+D$17)/($A22-D$17)/POWER(1+$A22,5)-'DCF - FCFF'!$O$22)/'DCF - FCFF'!$Q$22) | E22: =IF($A22-E$17<0.01,NA(),('DCF - FCFF'!$B$22*SUMPRODUCT(POWER(1+'DCF - FCFF'!$D$22,{1,2,3,4,5})/POWER(1+$A22,{1,2,3,4,5}))+'DCF - FCFF'!$B$22*POWER(1+'DCF - FCFF'!$D$22,5)*(1+E$17)/($A22-E$17)/POWER(1+$A22,5)-'DCF - FCFF'!$O$22)/'DCF - FCFF'!$Q$22) | F22: =IF($A22-F$17<0.01,NA(),('DCF - FCFF'!$B$22*SUMPRODUCT(POWER(1+'DCF - FCFF'!$D$22,{1,2,3,4,5})/POWER(1+$A22,{1,2,3,4,5}))+'DCF - FCFF'!$B$22*POWER(1+'DCF - FCFF'!$D$22,5)*(1+F$17)/($A22-F$17)/POWER(1+$A22,5)-'DCF - FCFF'!$O$22)/'DCF - FCFF'!$Q$22) | G22: =IF($A22-G$17<0.01,NA(),('DCF - FCFF'!$B$22*SUMPRODUCT(POWER(1+'DCF - FCFF'!$D$22,{1,2,3,4,5})/POWER(1+$A22,{1,2,3,4,5}))+'DCF - FCFF'!$B$22*POWER(1+'DCF - FCFF'!$D$22,5)*(1+G$17)/($A22-G$17)/POWER(1+$A22,5)-'DCF - FCFF'!$O$22)/'DCF - FCFF'!$Q$22) | H22: =IF($A22-H$17<0.01,NA(),('DCF - FCFF'!$B$22*SUMPRODUCT(POWER(1+'DCF - FCFF'!$D$22,{1,2,3,4,5})/POWER(1+$A22,{1,2,3,4,5}))+'DCF - FCFF'!$B$22*POWER(1+'DCF - FCFF'!$D$22,5)*(1+H$17)/($A22-H$17)/POWER(1+$A22,5)-'DCF - FCFF'!$O$22)/'DCF - FCFF'!$Q$22) | I22: =IF($A22-I$17<0.01,NA(),('DCF - FCFF'!$B$22*SUMPRODUCT(POWER(1+'DCF - FCFF'!$D$22,{1,2,3,4,5})/POWER(1+$A22,{1,2,3,4,5}))+'DCF - FCFF'!$B$22*POWER(1+'DCF - FCFF'!$D$22,5)*(1+I$17)/($A22-I$17)/POWER(1+$A22,5)-'DCF - FCFF'!$O$22)/'DCF - FCFF'!$Q$22) | J22: =IF($A22-J$17<0.01,NA(),('DCF - FCFF'!$B$22*SUMPRODUCT(POWER(1+'DCF - FCFF'!$D$22,{1,2,3,4,5})/POWER(1+$A22,{1,2,3,4,5}))+'DCF - FCFF'!$B$22*POWER(1+'DCF - FCFF'!$D$22,5)*(1+J$17)/($A22-J$17)/POWER(1+$A22,5)-'DCF - FCFF'!$O$22)/'DCF - FCFF'!$Q$22)
A23: ='DCF - FCFF'!$E$22+0.005 | B23: =IF($A23-B$17<0.01,NA(),('DCF - FCFF'!$B$22*SUMPRODUCT(POWER(1+'DCF - FCFF'!$D$22,{1,2,3,4,5})/POWER(1+$A23,{1,2,3,4,5}))+'DCF - FCFF'!$B$22*POWER(1+'DCF - FCFF'!$D$22,5)*(1+B$17)/($A23-B$17)/POWER(1+$A23,5)-'DCF - FCFF'!$O$22)/'DCF - FCFF'!$Q$22) | C23: =IF($A23-C$17<0.01,NA(),('DCF - FCFF'!$B$22*SUMPRODUCT(POWER(1+'DCF - FCFF'!$D$22,{1,2,3,4,5})/POWER(1+$A23,{1,2,3,4,5}))+'DCF - FCFF'!$B$22*POWER(1+'DCF - FCFF'!$D$22,5)*(1+C$17)/($A23-C$17)/POWER(1+$A23,5)-'DCF - FCFF'!$O$22)/'DCF - FCFF'!$Q$22) | D23: =IF($A23-D$17<0.01,NA(),('DCF - FCFF'!$B$22*SUMPRODUCT(POWER(1+'DCF - FCFF'!$D$22,{1,2,3,4,5})/POWER(1+$A23,{1,2,3,4,5}))+'DCF - FCFF'!$B$22*POWER(1+'DCF - FCFF'!$D$22,5)*(1+D$17)/($A23-D$17)/POWER(1+$A23,5)-'DCF - FCFF'!$O$22)/'DCF - FCFF'!$Q$22) | E23: =IF($A23-E$17<0.01,NA(),('DCF - FCFF'!$B$22*SUMPRODUCT(POWER(1+'DCF - FCFF'!$D$22,{1,2,3,4,5})/POWER(1+$A23,{1,2,3,4,5}))+'DCF - FCFF'!$B$22*POWER(1+'DCF - FCFF'!$D$22,5)*(1+E$17)/($A23-E$17)/POWER(1+$A23,5)-'DCF - FCFF'!$O$22)/'DCF - FCFF'!$Q$22) | F23: =IF($A23-F$17<0.01,NA(),('DCF - FCFF'!$B$22*SUMPRODUCT(POWER(1+'DCF - FCFF'!$D$22,{1,2,3,4,5})/POWER(1+$A23,{1,2,3,4,5}))+'DCF - FCFF'!$B$22*POWER(1+'DCF - FCFF'!$D$22,5)*(1+F$17)/($A23-F$17)/POWER(1+$A23,5)-'DCF - FCFF'!$O$22)/'DCF - FCFF'!$Q$22) | G23: =IF($A23-G$17<0.01,NA(),('DCF - FCFF'!$B$22*SUMPRODUCT(POWER(1+'DCF - FCFF'!$D$22,{1,2,3,4,5})/POWER(1+$A23,{1,2,3,4,5}))+'DCF - FCFF'!$B$22*POWER(1+'DCF - FCFF'!$D$22,5)*(1+G$17)/($A23-G$17)/POWER(1+$A23,5)-'DCF - FCFF'!$O$22)/'DCF - FCFF'!$Q$22) | H23: =IF($A23-H$17<0.01,NA(),('DCF - FCFF'!$B$22*SUMPRODUCT(POWER(1+'DCF - FCFF'!$D$22,{1,2,3,4,5})/POWER(1+$A23,{1,2,3,4,5}))+'DCF - FCFF'!$B$22*POWER(1+'DCF - FCFF'!$D$22,5)*(1+H$17)/($A23-H$17)/POWER(1+$A23,5)-'DCF - FCFF'!$O$22)/'DCF - FCFF'!$Q$22) | I23: =IF($A23-I$17<0.01,NA(),('DCF - FCFF'!$B$22*SUMPRODUCT(POWER(1+'DCF - FCFF'!$D$22,{1,2,3,4,5})/POWER(1+$A23,{1,2,3,4,5}))+'DCF - FCFF'!$B$22*POWER(1+'DCF - FCFF'!$D$22,5)*(1+I$17)/($A23-I$17)/POWER(1+$A23,5)-'DCF - FCFF'!$O$22)/'DCF - FCFF'!$Q$22) | J23: =IF($A23-J$17<0.01,NA(),('DCF - FCFF'!$B$22*SUMPRODUCT(POWER(1+'DCF - FCFF'!$D$22,{1,2,3,4,5})/POWER(1+$A23,{1,2,3,4,5}))+'DCF - FCFF'!$B$22*POWER(1+'DCF - FCFF'!$D$22,5)*(1+J$17)/($A23-J$17)/POWER(1+$A23,5)-'DCF - FCFF'!$O$22)/'DCF - FCFF'!$Q$22)
A24: ='DCF - FCFF'!$E$22+0.01 | B24: =IF($A24-B$17<0.01,NA(),('DCF - FCFF'!$B$22*SUMPRODUCT(POWER(1+'DCF - FCFF'!$D$22,{1,2,3,4,5})/POWER(1+$A24,{1,2,3,4,5}))+'DCF - FCFF'!$B$22*POWER(1+'DCF - FCFF'!$D$22,5)*(1+B$17)/($A24-B$17)/POWER(1+$A24,5)-'DCF - FCFF'!$O$22)/'DCF - FCFF'!$Q$22) | C24: =IF($A24-C$17<0.01,NA(),('DCF - FCFF'!$B$22*SUMPRODUCT(POWER(1+'DCF - FCFF'!$D$22,{1,2,3,4,5})/POWER(1+$A24,{1,2,3,4,5}))+'DCF - FCFF'!$B$22*POWER(1+'DCF - FCFF'!$D$22,5)*(1+C$17)/($A24-C$17)/POWER(1+$A24,5)-'DCF - FCFF'!$O$22)/'DCF - FCFF'!$Q$22) | D24: =IF($A24-D$17<0.01,NA(),('DCF - FCFF'!$B$22*SUMPRODUCT(POWER(1+'DCF - FCFF'!$D$22,{1,2,3,4,5})/POWER(1+$A24,{1,2,3,4,5}))+'DCF - FCFF'!$B$22*POWER(1+'DCF - FCFF'!$D$22,5)*(1+D$17)/($A24-D$17)/POWER(1+$A24,5)-'DCF - FCFF'!$O$22)/'DCF - FCFF'!$Q$22) | E24: =IF($A24-E$17<0.01,NA(),('DCF - FCFF'!$B$22*SUMPRODUCT(POWER(1+'DCF - FCFF'!$D$22,{1,2,3,4,5})/POWER(1+$A24,{1,2,3,4,5}))+'DCF - FCFF'!$B$22*POWER(1+'DCF - FCFF'!$D$22,5)*(1+E$17)/($A24-E$17)/POWER(1+$A24,5)-'DCF - FCFF'!$O$22)/'DCF - FCFF'!$Q$22) | F24: =IF($A24-F$17<0.01,NA(),('DCF - FCFF'!$B$22*SUMPRODUCT(POWER(1+'DCF - FCFF'!$D$22,{1,2,3,4,5})/POWER(1+$A24,{1,2,3,4,5}))+'DCF - FCFF'!$B$22*POWER(1+'DCF - FCFF'!$D$22,5)*(1+F$17)/($A24-F$17)/POWER(1+$A24,5)-'DCF - FCFF'!$O$22)/'DCF - FCFF'!$Q$22) | G24: =IF($A24-G$17<0.01,NA(),('DCF - FCFF'!$B$22*SUMPRODUCT(POWER(1+'DCF - FCFF'!$D$22,{1,2,3,4,5})/POWER(1+$A24,{1,2,3,4,5}))+'DCF - FCFF'!$B$22*POWER(1+'DCF - FCFF'!$D$22,5)*(1+G$17)/($A24-G$17)/POWER(1+$A24,5)-'DCF - FCFF'!$O$22)/'DCF - FCFF'!$Q$22) | H24: =IF($A24-H$17<0.01,NA(),('DCF - FCFF'!$B$22*SUMPRODUCT(POWER(1+'DCF - FCFF'!$D$22,{1,2,3,4,5})/POWER(1+$A24,{1,2,3,4,5}))+'DCF - FCFF'!$B$22*POWER(1+'DCF - FCFF'!$D$22,5)*(1+H$17)/($A24-H$17)/POWER(1+$A24,5)-'DCF - FCFF'!$O$22)/'DCF - FCFF'!$Q$22) | I24: =IF($A24-I$17<0.01,NA(),('DCF - FCFF'!$B$22*SUMPRODUCT(POWER(1+'DCF - FCFF'!$D$22,{1,2,3,4,5})/POWER(1+$A24,{1,2,3,4,5}))+'DCF - FCFF'!$B$22*POWER(1+'DCF - FCFF'!$D$22,5)*(1+I$17)/($A24-I$17)/POWER(1+$A24,5)-'DCF - FCFF'!$O$22)/'DCF - FCFF'!$Q$22) | J24: =IF($A24-J$17<0.01,NA(),('DCF - FCFF'!$B$22*SUMPRODUCT(POWER(1+'DCF - FCFF'!$D$22,{1,2,3,4,5})/POWER(1+$A24,{1,2,3,4,5}))+'DCF - FCFF'!$B$22*POWER(1+'DCF - FCFF'!$D$22,5)*(1+J$17)/($A24-J$17)/POWER(1+$A24,5)-'DCF - FCFF'!$O$22)/'DCF - FCFF'!$Q$22)
A25: ='DCF - FCFF'!$E$22+0.015 | B25: =IF($A25-B$17<0.01,NA(),('DCF - FCFF'!$B$22*SUMPRODUCT(POWER(1+'DCF - FCFF'!$D$22,{1,2,3,4,5})/POWER(1+$A25,{1,2,3,4,5}))+'DCF - FCFF'!$B$22*POWER(1+'DCF - FCFF'!$D$22,5)*(1+B$17)/($A25-B$17)/POWER(1+$A25,5)-'DCF - FCFF'!$O$22)/'DCF - FCFF'!$Q$22) | C25: =IF($A25-C$17<0.01,NA(),('DCF - FCFF'!$B$22*SUMPRODUCT(POWER(1+'DCF - FCFF'!$D$22,{1,2,3,4,5})/POWER(1+$A25,{1,2,3,4,5}))+'DCF - FCFF'!$B$22*POWER(1+'DCF - FCFF'!$D$22,5)*(1+C$17)/($A25-C$17)/POWER(1+$A25,5)-'DCF - FCFF'!$O$22)/'DCF - FCFF'!$Q$22) | D25: =IF($A25-D$17<0.01,NA(),('DCF - FCFF'!$B$22*SUMPRODUCT(POWER(1+'DCF - FCFF'!$D$22,{1,2,3,4,5})/POWER(1+$A25,{1,2,3,4,5}))+'DCF - FCFF'!$B$22*POWER(1+'DCF - FCFF'!$D$22,5)*(1+D$17)/($A25-D$17)/POWER(1+$A25,5)-'DCF - FCFF'!$O$22)/'DCF - FCFF'!$Q$22) | E25: =IF($A25-E$17<0.01,NA(),('DCF - FCFF'!$B$22*SUMPRODUCT(POWER(1+'DCF - FCFF'!$D$22,{1,2,3,4,5})/POWER(1+$A25,{1,2,3,4,5}))+'DCF - FCFF'!$B$22*POWER(1+'DCF - FCFF'!$D$22,5)*(1+E$17)/($A25-E$17)/POWER(1+$A25,5)-'DCF - FCFF'!$O$22)/'DCF - FCFF'!$Q$22) | F25: =IF($A25-F$17<0.01,NA(),('DCF - FCFF'!$B$22*SUMPRODUCT(POWER(1+'DCF - FCFF'!$D$22,{1,2,3,4,5})/POWER(1+$A25,{1,2,3,4,5}))+'DCF - FCFF'!$B$22*POWER(1+'DCF - FCFF'!$D$22,5)*(1+F$17)/($A25-F$17)/POWER(1+$A25,5)-'DCF - FCFF'!$O$22)/'DCF - FCFF'!$Q$22) | G25: =IF($A25-G$17<0.01,NA(),('DCF - FCFF'!$B$22*SUMPRODUCT(POWER(1+'DCF - FCFF'!$D$22,{1,2,3,4,5})/POWER(1+$A25,{1,2,3,4,5}))+'DCF - FCFF'!$B$22*POWER(1+'DCF - FCFF'!$D$22,5)*(1+G$17)/($A25-G$17)/POWER(1+$A25,5)-'DCF - FCFF'!$O$22)/'DCF - FCFF'!$Q$22) | H25: =IF($A25-H$17<0.01,NA(),('DCF - FCFF'!$B$22*SUMPRODUCT(POWER(1+'DCF - FCFF'!$D$22,{1,2,3,4,5})/POWER(1+$A25,{1,2,3,4,5}))+'DCF - FCFF'!$B$22*POWER(1+'DCF - FCFF'!$D$22,5)*(1+H$17)/($A25-H$17)/POWER(1+$A25,5)-'DCF - FCFF'!$O$22)/'DCF - FCFF'!$Q$22) | I25: =IF($A25-I$17<0.01,NA(),('DCF - FCFF'!$B$22*SUMPRODUCT(POWER(1+'DCF - FCFF'!$D$22,{1,2,3,4,5})/POWER(1+$A25,{1,2,3,4,5}))+'DCF - FCFF'!$B$22*POWER(1+'DCF - FCFF'!$D$22,5)*(1+I$17)/($A25-I$17)/POWER(1+$A25,5)-'DCF - FCFF'!$O$22)/'DCF - FCFF'!$Q$22) | J25: =IF($A25-J$17<0.01,NA(),('DCF - FCFF'!$B$22*SUMPRODUCT(POWER(1+'DCF - FCFF'!$D$22,{1,2,3,4,5})/POWER(1+$A25,{1,2,3,4,5}))+'DCF - FCFF'!$B$22*POWER(1+'DCF - FCFF'!$D$22,5)*(1+J$17)/($A25-J$17)/POWER(1+$A25,5)-'DCF - FCFF'!$O$22)/'DCF - FCFF'!$Q$22)
A26: ='DCF - FCFF'!$E$22+0.02 | B26: =IF($A26-B$17<0.01,NA(),('DCF - FCFF'!$B$22*SUMPRODUCT(POWER(1+'DCF - FCFF'!$D$22,{1,2,3,4,5})/POWER(1+$A26,{1,2,3,4,5}))+'DCF - FCFF'!$B$22*POWER(1+'DCF - FCFF'!$D$22,5)*(1+B$17)/($A26-B$17)/POWER(1+$A26,5)-'DCF - FCFF'!$O$22)/'DCF - FCFF'!$Q$22) | C26: =IF($A26-C$17<0.01,NA(),('DCF - FCFF'!$B$22*SUMPRODUCT(POWER(1+'DCF - FCFF'!$D$22,{1,2,3,4,5})/POWER(1+$A26,{1,2,3,4,5}))+'DCF - FCFF'!$B$22*POWER(1+'DCF - FCFF'!$D$22,5)*(1+C$17)/($A26-C$17)/POWER(1+$A26,5)-'DCF - FCFF'!$O$22)/'DCF - FCFF'!$Q$22) | D26: =IF($A26-D$17<0.01,NA(),('DCF - FCFF'!$B$22*SUMPRODUCT(POWER(1+'DCF - FCFF'!$D$22,{1,2,3,4,5})/POWER(1+$A26,{1,2,3,4,5}))+'DCF - FCFF'!$B$22*POWER(1+'DCF - FCFF'!$D$22,5)*(1+D$17)/($A26-D$17)/POWER(1+$A26,5)-'DCF - FCFF'!$O$22)/'DCF - FCFF'!$Q$22) | E26: =IF($A26-E$17<0.01,NA(),('DCF - FCFF'!$B$22*SUMPRODUCT(POWER(1+'DCF - FCFF'!$D$22,{1,2,3,4,5})/POWER(1+$A26,{1,2,3,4,5}))+'DCF - FCFF'!$B$22*POWER(1+'DCF - FCFF'!$D$22,5)*(1+E$17)/($A26-E$17)/POWER(1+$A26,5)-'DCF - FCFF'!$O$22)/'DCF - FCFF'!$Q$22) | F26: =IF($A26-F$17<0.01,NA(),('DCF - FCFF'!$B$22*SUMPRODUCT(POWER(1+'DCF - FCFF'!$D$22,{1,2,3,4,5})/POWER(1+$A26,{1,2,3,4,5}))+'DCF - FCFF'!$B$22*POWER(1+'DCF - FCFF'!$D$22,5)*(1+F$17)/($A26-F$17)/POWER(1+$A26,5)-'DCF - FCFF'!$O$22)/'DCF - FCFF'!$Q$22) | G26: =IF($A26-G$17<0.01,NA(),('DCF - FCFF'!$B$22*SUMPRODUCT(POWER(1+'DCF - FCFF'!$D$22,{1,2,3,4,5})/POWER(1+$A26,{1,2,3,4,5}))+'DCF - FCFF'!$B$22*POWER(1+'DCF - FCFF'!$D$22,5)*(1+G$17)/($A26-G$17)/POWER(1+$A26,5)-'DCF - FCFF'!$O$22)/'DCF - FCFF'!$Q$22) | H26: =IF($A26-H$17<0.01,NA(),('DCF - FCFF'!$B$22*SUMPRODUCT(POWER(1+'DCF - FCFF'!$D$22,{1,2,3,4,5})/POWER(1+$A26,{1,2,3,4,5}))+'DCF - FCFF'!$B$22*POWER(1+'DCF - FCFF'!$D$22,5)*(1+H$17)/($A26-H$17)/POWER(1+$A26,5)-'DCF - FCFF'!$O$22)/'DCF - FCFF'!$Q$22) | I26: =IF($A26-I$17<0.01,NA(),('DCF - FCFF'!$B$22*SUMPRODUCT(POWER(1+'DCF - FCFF'!$D$22,{1,2,3,4,5})/POWER(1+$A26,{1,2,3,4,5}))+'DCF - FCFF'!$B$22*POWER(1+'DCF - FCFF'!$D$22,5)*(1+I$17)/($A26-I$17)/POWER(1+$A26,5)-'DCF - FCFF'!$O$22)/'DCF - FCFF'!$Q$22) | J26: =IF($A26-J$17<0.01,NA(),('DCF - FCFF'!$B$22*SUMPRODUCT(POWER(1+'DCF - FCFF'!$D$22,{1,2,3,4,5})/POWER(1+$A26,{1,2,3,4,5}))+'DCF - FCFF'!$B$22*POWER(1+'DCF - FCFF'!$D$22,5)*(1+J$17)/($A26-J$17)/POWER(1+$A26,5)-'DCF - FCFF'!$O$22)/'DCF - FCFF'!$Q$22)
A28: Dabur | B28: ='Market Data'!$C$4 | C28: ← market price · rows: WACC · cols: terminal g
B29: 0.01 | C29: 0.015 | D29: 0.02 | E29: 0.025 | F29: 0.03 | G29: 0.035 | H29: 0.04 | I29: 0.045 | J29: 0.05
A30: ='DCF - FCFF'!$E$23-0.02 | B30: =IF($A30-B$29<0.01,NA(),('DCF - FCFF'!$B$23*SUMPRODUCT(POWER(1+'DCF - FCFF'!$D$23,{1,2,3,4,5})/POWER(1+$A30,{1,2,3,4,5}))+'DCF - FCFF'!$B$23*POWER(1+'DCF - FCFF'!$D$23,5)*(1+B$29)/($A30-B$29)/POWER(1+$A30,5)-'DCF - FCFF'!$O$23)/'DCF - FCFF'!$Q$23) | C30: =IF($A30-C$29<0.01,NA(),('DCF - FCFF'!$B$23*SUMPRODUCT(POWER(1+'DCF - FCFF'!$D$23,{1,2,3,4,5})/POWER(1+$A30,{1,2,3,4,5}))+'DCF - FCFF'!$B$23*POWER(1+'DCF - FCFF'!$D$23,5)*(1+C$29)/($A30-C$29)/POWER(1+$A30,5)-'DCF - FCFF'!$O$23)/'DCF - FCFF'!$Q$23) | D30: =IF($A30-D$29<0.01,NA(),('DCF - FCFF'!$B$23*SUMPRODUCT(POWER(1+'DCF - FCFF'!$D$23,{1,2,3,4,5})/POWER(1+$A30,{1,2,3,4,5}))+'DCF - FCFF'!$B$23*POWER(1+'DCF - FCFF'!$D$23,5)*(1+D$29)/($A30-D$29)/POWER(1+$A30,5)-'DCF - FCFF'!$O$23)/'DCF - FCFF'!$Q$23) | E30: =IF($A30-E$29<0.01,NA(),('DCF - FCFF'!$B$23*SUMPRODUCT(POWER(1+'DCF - FCFF'!$D$23,{1,2,3,4,5})/POWER(1+$A30,{1,2,3,4,5}))+'DCF - FCFF'!$B$23*POWER(1+'DCF - FCFF'!$D$23,5)*(1+E$29)/($A30-E$29)/POWER(1+$A30,5)-'DCF - FCFF'!$O$23)/'DCF - FCFF'!$Q$23) | F30: =IF($A30-F$29<0.01,NA(),('DCF - FCFF'!$B$23*SUMPRODUCT(POWER(1+'DCF - FCFF'!$D$23,{1,2,3,4,5})/POWER(1+$A30,{1,2,3,4,5}))+'DCF - FCFF'!$B$23*POWER(1+'DCF - FCFF'!$D$23,5)*(1+F$29)/($A30-F$29)/POWER(1+$A30,5)-'DCF - FCFF'!$O$23)/'DCF - FCFF'!$Q$23) | G30: =IF($A30-G$29<0.01,NA(),('DCF - FCFF'!$B$23*SUMPRODUCT(POWER(1+'DCF - FCFF'!$D$23,{1,2,3,4,5})/POWER(1+$A30,{1,2,3,4,5}))+'DCF - FCFF'!$B$23*POWER(1+'DCF - FCFF'!$D$23,5)*(1+G$29)/($A30-G$29)/POWER(1+$A30,5)-'DCF - FCFF'!$O$23)/'DCF - FCFF'!$Q$23) | H30: =IF($A30-H$29<0.01,NA(),('DCF - FCFF'!$B$23*SUMPRODUCT(POWER(1+'DCF - FCFF'!$D$23,{1,2,3,4,5})/POWER(1+$A30,{1,2,3,4,5}))+'DCF - FCFF'!$B$23*POWER(1+'DCF - FCFF'!$D$23,5)*(1+H$29)/($A30-H$29)/POWER(1+$A30,5)-'DCF - FCFF'!$O$23)/'DCF - FCFF'!$Q$23) | I30: =IF($A30-I$29<0.01,NA(),('DCF - FCFF'!$B$23*SUMPRODUCT(POWER(1+'DCF - FCFF'!$D$23,{1,2,3,4,5})/POWER(1+$A30,{1,2,3,4,5}))+'DCF - FCFF'!$B$23*POWER(1+'DCF - FCFF'!$D$23,5)*(1+I$29)/($A30-I$29)/POWER(1+$A30,5)-'DCF - FCFF'!$O$23)/'DCF - FCFF'!$Q$23) | J30: =IF($A30-J$29<0.01,NA(),('DCF - FCFF'!$B$23*SUMPRODUCT(POWER(1+'DCF - FCFF'!$D$23,{1,2,3,4,5})/POWER(1+$A30,{1,2,3,4,5}))+'DCF - FCFF'!$B$23*POWER(1+'DCF - FCFF'!$D$23,5)*(1+J$29)/($A30-J$29)/POWER(1+$A30,5)-'DCF - FCFF'!$O$23)/'DCF - FCFF'!$Q$23)
A31: ='DCF - FCFF'!$E$23-0.015 | B31: =IF($A31-B$29<0.01,NA(),('DCF - FCFF'!$B$23*SUMPRODUCT(POWER(1+'DCF - FCFF'!$D$23,{1,2,3,4,5})/POWER(1+$A31,{1,2,3,4,5}))+'DCF - FCFF'!$B$23*POWER(1+'DCF - FCFF'!$D$23,5)*(1+B$29)/($A31-B$29)/POWER(1+$A31,5)-'DCF - FCFF'!$O$23)/'DCF - FCFF'!$Q$23) | C31: =IF($A31-C$29<0.01,NA(),('DCF - FCFF'!$B$23*SUMPRODUCT(POWER(1+'DCF - FCFF'!$D$23,{1,2,3,4,5})/POWER(1+$A31,{1,2,3,4,5}))+'DCF - FCFF'!$B$23*POWER(1+'DCF - FCFF'!$D$23,5)*(1+C$29)/($A31-C$29)/POWER(1+$A31,5)-'DCF - FCFF'!$O$23)/'DCF - FCFF'!$Q$23) | D31: =IF($A31-D$29<0.01,NA(),('DCF - FCFF'!$B$23*SUMPRODUCT(POWER(1+'DCF - FCFF'!$D$23,{1,2,3,4,5})/POWER(1+$A31,{1,2,3,4,5}))+'DCF - FCFF'!$B$23*POWER(1+'DCF - FCFF'!$D$23,5)*(1+D$29)/($A31-D$29)/POWER(1+$A31,5)-'DCF - FCFF'!$O$23)/'DCF - FCFF'!$Q$23) | E31: =IF($A31-E$29<0.01,NA(),('DCF - FCFF'!$B$23*SUMPRODUCT(POWER(1+'DCF - FCFF'!$D$23,{1,2,3,4,5})/POWER(1+$A31,{1,2,3,4,5}))+'DCF - FCFF'!$B$23*POWER(1+'DCF - FCFF'!$D$23,5)*(1+E$29)/($A31-E$29)/POWER(1+$A31,5)-'DCF - FCFF'!$O$23)/'DCF - FCFF'!$Q$23) | F31: =IF($A31-F$29<0.01,NA(),('DCF - FCFF'!$B$23*SUMPRODUCT(POWER(1+'DCF - FCFF'!$D$23,{1,2,3,4,5})/POWER(1+$A31,{1,2,3,4,5}))+'DCF - FCFF'!$B$23*POWER(1+'DCF - FCFF'!$D$23,5)*(1+F$29)/($A31-F$29)/POWER(1+$A31,5)-'DCF - FCFF'!$O$23)/'DCF - FCFF'!$Q$23) | G31: =IF($A31-G$29<0.01,NA(),('DCF - FCFF'!$B$23*SUMPRODUCT(POWER(1+'DCF - FCFF'!$D$23,{1,2,3,4,5})/POWER(1+$A31,{1,2,3,4,5}))+'DCF - FCFF'!$B$23*POWER(1+'DCF - FCFF'!$D$23,5)*(1+G$29)/($A31-G$29)/POWER(1+$A31,5)-'DCF - FCFF'!$O$23)/'DCF - FCFF'!$Q$23) | H31: =IF($A31-H$29<0.01,NA(),('DCF - FCFF'!$B$23*SUMPRODUCT(POWER(1+'DCF - FCFF'!$D$23,{1,2,3,4,5})/POWER(1+$A31,{1,2,3,4,5}))+'DCF - FCFF'!$B$23*POWER(1+'DCF - FCFF'!$D$23,5)*(1+H$29)/($A31-H$29)/POWER(1+$A31,5)-'DCF - FCFF'!$O$23)/'DCF - FCFF'!$Q$23) | I31: =IF($A31-I$29<0.01,NA(),('DCF - FCFF'!$B$23*SUMPRODUCT(POWER(1+'DCF - FCFF'!$D$23,{1,2,3,4,5})/POWER(1+$A31,{1,2,3,4,5}))+'DCF - FCFF'!$B$23*POWER(1+'DCF - FCFF'!$D$23,5)*(1+I$29)/($A31-I$29)/POWER(1+$A31,5)-'DCF - FCFF'!$O$23)/'DCF - FCFF'!$Q$23) | J31: =IF($A31-J$29<0.01,NA(),('DCF - FCFF'!$B$23*SUMPRODUCT(POWER(1+'DCF - FCFF'!$D$23,{1,2,3,4,5})/POWER(1+$A31,{1,2,3,4,5}))+'DCF - FCFF'!$B$23*POWER(1+'DCF - FCFF'!$D$23,5)*(1+J$29)/($A31-J$29)/POWER(1+$A31,5)-'DCF - FCFF'!$O$23)/'DCF - FCFF'!$Q$23)
A32: ='DCF - FCFF'!$E$23-0.01 | B32: =IF($A32-B$29<0.01,NA(),('DCF - FCFF'!$B$23*SUMPRODUCT(POWER(1+'DCF - FCFF'!$D$23,{1,2,3,4,5})/POWER(1+$A32,{1,2,3,4,5}))+'DCF - FCFF'!$B$23*POWER(1+'DCF - FCFF'!$D$23,5)*(1+B$29)/($A32-B$29)/POWER(1+$A32,5)-'DCF - FCFF'!$O$23)/'DCF - FCFF'!$Q$23) | C32: =IF($A32-C$29<0.01,NA(),('DCF - FCFF'!$B$23*SUMPRODUCT(POWER(1+'DCF - FCFF'!$D$23,{1,2,3,4,5})/POWER(1+$A32,{1,2,3,4,5}))+'DCF - FCFF'!$B$23*POWER(1+'DCF - FCFF'!$D$23,5)*(1+C$29)/($A32-C$29)/POWER(1+$A32,5)-'DCF - FCFF'!$O$23)/'DCF - FCFF'!$Q$23) | D32: =IF($A32-D$29<0.01,NA(),('DCF - FCFF'!$B$23*SUMPRODUCT(POWER(1+'DCF - FCFF'!$D$23,{1,2,3,4,5})/POWER(1+$A32,{1,2,3,4,5}))+'DCF - FCFF'!$B$23*POWER(1+'DCF - FCFF'!$D$23,5)*(1+D$29)/($A32-D$29)/POWER(1+$A32,5)-'DCF - FCFF'!$O$23)/'DCF - FCFF'!$Q$23) | E32: =IF($A32-E$29<0.01,NA(),('DCF - FCFF'!$B$23*SUMPRODUCT(POWER(1+'DCF - FCFF'!$D$23,{1,2,3,4,5})/POWER(1+$A32,{1,2,3,4,5}))+'DCF - FCFF'!$B$23*POWER(1+'DCF - FCFF'!$D$23,5)*(1+E$29)/($A32-E$29)/POWER(1+$A32,5)-'DCF - FCFF'!$O$23)/'DCF - FCFF'!$Q$23) | F32: =IF($A32-F$29<0.01,NA(),('DCF - FCFF'!$B$23*SUMPRODUCT(POWER(1+'DCF - FCFF'!$D$23,{1,2,3,4,5})/POWER(1+$A32,{1,2,3,4,5}))+'DCF - FCFF'!$B$23*POWER(1+'DCF - FCFF'!$D$23,5)*(1+F$29)/($A32-F$29)/POWER(1+$A32,5)-'DCF - FCFF'!$O$23)/'DCF - FCFF'!$Q$23) | G32: =IF($A32-G$29<0.01,NA(),('DCF - FCFF'!$B$23*SUMPRODUCT(POWER(1+'DCF - FCFF'!$D$23,{1,2,3,4,5})/POWER(1+$A32,{1,2,3,4,5}))+'DCF - FCFF'!$B$23*POWER(1+'DCF - FCFF'!$D$23,5)*(1+G$29)/($A32-G$29)/POWER(1+$A32,5)-'DCF - FCFF'!$O$23)/'DCF - FCFF'!$Q$23) | H32: =IF($A32-H$29<0.01,NA(),('DCF - FCFF'!$B$23*SUMPRODUCT(POWER(1+'DCF - FCFF'!$D$23,{1,2,3,4,5})/POWER(1+$A32,{1,2,3,4,5}))+'DCF - FCFF'!$B$23*POWER(1+'DCF - FCFF'!$D$23,5)*(1+H$29)/($A32-H$29)/POWER(1+$A32,5)-'DCF - FCFF'!$O$23)/'DCF - FCFF'!$Q$23) | I32: =IF($A32-I$29<0.01,NA(),('DCF - FCFF'!$B$23*SUMPRODUCT(POWER(1+'DCF - FCFF'!$D$23,{1,2,3,4,5})/POWER(1+$A32,{1,2,3,4,5}))+'DCF - FCFF'!$B$23*POWER(1+'DCF - FCFF'!$D$23,5)*(1+I$29)/($A32-I$29)/POWER(1+$A32,5)-'DCF - FCFF'!$O$23)/'DCF - FCFF'!$Q$23) | J32: =IF($A32-J$29<0.01,NA(),('DCF - FCFF'!$B$23*SUMPRODUCT(POWER(1+'DCF - FCFF'!$D$23,{1,2,3,4,5})/POWER(1+$A32,{1,2,3,4,5}))+'DCF - FCFF'!$B$23*POWER(1+'DCF - FCFF'!$D$23,5)*(1+J$29)/($A32-J$29)/POWER(1+$A32,5)-'DCF - FCFF'!$O$23)/'DCF - FCFF'!$Q$23)
A33: ='DCF - FCFF'!$E$23-0.005 | B33: =IF($A33-B$29<0.01,NA(),('DCF - FCFF'!$B$23*SUMPRODUCT(POWER(1+'DCF - FCFF'!$D$23,{1,2,3,4,5})/POWER(1+$A33,{1,2,3,4,5}))+'DCF - FCFF'!$B$23*POWER(1+'DCF - FCFF'!$D$23,5)*(1+B$29)/($A33-B$29)/POWER(1+$A33,5)-'DCF - FCFF'!$O$23)/'DCF - FCFF'!$Q$23) | C33: =IF($A33-C$29<0.01,NA(),('DCF - FCFF'!$B$23*SUMPRODUCT(POWER(1+'DCF - FCFF'!$D$23,{1,2,3,4,5})/POWER(1+$A33,{1,2,3,4,5}))+'DCF - FCFF'!$B$23*POWER(1+'DCF - FCFF'!$D$23,5)*(1+C$29)/($A33-C$29)/POWER(1+$A33,5)-'DCF - FCFF'!$O$23)/'DCF - FCFF'!$Q$23) | D33: =IF($A33-D$29<0.01,NA(),('DCF - FCFF'!$B$23*SUMPRODUCT(POWER(1+'DCF - FCFF'!$D$23,{1,2,3,4,5})/POWER(1+$A33,{1,2,3,4,5}))+'DCF - FCFF'!$B$23*POWER(1+'DCF - FCFF'!$D$23,5)*(1+D$29)/($A33-D$29)/POWER(1+$A33,5)-'DCF - FCFF'!$O$23)/'DCF - FCFF'!$Q$23) | E33: =IF($A33-E$29<0.01,NA(),('DCF - FCFF'!$B$23*SUMPRODUCT(POWER(1+'DCF - FCFF'!$D$23,{1,2,3,4,5})/POWER(1+$A33,{1,2,3,4,5}))+'DCF - FCFF'!$B$23*POWER(1+'DCF - FCFF'!$D$23,5)*(1+E$29)/($A33-E$29)/POWER(1+$A33,5)-'DCF - FCFF'!$O$23)/'DCF - FCFF'!$Q$23) | F33: =IF($A33-F$29<0.01,NA(),('DCF - FCFF'!$B$23*SUMPRODUCT(POWER(1+'DCF - FCFF'!$D$23,{1,2,3,4,5})/POWER(1+$A33,{1,2,3,4,5}))+'DCF - FCFF'!$B$23*POWER(1+'DCF - FCFF'!$D$23,5)*(1+F$29)/($A33-F$29)/POWER(1+$A33,5)-'DCF - FCFF'!$O$23)/'DCF - FCFF'!$Q$23) | G33: =IF($A33-G$29<0.01,NA(),('DCF - FCFF'!$B$23*SUMPRODUCT(POWER(1+'DCF - FCFF'!$D$23,{1,2,3,4,5})/POWER(1+$A33,{1,2,3,4,5}))+'DCF - FCFF'!$B$23*POWER(1+'DCF - FCFF'!$D$23,5)*(1+G$29)/($A33-G$29)/POWER(1+$A33,5)-'DCF - FCFF'!$O$23)/'DCF - FCFF'!$Q$23) | H33: =IF($A33-H$29<0.01,NA(),('DCF - FCFF'!$B$23*SUMPRODUCT(POWER(1+'DCF - FCFF'!$D$23,{1,2,3,4,5})/POWER(1+$A33,{1,2,3,4,5}))+'DCF - FCFF'!$B$23*POWER(1+'DCF - FCFF'!$D$23,5)*(1+H$29)/($A33-H$29)/POWER(1+$A33,5)-'DCF - FCFF'!$O$23)/'DCF - FCFF'!$Q$23) | I33: =IF($A33-I$29<0.01,NA(),('DCF - FCFF'!$B$23*SUMPRODUCT(POWER(1+'DCF - FCFF'!$D$23,{1,2,3,4,5})/POWER(1+$A33,{1,2,3,4,5}))+'DCF - FCFF'!$B$23*POWER(1+'DCF - FCFF'!$D$23,5)*(1+I$29)/($A33-I$29)/POWER(1+$A33,5)-'DCF - FCFF'!$O$23)/'DCF - FCFF'!$Q$23) | J33: =IF($A33-J$29<0.01,NA(),('DCF - FCFF'!$B$23*SUMPRODUCT(POWER(1+'DCF - FCFF'!$D$23,{1,2,3,4,5})/POWER(1+$A33,{1,2,3,4,5}))+'DCF - FCFF'!$B$23*POWER(1+'DCF - FCFF'!$D$23,5)*(1+J$29)/($A33-J$29)/POWER(1+$A33,5)-'DCF - FCFF'!$O$23)/'DCF - FCFF'!$Q$23)
A34: ='DCF - FCFF'!$E$23+0.0 | B34: =IF($A34-B$29<0.01,NA(),('DCF - FCFF'!$B$23*SUMPRODUCT(POWER(1+'DCF - FCFF'!$D$23,{1,2,3,4,5})/POWER(1+$A34,{1,2,3,4,5}))+'DCF - FCFF'!$B$23*POWER(1+'DCF - FCFF'!$D$23,5)*(1+B$29)/($A34-B$29)/POWER(1+$A34,5)-'DCF - FCFF'!$O$23)/'DCF - FCFF'!$Q$23) | C34: =IF($A34-C$29<0.01,NA(),('DCF - FCFF'!$B$23*SUMPRODUCT(POWER(1+'DCF - FCFF'!$D$23,{1,2,3,4,5})/POWER(1+$A34,{1,2,3,4,5}))+'DCF - FCFF'!$B$23*POWER(1+'DCF - FCFF'!$D$23,5)*(1+C$29)/($A34-C$29)/POWER(1+$A34,5)-'DCF - FCFF'!$O$23)/'DCF - FCFF'!$Q$23) | D34: =IF($A34-D$29<0.01,NA(),('DCF - FCFF'!$B$23*SUMPRODUCT(POWER(1+'DCF - FCFF'!$D$23,{1,2,3,4,5})/POWER(1+$A34,{1,2,3,4,5}))+'DCF - FCFF'!$B$23*POWER(1+'DCF - FCFF'!$D$23,5)*(1+D$29)/($A34-D$29)/POWER(1+$A34,5)-'DCF - FCFF'!$O$23)/'DCF - FCFF'!$Q$23) | E34: =IF($A34-E$29<0.01,NA(),('DCF - FCFF'!$B$23*SUMPRODUCT(POWER(1+'DCF - FCFF'!$D$23,{1,2,3,4,5})/POWER(1+$A34,{1,2,3,4,5}))+'DCF - FCFF'!$B$23*POWER(1+'DCF - FCFF'!$D$23,5)*(1+E$29)/($A34-E$29)/POWER(1+$A34,5)-'DCF - FCFF'!$O$23)/'DCF - FCFF'!$Q$23) | F34: =IF($A34-F$29<0.01,NA(),('DCF - FCFF'!$B$23*SUMPRODUCT(POWER(1+'DCF - FCFF'!$D$23,{1,2,3,4,5})/POWER(1+$A34,{1,2,3,4,5}))+'DCF - FCFF'!$B$23*POWER(1+'DCF - FCFF'!$D$23,5)*(1+F$29)/($A34-F$29)/POWER(1+$A34,5)-'DCF - FCFF'!$O$23)/'DCF - FCFF'!$Q$23) | G34: =IF($A34-G$29<0.01,NA(),('DCF - FCFF'!$B$23*SUMPRODUCT(POWER(1+'DCF - FCFF'!$D$23,{1,2,3,4,5})/POWER(1+$A34,{1,2,3,4,5}))+'DCF - FCFF'!$B$23*POWER(1+'DCF - FCFF'!$D$23,5)*(1+G$29)/($A34-G$29)/POWER(1+$A34,5)-'DCF - FCFF'!$O$23)/'DCF - FCFF'!$Q$23) | H34: =IF($A34-H$29<0.01,NA(),('DCF - FCFF'!$B$23*SUMPRODUCT(POWER(1+'DCF - FCFF'!$D$23,{1,2,3,4,5})/POWER(1+$A34,{1,2,3,4,5}))+'DCF - FCFF'!$B$23*POWER(1+'DCF - FCFF'!$D$23,5)*(1+H$29)/($A34-H$29)/POWER(1+$A34,5)-'DCF - FCFF'!$O$23)/'DCF - FCFF'!$Q$23) | I34: =IF($A34-I$29<0.01,NA(),('DCF - FCFF'!$B$23*SUMPRODUCT(POWER(1+'DCF - FCFF'!$D$23,{1,2,3,4,5})/POWER(1+$A34,{1,2,3,4,5}))+'DCF - FCFF'!$B$23*POWER(1+'DCF - FCFF'!$D$23,5)*(1+I$29)/($A34-I$29)/POWER(1+$A34,5)-'DCF - FCFF'!$O$23)/'DCF - FCFF'!$Q$23) | J34: =IF($A34-J$29<0.01,NA(),('DCF - FCFF'!$B$23*SUMPRODUCT(POWER(1+'DCF - FCFF'!$D$23,{1,2,3,4,5})/POWER(1+$A34,{1,2,3,4,5}))+'DCF - FCFF'!$B$23*POWER(1+'DCF - FCFF'!$D$23,5)*(1+J$29)/($A34-J$29)/POWER(1+$A34,5)-'DCF - FCFF'!$O$23)/'DCF - FCFF'!$Q$23)
A35: ='DCF - FCFF'!$E$23+0.005 | B35: =IF($A35-B$29<0.01,NA(),('DCF - FCFF'!$B$23*SUMPRODUCT(POWER(1+'DCF - FCFF'!$D$23,{1,2,3,4,5})/POWER(1+$A35,{1,2,3,4,5}))+'DCF - FCFF'!$B$23*POWER(1+'DCF - FCFF'!$D$23,5)*(1+B$29)/($A35-B$29)/POWER(1+$A35,5)-'DCF - FCFF'!$O$23)/'DCF - FCFF'!$Q$23) | C35: =IF($A35-C$29<0.01,NA(),('DCF - FCFF'!$B$23*SUMPRODUCT(POWER(1+'DCF - FCFF'!$D$23,{1,2,3,4,5})/POWER(1+$A35,{1,2,3,4,5}))+'DCF - FCFF'!$B$23*POWER(1+'DCF - FCFF'!$D$23,5)*(1+C$29)/($A35-C$29)/POWER(1+$A35,5)-'DCF - FCFF'!$O$23)/'DCF - FCFF'!$Q$23) | D35: =IF($A35-D$29<0.01,NA(),('DCF - FCFF'!$B$23*SUMPRODUCT(POWER(1+'DCF - FCFF'!$D$23,{1,2,3,4,5})/POWER(1+$A35,{1,2,3,4,5}))+'DCF - FCFF'!$B$23*POWER(1+'DCF - FCFF'!$D$23,5)*(1+D$29)/($A35-D$29)/POWER(1+$A35,5)-'DCF - FCFF'!$O$23)/'DCF - FCFF'!$Q$23) | E35: =IF($A35-E$29<0.01,NA(),('DCF - FCFF'!$B$23*SUMPRODUCT(POWER(1+'DCF - FCFF'!$D$23,{1,2,3,4,5})/POWER(1+$A35,{1,2,3,4,5}))+'DCF - FCFF'!$B$23*POWER(1+'DCF - FCFF'!$D$23,5)*(1+E$29)/($A35-E$29)/POWER(1+$A35,5)-'DCF - FCFF'!$O$23)/'DCF - FCFF'!$Q$23) | F35: =IF($A35-F$29<0.01,NA(),('DCF - FCFF'!$B$23*SUMPRODUCT(POWER(1+'DCF - FCFF'!$D$23,{1,2,3,4,5})/POWER(1+$A35,{1,2,3,4,5}))+'DCF - FCFF'!$B$23*POWER(1+'DCF - FCFF'!$D$23,5)*(1+F$29)/($A35-F$29)/POWER(1+$A35,5)-'DCF - FCFF'!$O$23)/'DCF - FCFF'!$Q$23) | G35: =IF($A35-G$29<0.01,NA(),('DCF - FCFF'!$B$23*SUMPRODUCT(POWER(1+'DCF - FCFF'!$D$23,{1,2,3,4,5})/POWER(1+$A35,{1,2,3,4,5}))+'DCF - FCFF'!$B$23*POWER(1+'DCF - FCFF'!$D$23,5)*(1+G$29)/($A35-G$29)/POWER(1+$A35,5)-'DCF - FCFF'!$O$23)/'DCF - FCFF'!$Q$23) | H35: =IF($A35-H$29<0.01,NA(),('DCF - FCFF'!$B$23*SUMPRODUCT(POWER(1+'DCF - FCFF'!$D$23,{1,2,3,4,5})/POWER(1+$A35,{1,2,3,4,5}))+'DCF - FCFF'!$B$23*POWER(1+'DCF - FCFF'!$D$23,5)*(1+H$29)/($A35-H$29)/POWER(1+$A35,5)-'DCF - FCFF'!$O$23)/'DCF - FCFF'!$Q$23) | I35: =IF($A35-I$29<0.01,NA(),('DCF - FCFF'!$B$23*SUMPRODUCT(POWER(1+'DCF - FCFF'!$D$23,{1,2,3,4,5})/POWER(1+$A35,{1,2,3,4,5}))+'DCF - FCFF'!$B$23*POWER(1+'DCF - FCFF'!$D$23,5)*(1+I$29)/($A35-I$29)/POWER(1+$A35,5)-'DCF - FCFF'!$O$23)/'DCF - FCFF'!$Q$23) | J35: =IF($A35-J$29<0.01,NA(),('DCF - FCFF'!$B$23*SUMPRODUCT(POWER(1+'DCF - FCFF'!$D$23,{1,2,3,4,5})/POWER(1+$A35,{1,2,3,4,5}))+'DCF - FCFF'!$B$23*POWER(1+'DCF - FCFF'!$D$23,5)*(1+J$29)/($A35-J$29)/POWER(1+$A35,5)-'DCF - FCFF'!$O$23)/'DCF - FCFF'!$Q$23)
A36: ='DCF - FCFF'!$E$23+0.01 | B36: =IF($A36-B$29<0.01,NA(),('DCF - FCFF'!$B$23*SUMPRODUCT(POWER(1+'DCF - FCFF'!$D$23,{1,2,3,4,5})/POWER(1+$A36,{1,2,3,4,5}))+'DCF - FCFF'!$B$23*POWER(1+'DCF - FCFF'!$D$23,5)*(1+B$29)/($A36-B$29)/POWER(1+$A36,5)-'DCF - FCFF'!$O$23)/'DCF - FCFF'!$Q$23) | C36: =IF($A36-C$29<0.01,NA(),('DCF - FCFF'!$B$23*SUMPRODUCT(POWER(1+'DCF - FCFF'!$D$23,{1,2,3,4,5})/POWER(1+$A36,{1,2,3,4,5}))+'DCF - FCFF'!$B$23*POWER(1+'DCF - FCFF'!$D$23,5)*(1+C$29)/($A36-C$29)/POWER(1+$A36,5)-'DCF - FCFF'!$O$23)/'DCF - FCFF'!$Q$23) | D36: =IF($A36-D$29<0.01,NA(),('DCF - FCFF'!$B$23*SUMPRODUCT(POWER(1+'DCF - FCFF'!$D$23,{1,2,3,4,5})/POWER(1+$A36,{1,2,3,4,5}))+'DCF - FCFF'!$B$23*POWER(1+'DCF - FCFF'!$D$23,5)*(1+D$29)/($A36-D$29)/POWER(1+$A36,5)-'DCF - FCFF'!$O$23)/'DCF - FCFF'!$Q$23) | E36: =IF($A36-E$29<0.01,NA(),('DCF - FCFF'!$B$23*SUMPRODUCT(POWER(1+'DCF - FCFF'!$D$23,{1,2,3,4,5})/POWER(1+$A36,{1,2,3,4,5}))+'DCF - FCFF'!$B$23*POWER(1+'DCF - FCFF'!$D$23,5)*(1+E$29)/($A36-E$29)/POWER(1+$A36,5)-'DCF - FCFF'!$O$23)/'DCF - FCFF'!$Q$23) | F36: =IF($A36-F$29<0.01,NA(),('DCF - FCFF'!$B$23*SUMPRODUCT(POWER(1+'DCF - FCFF'!$D$23,{1,2,3,4,5})/POWER(1+$A36,{1,2,3,4,5}))+'DCF - FCFF'!$B$23*POWER(1+'DCF - FCFF'!$D$23,5)*(1+F$29)/($A36-F$29)/POWER(1+$A36,5)-'DCF - FCFF'!$O$23)/'DCF - FCFF'!$Q$23) | G36: =IF($A36-G$29<0.01,NA(),('DCF - FCFF'!$B$23*SUMPRODUCT(POWER(1+'DCF - FCFF'!$D$23,{1,2,3,4,5})/POWER(1+$A36,{1,2,3,4,5}))+'DCF - FCFF'!$B$23*POWER(1+'DCF - FCFF'!$D$23,5)*(1+G$29)/($A36-G$29)/POWER(1+$A36,5)-'DCF - FCFF'!$O$23)/'DCF - FCFF'!$Q$23) | H36: =IF($A36-H$29<0.01,NA(),('DCF - FCFF'!$B$23*SUMPRODUCT(POWER(1+'DCF - FCFF'!$D$23,{1,2,3,4,5})/POWER(1+$A36,{1,2,3,4,5}))+'DCF - FCFF'!$B$23*POWER(1+'DCF - FCFF'!$D$23,5)*(1+H$29)/($A36-H$29)/POWER(1+$A36,5)-'DCF - FCFF'!$O$23)/'DCF - FCFF'!$Q$23) | I36: =IF($A36-I$29<0.01,NA(),('DCF - FCFF'!$B$23*SUMPRODUCT(POWER(1+'DCF - FCFF'!$D$23,{1,2,3,4,5})/POWER(1+$A36,{1,2,3,4,5}))+'DCF - FCFF'!$B$23*POWER(1+'DCF - FCFF'!$D$23,5)*(1+I$29)/($A36-I$29)/POWER(1+$A36,5)-'DCF - FCFF'!$O$23)/'DCF - FCFF'!$Q$23) | J36: =IF($A36-J$29<0.01,NA(),('DCF - FCFF'!$B$23*SUMPRODUCT(POWER(1+'DCF - FCFF'!$D$23,{1,2,3,4,5})/POWER(1+$A36,{1,2,3,4,5}))+'DCF - FCFF'!$B$23*POWER(1+'DCF - FCFF'!$D$23,5)*(1+J$29)/($A36-J$29)/POWER(1+$A36,5)-'DCF - FCFF'!$O$23)/'DCF - FCFF'!$Q$23)
A37: ='DCF - FCFF'!$E$23+0.015 | B37: =IF($A37-B$29<0.01,NA(),('DCF - FCFF'!$B$23*SUMPRODUCT(POWER(1+'DCF - FCFF'!$D$23,{1,2,3,4,5})/POWER(1+$A37,{1,2,3,4,5}))+'DCF - FCFF'!$B$23*POWER(1+'DCF - FCFF'!$D$23,5)*(1+B$29)/($A37-B$29)/POWER(1+$A37,5)-'DCF - FCFF'!$O$23)/'DCF - FCFF'!$Q$23) | C37: =IF($A37-C$29<0.01,NA(),('DCF - FCFF'!$B$23*SUMPRODUCT(POWER(1+'DCF - FCFF'!$D$23,{1,2,3,4,5})/POWER(1+$A37,{1,2,3,4,5}))+'DCF - FCFF'!$B$23*POWER(1+'DCF - FCFF'!$D$23,5)*(1+C$29)/($A37-C$29)/POWER(1+$A37,5)-'DCF - FCFF'!$O$23)/'DCF - FCFF'!$Q$23) | D37: =IF($A37-D$29<0.01,NA(),('DCF - FCFF'!$B$23*SUMPRODUCT(POWER(1+'DCF - FCFF'!$D$23,{1,2,3,4,5})/POWER(1+$A37,{1,2,3,4,5}))+'DCF - FCFF'!$B$23*POWER(1+'DCF - FCFF'!$D$23,5)*(1+D$29)/($A37-D$29)/POWER(1+$A37,5)-'DCF - FCFF'!$O$23)/'DCF - FCFF'!$Q$23) | E37: =IF($A37-E$29<0.01,NA(),('DCF - FCFF'!$B$23*SUMPRODUCT(POWER(1+'DCF - FCFF'!$D$23,{1,2,3,4,5})/POWER(1+$A37,{1,2,3,4,5}))+'DCF - FCFF'!$B$23*POWER(1+'DCF - FCFF'!$D$23,5)*(1+E$29)/($A37-E$29)/POWER(1+$A37,5)-'DCF - FCFF'!$O$23)/'DCF - FCFF'!$Q$23) | F37: =IF($A37-F$29<0.01,NA(),('DCF - FCFF'!$B$23*SUMPRODUCT(POWER(1+'DCF - FCFF'!$D$23,{1,2,3,4,5})/POWER(1+$A37,{1,2,3,4,5}))+'DCF - FCFF'!$B$23*POWER(1+'DCF - FCFF'!$D$23,5)*(1+F$29)/($A37-F$29)/POWER(1+$A37,5)-'DCF - FCFF'!$O$23)/'DCF - FCFF'!$Q$23) | G37: =IF($A37-G$29<0.01,NA(),('DCF - FCFF'!$B$23*SUMPRODUCT(POWER(1+'DCF - FCFF'!$D$23,{1,2,3,4,5})/POWER(1+$A37,{1,2,3,4,5}))+'DCF - FCFF'!$B$23*POWER(1+'DCF - FCFF'!$D$23,5)*(1+G$29)/($A37-G$29)/POWER(1+$A37,5)-'DCF - FCFF'!$O$23)/'DCF - FCFF'!$Q$23) | H37: =IF($A37-H$29<0.01,NA(),('DCF - FCFF'!$B$23*SUMPRODUCT(POWER(1+'DCF - FCFF'!$D$23,{1,2,3,4,5})/POWER(1+$A37,{1,2,3,4,5}))+'DCF - FCFF'!$B$23*POWER(1+'DCF - FCFF'!$D$23,5)*(1+H$29)/($A37-H$29)/POWER(1+$A37,5)-'DCF - FCFF'!$O$23)/'DCF - FCFF'!$Q$23) | I37: =IF($A37-I$29<0.01,NA(),('DCF - FCFF'!$B$23*SUMPRODUCT(POWER(1+'DCF - FCFF'!$D$23,{1,2,3,4,5})/POWER(1+$A37,{1,2,3,4,5}))+'DCF - FCFF'!$B$23*POWER(1+'DCF - FCFF'!$D$23,5)*(1+I$29)/($A37-I$29)/POWER(1+$A37,5)-'DCF - FCFF'!$O$23)/'DCF - FCFF'!$Q$23) | J37: =IF($A37-J$29<0.01,NA(),('DCF - FCFF'!$B$23*SUMPRODUCT(POWER(1+'DCF - FCFF'!$D$23,{1,2,3,4,5})/POWER(1+$A37,{1,2,3,4,5}))+'DCF - FCFF'!$B$23*POWER(1+'DCF - FCFF'!$D$23,5)*(1+J$29)/($A37-J$29)/POWER(1+$A37,5)-'DCF - FCFF'!$O$23)/'DCF - FCFF'!$Q$23)
A38: ='DCF - FCFF'!$E$23+0.02 | B38: =IF($A38-B$29<0.01,NA(),('DCF - FCFF'!$B$23*SUMPRODUCT(POWER(1+'DCF - FCFF'!$D$23,{1,2,3,4,5})/POWER(1+$A38,{1,2,3,4,5}))+'DCF - FCFF'!$B$23*POWER(1+'DCF - FCFF'!$D$23,5)*(1+B$29)/($A38-B$29)/POWER(1+$A38,5)-'DCF - FCFF'!$O$23)/'DCF - FCFF'!$Q$23) | C38: =IF($A38-C$29<0.01,NA(),('DCF - FCFF'!$B$23*SUMPRODUCT(POWER(1+'DCF - FCFF'!$D$23,{1,2,3,4,5})/POWER(1+$A38,{1,2,3,4,5}))+'DCF - FCFF'!$B$23*POWER(1+'DCF - FCFF'!$D$23,5)*(1+C$29)/($A38-C$29)/POWER(1+$A38,5)-'DCF - FCFF'!$O$23)/'DCF - FCFF'!$Q$23) | D38: =IF($A38-D$29<0.01,NA(),('DCF - FCFF'!$B$23*SUMPRODUCT(POWER(1+'DCF - FCFF'!$D$23,{1,2,3,4,5})/POWER(1+$A38,{1,2,3,4,5}))+'DCF - FCFF'!$B$23*POWER(1+'DCF - FCFF'!$D$23,5)*(1+D$29)/($A38-D$29)/POWER(1+$A38,5)-'DCF - FCFF'!$O$23)/'DCF - FCFF'!$Q$23) | E38: =IF($A38-E$29<0.01,NA(),('DCF - FCFF'!$B$23*SUMPRODUCT(POWER(1+'DCF - FCFF'!$D$23,{1,2,3,4,5})/POWER(1+$A38,{1,2,3,4,5}))+'DCF - FCFF'!$B$23*POWER(1+'DCF - FCFF'!$D$23,5)*(1+E$29)/($A38-E$29)/POWER(1+$A38,5)-'DCF - FCFF'!$O$23)/'DCF - FCFF'!$Q$23) | F38: =IF($A38-F$29<0.01,NA(),('DCF - FCFF'!$B$23*SUMPRODUCT(POWER(1+'DCF - FCFF'!$D$23,{1,2,3,4,5})/POWER(1+$A38,{1,2,3,4,5}))+'DCF - FCFF'!$B$23*POWER(1+'DCF - FCFF'!$D$23,5)*(1+F$29)/($A38-F$29)/POWER(1+$A38,5)-'DCF - FCFF'!$O$23)/'DCF - FCFF'!$Q$23) | G38: =IF($A38-G$29<0.01,NA(),('DCF - FCFF'!$B$23*SUMPRODUCT(POWER(1+'DCF - FCFF'!$D$23,{1,2,3,4,5})/POWER(1+$A38,{1,2,3,4,5}))+'DCF - FCFF'!$B$23*POWER(1+'DCF - FCFF'!$D$23,5)*(1+G$29)/($A38-G$29)/POWER(1+$A38,5)-'DCF - FCFF'!$O$23)/'DCF - FCFF'!$Q$23) | H38: =IF($A38-H$29<0.01,NA(),('DCF - FCFF'!$B$23*SUMPRODUCT(POWER(1+'DCF - FCFF'!$D$23,{1,2,3,4,5})/POWER(1+$A38,{1,2,3,4,5}))+'DCF - FCFF'!$B$23*POWER(1+'DCF - FCFF'!$D$23,5)*(1+H$29)/($A38-H$29)/POWER(1+$A38,5)-'DCF - FCFF'!$O$23)/'DCF - FCFF'!$Q$23) | I38: =IF($A38-I$29<0.01,NA(),('DCF - FCFF'!$B$23*SUMPRODUCT(POWER(1+'DCF - FCFF'!$D$23,{1,2,3,4,5})/POWER(1+$A38,{1,2,3,4,5}))+'DCF - FCFF'!$B$23*POWER(1+'DCF - FCFF'!$D$23,5)*(1+I$29)/($A38-I$29)/POWER(1+$A38,5)-'DCF - FCFF'!$O$23)/'DCF - FCFF'!$Q$23) | J38: =IF($A38-J$29<0.01,NA(),('DCF - FCFF'!$B$23*SUMPRODUCT(POWER(1+'DCF - FCFF'!$D$23,{1,2,3,4,5})/POWER(1+$A38,{1,2,3,4,5}))+'DCF - FCFF'!$B$23*POWER(1+'DCF - FCFF'!$D$23,5)*(1+J$29)/($A38-J$29)/POWER(1+$A38,5)-'DCF - FCFF'!$O$23)/'DCF - FCFF'!$Q$23)
A40: Marico | B40: ='Market Data'!$C$5 | C40: ← market price · rows: WACC · cols: terminal g
B41: 0.01 | C41: 0.015 | D41: 0.02 | E41: 0.025 | F41: 0.03 | G41: 0.035 | H41: 0.04 | I41: 0.045 | J41: 0.05
A42: ='DCF - FCFF'!$E$24-0.02 | B42: =IF($A42-B$41<0.01,NA(),('DCF - FCFF'!$B$24*SUMPRODUCT(POWER(1+'DCF - FCFF'!$D$24,{1,2,3,4,5})/POWER(1+$A42,{1,2,3,4,5}))+'DCF - FCFF'!$B$24*POWER(1+'DCF - FCFF'!$D$24,5)*(1+B$41)/($A42-B$41)/POWER(1+$A42,5)-'DCF - FCFF'!$O$24)/'DCF - FCFF'!$Q$24) | C42: =IF($A42-C$41<0.01,NA(),('DCF - FCFF'!$B$24*SUMPRODUCT(POWER(1+'DCF - FCFF'!$D$24,{1,2,3,4,5})/POWER(1+$A42,{1,2,3,4,5}))+'DCF - FCFF'!$B$24*POWER(1+'DCF - FCFF'!$D$24,5)*(1+C$41)/($A42-C$41)/POWER(1+$A42,5)-'DCF - FCFF'!$O$24)/'DCF - FCFF'!$Q$24) | D42: =IF($A42-D$41<0.01,NA(),('DCF - FCFF'!$B$24*SUMPRODUCT(POWER(1+'DCF - FCFF'!$D$24,{1,2,3,4,5})/POWER(1+$A42,{1,2,3,4,5}))+'DCF - FCFF'!$B$24*POWER(1+'DCF - FCFF'!$D$24,5)*(1+D$41)/($A42-D$41)/POWER(1+$A42,5)-'DCF - FCFF'!$O$24)/'DCF - FCFF'!$Q$24) | E42: =IF($A42-E$41<0.01,NA(),('DCF - FCFF'!$B$24*SUMPRODUCT(POWER(1+'DCF - FCFF'!$D$24,{1,2,3,4,5})/POWER(1+$A42,{1,2,3,4,5}))+'DCF - FCFF'!$B$24*POWER(1+'DCF - FCFF'!$D$24,5)*(1+E$41)/($A42-E$41)/POWER(1+$A42,5)-'DCF - FCFF'!$O$24)/'DCF - FCFF'!$Q$24) | F42: =IF($A42-F$41<0.01,NA(),('DCF - FCFF'!$B$24*SUMPRODUCT(POWER(1+'DCF - FCFF'!$D$24,{1,2,3,4,5})/POWER(1+$A42,{1,2,3,4,5}))+'DCF - FCFF'!$B$24*POWER(1+'DCF - FCFF'!$D$24,5)*(1+F$41)/($A42-F$41)/POWER(1+$A42,5)-'DCF - FCFF'!$O$24)/'DCF - FCFF'!$Q$24) | G42: =IF($A42-G$41<0.01,NA(),('DCF - FCFF'!$B$24*SUMPRODUCT(POWER(1+'DCF - FCFF'!$D$24,{1,2,3,4,5})/POWER(1+$A42,{1,2,3,4,5}))+'DCF - FCFF'!$B$24*POWER(1+'DCF - FCFF'!$D$24,5)*(1+G$41)/($A42-G$41)/POWER(1+$A42,5)-'DCF - FCFF'!$O$24)/'DCF - FCFF'!$Q$24) | H42: =IF($A42-H$41<0.01,NA(),('DCF - FCFF'!$B$24*SUMPRODUCT(POWER(1+'DCF - FCFF'!$D$24,{1,2,3,4,5})/POWER(1+$A42,{1,2,3,4,5}))+'DCF - FCFF'!$B$24*POWER(1+'DCF - FCFF'!$D$24,5)*(1+H$41)/($A42-H$41)/POWER(1+$A42,5)-'DCF - FCFF'!$O$24)/'DCF - FCFF'!$Q$24) | I42: =IF($A42-I$41<0.01,NA(),('DCF - FCFF'!$B$24*SUMPRODUCT(POWER(1+'DCF - FCFF'!$D$24,{1,2,3,4,5})/POWER(1+$A42,{1,2,3,4,5}))+'DCF - FCFF'!$B$24*POWER(1+'DCF - FCFF'!$D$24,5)*(1+I$41)/($A42-I$41)/POWER(1+$A42,5)-'DCF - FCFF'!$O$24)/'DCF - FCFF'!$Q$24) | J42: =IF($A42-J$41<0.01,NA(),('DCF - FCFF'!$B$24*SUMPRODUCT(POWER(1+'DCF - FCFF'!$D$24,{1,2,3,4,5})/POWER(1+$A42,{1,2,3,4,5}))+'DCF - FCFF'!$B$24*POWER(1+'DCF - FCFF'!$D$24,5)*(1+J$41)/($A42-J$41)/POWER(1+$A42,5)-'DCF - FCFF'!$O$24)/'DCF - FCFF'!$Q$24)
A43: ='DCF - FCFF'!$E$24-0.015 | B43: =IF($A43-B$41<0.01,NA(),('DCF - FCFF'!$B$24*SUMPRODUCT(POWER(1+'DCF - FCFF'!$D$24,{1,2,3,4,5})/POWER(1+$A43,{1,2,3,4,5}))+'DCF - FCFF'!$B$24*POWER(1+'DCF - FCFF'!$D$24,5)*(1+B$41)/($A43-B$41)/POWER(1+$A43,5)-'DCF - FCFF'!$O$24)/'DCF - FCFF'!$Q$24) | C43: =IF($A43-C$41<0.01,NA(),('DCF - FCFF'!$B$24*SUMPRODUCT(POWER(1+'DCF - FCFF'!$D$24,{1,2,3,4,5})/POWER(1+$A43,{1,2,3,4,5}))+'DCF - FCFF'!$B$24*POWER(1+'DCF - FCFF'!$D$24,5)*(1+C$41)/($A43-C$41)/POWER(1+$A43,5)-'DCF - FCFF'!$O$24)/'DCF - FCFF'!$Q$24) | D43: =IF($A43-D$41<0.01,NA(),('DCF - FCFF'!$B$24*SUMPRODUCT(POWER(1+'DCF - FCFF'!$D$24,{1,2,3,4,5})/POWER(1+$A43,{1,2,3,4,5}))+'DCF - FCFF'!$B$24*POWER(1+'DCF - FCFF'!$D$24,5)*(1+D$41)/($A43-D$41)/POWER(1+$A43,5)-'DCF - FCFF'!$O$24)/'DCF - FCFF'!$Q$24) | E43: =IF($A43-E$41<0.01,NA(),('DCF - FCFF'!$B$24*SUMPRODUCT(POWER(1+'DCF - FCFF'!$D$24,{1,2,3,4,5})/POWER(1+$A43,{1,2,3,4,5}))+'DCF - FCFF'!$B$24*POWER(1+'DCF - FCFF'!$D$24,5)*(1+E$41)/($A43-E$41)/POWER(1+$A43,5)-'DCF - FCFF'!$O$24)/'DCF - FCFF'!$Q$24) | F43: =IF($A43-F$41<0.01,NA(),('DCF - FCFF'!$B$24*SUMPRODUCT(POWER(1+'DCF - FCFF'!$D$24,{1,2,3,4,5})/POWER(1+$A43,{1,2,3,4,5}))+'DCF - FCFF'!$B$24*POWER(1+'DCF - FCFF'!$D$24,5)*(1+F$41)/($A43-F$41)/POWER(1+$A43,5)-'DCF - FCFF'!$O$24)/'DCF - FCFF'!$Q$24) | G43: =IF($A43-G$41<0.01,NA(),('DCF - FCFF'!$B$24*SUMPRODUCT(POWER(1+'DCF - FCFF'!$D$24,{1,2,3,4,5})/POWER(1+$A43,{1,2,3,4,5}))+'DCF - FCFF'!$B$24*POWER(1+'DCF - FCFF'!$D$24,5)*(1+G$41)/($A43-G$41)/POWER(1+$A43,5)-'DCF - FCFF'!$O$24)/'DCF - FCFF'!$Q$24) | H43: =IF($A43-H$41<0.01,NA(),('DCF - FCFF'!$B$24*SUMPRODUCT(POWER(1+'DCF - FCFF'!$D$24,{1,2,3,4,5})/POWER(1+$A43,{1,2,3,4,5}))+'DCF - FCFF'!$B$24*POWER(1+'DCF - FCFF'!$D$24,5)*(1+H$41)/($A43-H$41)/POWER(1+$A43,5)-'DCF - FCFF'!$O$24)/'DCF - FCFF'!$Q$24) | I43: =IF($A43-I$41<0.01,NA(),('DCF - FCFF'!$B$24*SUMPRODUCT(POWER(1+'DCF - FCFF'!$D$24,{1,2,3,4,5})/POWER(1+$A43,{1,2,3,4,5}))+'DCF - FCFF'!$B$24*POWER(1+'DCF - FCFF'!$D$24,5)*(1+I$41)/($A43-I$41)/POWER(1+$A43,5)-'DCF - FCFF'!$O$24)/'DCF - FCFF'!$Q$24) | J43: =IF($A43-J$41<0.01,NA(),('DCF - FCFF'!$B$24*SUMPRODUCT(POWER(1+'DCF - FCFF'!$D$24,{1,2,3,4,5})/POWER(1+$A43,{1,2,3,4,5}))+'DCF - FCFF'!$B$24*POWER(1+'DCF - FCFF'!$D$24,5)*(1+J$41)/($A43-J$41)/POWER(1+$A43,5)-'DCF - FCFF'!$O$24)/'DCF - FCFF'!$Q$24)
A44: ='DCF - FCFF'!$E$24-0.01 | B44: =IF($A44-B$41<0.01,NA(),('DCF - FCFF'!$B$24*SUMPRODUCT(POWER(1+'DCF - FCFF'!$D$24,{1,2,3,4,5})/POWER(1+$A44,{1,2,3,4,5}))+'DCF - FCFF'!$B$24*POWER(1+'DCF - FCFF'!$D$24,5)*(1+B$41)/($A44-B$41)/POWER(1+$A44,5)-'DCF - FCFF'!$O$24)/'DCF - FCFF'!$Q$24) | C44: =IF($A44-C$41<0.01,NA(),('DCF - FCFF'!$B$24*SUMPRODUCT(POWER(1+'DCF - FCFF'!$D$24,{1,2,3,4,5})/POWER(1+$A44,{1,2,3,4,5}))+'DCF - FCFF'!$B$24*POWER(1+'DCF - FCFF'!$D$24,5)*(1+C$41)/($A44-C$41)/POWER(1+$A44,5)-'DCF - FCFF'!$O$24)/'DCF - FCFF'!$Q$24) | D44: =IF($A44-D$41<0.01,NA(),('DCF - FCFF'!$B$24*SUMPRODUCT(POWER(1+'DCF - FCFF'!$D$24,{1,2,3,4,5})/POWER(1+$A44,{1,2,3,4,5}))+'DCF - FCFF'!$B$24*POWER(1+'DCF - FCFF'!$D$24,5)*(1+D$41)/($A44-D$41)/POWER(1+$A44,5)-'DCF - FCFF'!$O$24)/'DCF - FCFF'!$Q$24) | E44: =IF($A44-E$41<0.01,NA(),('DCF - FCFF'!$B$24*SUMPRODUCT(POWER(1+'DCF - FCFF'!$D$24,{1,2,3,4,5})/POWER(1+$A44,{1,2,3,4,5}))+'DCF - FCFF'!$B$24*POWER(1+'DCF - FCFF'!$D$24,5)*(1+E$41)/($A44-E$41)/POWER(1+$A44,5)-'DCF - FCFF'!$O$24)/'DCF - FCFF'!$Q$24) | F44: =IF($A44-F$41<0.01,NA(),('DCF - FCFF'!$B$24*SUMPRODUCT(POWER(1+'DCF - FCFF'!$D$24,{1,2,3,4,5})/POWER(1+$A44,{1,2,3,4,5}))+'DCF - FCFF'!$B$24*POWER(1+'DCF - FCFF'!$D$24,5)*(1+F$41)/($A44-F$41)/POWER(1+$A44,5)-'DCF - FCFF'!$O$24)/'DCF - FCFF'!$Q$24) | G44: =IF($A44-G$41<0.01,NA(),('DCF - FCFF'!$B$24*SUMPRODUCT(POWER(1+'DCF - FCFF'!$D$24,{1,2,3,4,5})/POWER(1+$A44,{1,2,3,4,5}))+'DCF - FCFF'!$B$24*POWER(1+'DCF - FCFF'!$D$24,5)*(1+G$41)/($A44-G$41)/POWER(1+$A44,5)-'DCF - FCFF'!$O$24)/'DCF - FCFF'!$Q$24) | H44: =IF($A44-H$41<0.01,NA(),('DCF - FCFF'!$B$24*SUMPRODUCT(POWER(1+'DCF - FCFF'!$D$24,{1,2,3,4,5})/POWER(1+$A44,{1,2,3,4,5}))+'DCF - FCFF'!$B$24*POWER(1+'DCF - FCFF'!$D$24,5)*(1+H$41)/($A44-H$41)/POWER(1+$A44,5)-'DCF - FCFF'!$O$24)/'DCF - FCFF'!$Q$24) | I44: =IF($A44-I$41<0.01,NA(),('DCF - FCFF'!$B$24*SUMPRODUCT(POWER(1+'DCF - FCFF'!$D$24,{1,2,3,4,5})/POWER(1+$A44,{1,2,3,4,5}))+'DCF - FCFF'!$B$24*POWER(1+'DCF - FCFF'!$D$24,5)*(1+I$41)/($A44-I$41)/POWER(1+$A44,5)-'DCF - FCFF'!$O$24)/'DCF - FCFF'!$Q$24) | J44: =IF($A44-J$41<0.01,NA(),('DCF - FCFF'!$B$24*SUMPRODUCT(POWER(1+'DCF - FCFF'!$D$24,{1,2,3,4,5})/POWER(1+$A44,{1,2,3,4,5}))+'DCF - FCFF'!$B$24*POWER(1+'DCF - FCFF'!$D$24,5)*(1+J$41)/($A44-J$41)/POWER(1+$A44,5)-'DCF - FCFF'!$O$24)/'DCF - FCFF'!$Q$24)
A45: ='DCF - FCFF'!$E$24-0.005 | B45: =IF($A45-B$41<0.01,NA(),('DCF - FCFF'!$B$24*SUMPRODUCT(POWER(1+'DCF - FCFF'!$D$24,{1,2,3,4,5})/POWER(1+$A45,{1,2,3,4,5}))+'DCF - FCFF'!$B$24*POWER(1+'DCF - FCFF'!$D$24,5)*(1+B$41)/($A45-B$41)/POWER(1+$A45,5)-'DCF - FCFF'!$O$24)/'DCF - FCFF'!$Q$24) | C45: =IF($A45-C$41<0.01,NA(),('DCF - FCFF'!$B$24*SUMPRODUCT(POWER(1+'DCF - FCFF'!$D$24,{1,2,3,4,5})/POWER(1+$A45,{1,2,3,4,5}))+'DCF - FCFF'!$B$24*POWER(1+'DCF - FCFF'!$D$24,5)*(1+C$41)/($A45-C$41)/POWER(1+$A45,5)-'DCF - FCFF'!$O$24)/'DCF - FCFF'!$Q$24) | D45: =IF($A45-D$41<0.01,NA(),('DCF - FCFF'!$B$24*SUMPRODUCT(POWER(1+'DCF - FCFF'!$D$24,{1,2,3,4,5})/POWER(1+$A45,{1,2,3,4,5}))+'DCF - FCFF'!$B$24*POWER(1+'DCF - FCFF'!$D$24,5)*(1+D$41)/($A45-D$41)/POWER(1+$A45,5)-'DCF - FCFF'!$O$24)/'DCF - FCFF'!$Q$24) | E45: =IF($A45-E$41<0.01,NA(),('DCF - FCFF'!$B$24*SUMPRODUCT(POWER(1+'DCF - FCFF'!$D$24,{1,2,3,4,5})/POWER(1+$A45,{1,2,3,4,5}))+'DCF - FCFF'!$B$24*POWER(1+'DCF - FCFF'!$D$24,5)*(1+E$41)/($A45-E$41)/POWER(1+$A45,5)-'DCF - FCFF'!$O$24)/'DCF - FCFF'!$Q$24) | F45: =IF($A45-F$41<0.01,NA(),('DCF - FCFF'!$B$24*SUMPRODUCT(POWER(1+'DCF - FCFF'!$D$24,{1,2,3,4,5})/POWER(1+$A45,{1,2,3,4,5}))+'DCF - FCFF'!$B$24*POWER(1+'DCF - FCFF'!$D$24,5)*(1+F$41)/($A45-F$41)/POWER(1+$A45,5)-'DCF - FCFF'!$O$24)/'DCF - FCFF'!$Q$24) | G45: =IF($A45-G$41<0.01,NA(),('DCF - FCFF'!$B$24*SUMPRODUCT(POWER(1+'DCF - FCFF'!$D$24,{1,2,3,4,5})/POWER(1+$A45,{1,2,3,4,5}))+'DCF - FCFF'!$B$24*POWER(1+'DCF - FCFF'!$D$24,5)*(1+G$41)/($A45-G$41)/POWER(1+$A45,5)-'DCF - FCFF'!$O$24)/'DCF - FCFF'!$Q$24) | H45: =IF($A45-H$41<0.01,NA(),('DCF - FCFF'!$B$24*SUMPRODUCT(POWER(1+'DCF - FCFF'!$D$24,{1,2,3,4,5})/POWER(1+$A45,{1,2,3,4,5}))+'DCF - FCFF'!$B$24*POWER(1+'DCF - FCFF'!$D$24,5)*(1+H$41)/($A45-H$41)/POWER(1+$A45,5)-'DCF - FCFF'!$O$24)/'DCF - FCFF'!$Q$24) | I45: =IF($A45-I$41<0.01,NA(),('DCF - FCFF'!$B$24*SUMPRODUCT(POWER(1+'DCF - FCFF'!$D$24,{1,2,3,4,5})/POWER(1+$A45,{1,2,3,4,5}))+'DCF - FCFF'!$B$24*POWER(1+'DCF - FCFF'!$D$24,5)*(1+I$41)/($A45-I$41)/POWER(1+$A45,5)-'DCF - FCFF'!$O$24)/'DCF - FCFF'!$Q$24) | J45: =IF($A45-J$41<0.01,NA(),('DCF - FCFF'!$B$24*SUMPRODUCT(POWER(1+'DCF - FCFF'!$D$24,{1,2,3,4,5})/POWER(1+$A45,{1,2,3,4,5}))+'DCF - FCFF'!$B$24*POWER(1+'DCF - FCFF'!$D$24,5)*(1+J$41)/($A45-J$41)/POWER(1+$A45,5)-'DCF - FCFF'!$O$24)/'DCF - FCFF'!$Q$24)
A46: ='DCF - FCFF'!$E$24+0.0 | B46: =IF($A46-B$41<0.01,NA(),('DCF - FCFF'!$B$24*SUMPRODUCT(POWER(1+'DCF - FCFF'!$D$24,{1,2,3,4,5})/POWER(1+$A46,{1,2,3,4,5}))+'DCF - FCFF'!$B$24*POWER(1+'DCF - FCFF'!$D$24,5)*(1+B$41)/($A46-B$41)/POWER(1+$A46,5)-'DCF - FCFF'!$O$24)/'DCF - FCFF'!$Q$24) | C46: =IF($A46-C$41<0.01,NA(),('DCF - FCFF'!$B$24*SUMPRODUCT(POWER(1+'DCF - FCFF'!$D$24,{1,2,3,4,5})/POWER(1+$A46,{1,2,3,4,5}))+'DCF - FCFF'!$B$24*POWER(1+'DCF - FCFF'!$D$24,5)*(1+C$41)/($A46-C$41)/POWER(1+$A46,5)-'DCF - FCFF'!$O$24)/'DCF - FCFF'!$Q$24) | D46: =IF($A46-D$41<0.01,NA(),('DCF - FCFF'!$B$24*SUMPRODUCT(POWER(1+'DCF - FCFF'!$D$24,{1,2,3,4,5})/POWER(1+$A46,{1,2,3,4,5}))+'DCF - FCFF'!$B$24*POWER(1+'DCF - FCFF'!$D$24,5)*(1+D$41)/($A46-D$41)/POWER(1+$A46,5)-'DCF - FCFF'!$O$24)/'DCF - FCFF'!$Q$24) | E46: =IF($A46-E$41<0.01,NA(),('DCF - FCFF'!$B$24*SUMPRODUCT(POWER(1+'DCF - FCFF'!$D$24,{1,2,3,4,5})/POWER(1+$A46,{1,2,3,4,5}))+'DCF - FCFF'!$B$24*POWER(1+'DCF - FCFF'!$D$24,5)*(1+E$41)/($A46-E$41)/POWER(1+$A46,5)-'DCF - FCFF'!$O$24)/'DCF - FCFF'!$Q$24) | F46: =IF($A46-F$41<0.01,NA(),('DCF - FCFF'!$B$24*SUMPRODUCT(POWER(1+'DCF - FCFF'!$D$24,{1,2,3,4,5})/POWER(1+$A46,{1,2,3,4,5}))+'DCF - FCFF'!$B$24*POWER(1+'DCF - FCFF'!$D$24,5)*(1+F$41)/($A46-F$41)/POWER(1+$A46,5)-'DCF - FCFF'!$O$24)/'DCF - FCFF'!$Q$24) | G46: =IF($A46-G$41<0.01,NA(),('DCF - FCFF'!$B$24*SUMPRODUCT(POWER(1+'DCF - FCFF'!$D$24,{1,2,3,4,5})/POWER(1+$A46,{1,2,3,4,5}))+'DCF - FCFF'!$B$24*POWER(1+'DCF - FCFF'!$D$24,5)*(1+G$41)/($A46-G$41)/POWER(1+$A46,5)-'DCF - FCFF'!$O$24)/'DCF - FCFF'!$Q$24) | H46: =IF($A46-H$41<0.01,NA(),('DCF - FCFF'!$B$24*SUMPRODUCT(POWER(1+'DCF - FCFF'!$D$24,{1,2,3,4,5})/POWER(1+$A46,{1,2,3,4,5}))+'DCF - FCFF'!$B$24*POWER(1+'DCF - FCFF'!$D$24,5)*(1+H$41)/($A46-H$41)/POWER(1+$A46,5)-'DCF - FCFF'!$O$24)/'DCF - FCFF'!$Q$24) | I46: =IF($A46-I$41<0.01,NA(),('DCF - FCFF'!$B$24*SUMPRODUCT(POWER(1+'DCF - FCFF'!$D$24,{1,2,3,4,5})/POWER(1+$A46,{1,2,3,4,5}))+'DCF - FCFF'!$B$24*POWER(1+'DCF - FCFF'!$D$24,5)*(1+I$41)/($A46-I$41)/POWER(1+$A46,5)-'DCF - FCFF'!$O$24)/'DCF - FCFF'!$Q$24) | J46: =IF($A46-J$41<0.01,NA(),('DCF - FCFF'!$B$24*SUMPRODUCT(POWER(1+'DCF - FCFF'!$D$24,{1,2,3,4,5})/POWER(1+$A46,{1,2,3,4,5}))+'DCF - FCFF'!$B$24*POWER(1+'DCF - FCFF'!$D$24,5)*(1+J$41)/($A46-J$41)/POWER(1+$A46,5)-'DCF - FCFF'!$O$24)/'DCF - FCFF'!$Q$24)
A47: ='DCF - FCFF'!$E$24+0.005 | B47: =IF($A47-B$41<0.01,NA(),('DCF - FCFF'!$B$24*SUMPRODUCT(POWER(1+'DCF - FCFF'!$D$24,{1,2,3,4,5})/POWER(1+$A47,{1,2,3,4,5}))+'DCF - FCFF'!$B$24*POWER(1+'DCF - FCFF'!$D$24,5)*(1+B$41)/($A47-B$41)/POWER(1+$A47,5)-'DCF - FCFF'!$O$24)/'DCF - FCFF'!$Q$24) | C47: =IF($A47-C$41<0.01,NA(),('DCF - FCFF'!$B$24*SUMPRODUCT(POWER(1+'DCF - FCFF'!$D$24,{1,2,3,4,5})/POWER(1+$A47,{1,2,3,4,5}))+'DCF - FCFF'!$B$24*POWER(1+'DCF - FCFF'!$D$24,5)*(1+C$41)/($A47-C$41)/POWER(1+$A47,5)-'DCF - FCFF'!$O$24)/'DCF - FCFF'!$Q$24) | D47: =IF($A47-D$41<0.01,NA(),('DCF - FCFF'!$B$24*SUMPRODUCT(POWER(1+'DCF - FCFF'!$D$24,{1,2,3,4,5})/POWER(1+$A47,{1,2,3,4,5}))+'DCF - FCFF'!$B$24*POWER(1+'DCF - FCFF'!$D$24,5)*(1+D$41)/($A47-D$41)/POWER(1+$A47,5)-'DCF - FCFF'!$O$24)/'DCF - FCFF'!$Q$24) | E47: =IF($A47-E$41<0.01,NA(),('DCF - FCFF'!$B$24*SUMPRODUCT(POWER(1+'DCF - FCFF'!$D$24,{1,2,3,4,5})/POWER(1+$A47,{1,2,3,4,5}))+'DCF - FCFF'!$B$24*POWER(1+'DCF - FCFF'!$D$24,5)*(1+E$41)/($A47-E$41)/POWER(1+$A47,5)-'DCF - FCFF'!$O$24)/'DCF - FCFF'!$Q$24) | F47: =IF($A47-F$41<0.01,NA(),('DCF - FCFF'!$B$24*SUMPRODUCT(POWER(1+'DCF - FCFF'!$D$24,{1,2,3,4,5})/POWER(1+$A47,{1,2,3,4,5}))+'DCF - FCFF'!$B$24*POWER(1+'DCF - FCFF'!$D$24,5)*(1+F$41)/($A47-F$41)/POWER(1+$A47,5)-'DCF - FCFF'!$O$24)/'DCF - FCFF'!$Q$24) | G47: =IF($A47-G$41<0.01,NA(),('DCF - FCFF'!$B$24*SUMPRODUCT(POWER(1+'DCF - FCFF'!$D$24,{1,2,3,4,5})/POWER(1+$A47,{1,2,3,4,5}))+'DCF - FCFF'!$B$24*POWER(1+'DCF - FCFF'!$D$24,5)*(1+G$41)/($A47-G$41)/POWER(1+$A47,5)-'DCF - FCFF'!$O$24)/'DCF - FCFF'!$Q$24) | H47: =IF($A47-H$41<0.01,NA(),('DCF - FCFF'!$B$24*SUMPRODUCT(POWER(1+'DCF - FCFF'!$D$24,{1,2,3,4,5})/POWER(1+$A47,{1,2,3,4,5}))+'DCF - FCFF'!$B$24*POWER(1+'DCF - FCFF'!$D$24,5)*(1+H$41)/($A47-H$41)/POWER(1+$A47,5)-'DCF - FCFF'!$O$24)/'DCF - FCFF'!$Q$24) | I47: =IF($A47-I$41<0.01,NA(),('DCF - FCFF'!$B$24*SUMPRODUCT(POWER(1+'DCF - FCFF'!$D$24,{1,2,3,4,5})/POWER(1+$A47,{1,2,3,4,5}))+'DCF - FCFF'!$B$24*POWER(1+'DCF - FCFF'!$D$24,5)*(1+I$41)/($A47-I$41)/POWER(1+$A47,5)-'DCF - FCFF'!$O$24)/'DCF - FCFF'!$Q$24) | J47: =IF($A47-J$41<0.01,NA(),('DCF - FCFF'!$B$24*SUMPRODUCT(POWER(1+'DCF - FCFF'!$D$24,{1,2,3,4,5})/POWER(1+$A47,{1,2,3,4,5}))+'DCF - FCFF'!$B$24*POWER(1+'DCF - FCFF'!$D$24,5)*(1+J$41)/($A47-J$41)/POWER(1+$A47,5)-'DCF - FCFF'!$O$24)/'DCF - FCFF'!$Q$24)
A48: ='DCF - FCFF'!$E$24+0.01 | B48: =IF($A48-B$41<0.01,NA(),('DCF - FCFF'!$B$24*SUMPRODUCT(POWER(1+'DCF - FCFF'!$D$24,{1,2,3,4,5})/POWER(1+$A48,{1,2,3,4,5}))+'DCF - FCFF'!$B$24*POWER(1+'DCF - FCFF'!$D$24,5)*(1+B$41)/($A48-B$41)/POWER(1+$A48,5)-'DCF - FCFF'!$O$24)/'DCF - FCFF'!$Q$24) | C48: =IF($A48-C$41<0.01,NA(),('DCF - FCFF'!$B$24*SUMPRODUCT(POWER(1+'DCF - FCFF'!$D$24,{1,2,3,4,5})/POWER(1+$A48,{1,2,3,4,5}))+'DCF - FCFF'!$B$24*POWER(1+'DCF - FCFF'!$D$24,5)*(1+C$41)/($A48-C$41)/POWER(1+$A48,5)-'DCF - FCFF'!$O$24)/'DCF - FCFF'!$Q$24) | D48: =IF($A48-D$41<0.01,NA(),('DCF - FCFF'!$B$24*SUMPRODUCT(POWER(1+'DCF - FCFF'!$D$24,{1,2,3,4,5})/POWER(1+$A48,{1,2,3,4,5}))+'DCF - FCFF'!$B$24*POWER(1+'DCF - FCFF'!$D$24,5)*(1+D$41)/($A48-D$41)/POWER(1+$A48,5)-'DCF - FCFF'!$O$24)/'DCF - FCFF'!$Q$24) | E48: =IF($A48-E$41<0.01,NA(),('DCF - FCFF'!$B$24*SUMPRODUCT(POWER(1+'DCF - FCFF'!$D$24,{1,2,3,4,5})/POWER(1+$A48,{1,2,3,4,5}))+'DCF - FCFF'!$B$24*POWER(1+'DCF - FCFF'!$D$24,5)*(1+E$41)/($A48-E$41)/POWER(1+$A48,5)-'DCF - FCFF'!$O$24)/'DCF - FCFF'!$Q$24) | F48: =IF($A48-F$41<0.01,NA(),('DCF - FCFF'!$B$24*SUMPRODUCT(POWER(1+'DCF - FCFF'!$D$24,{1,2,3,4,5})/POWER(1+$A48,{1,2,3,4,5}))+'DCF - FCFF'!$B$24*POWER(1+'DCF - FCFF'!$D$24,5)*(1+F$41)/($A48-F$41)/POWER(1+$A48,5)-'DCF - FCFF'!$O$24)/'DCF - FCFF'!$Q$24) | G48: =IF($A48-G$41<0.01,NA(),('DCF - FCFF'!$B$24*SUMPRODUCT(POWER(1+'DCF - FCFF'!$D$24,{1,2,3,4,5})/POWER(1+$A48,{1,2,3,4,5}))+'DCF - FCFF'!$B$24*POWER(1+'DCF - FCFF'!$D$24,5)*(1+G$41)/($A48-G$41)/POWER(1+$A48,5)-'DCF - FCFF'!$O$24)/'DCF - FCFF'!$Q$24) | H48: =IF($A48-H$41<0.01,NA(),('DCF - FCFF'!$B$24*SUMPRODUCT(POWER(1+'DCF - FCFF'!$D$24,{1,2,3,4,5})/POWER(1+$A48,{1,2,3,4,5}))+'DCF - FCFF'!$B$24*POWER(1+'DCF - FCFF'!$D$24,5)*(1+H$41)/($A48-H$41)/POWER(1+$A48,5)-'DCF - FCFF'!$O$24)/'DCF - FCFF'!$Q$24) | I48: =IF($A48-I$41<0.01,NA(),('DCF - FCFF'!$B$24*SUMPRODUCT(POWER(1+'DCF - FCFF'!$D$24,{1,2,3,4,5})/POWER(1+$A48,{1,2,3,4,5}))+'DCF - FCFF'!$B$24*POWER(1+'DCF - FCFF'!$D$24,5)*(1+I$41)/($A48-I$41)/POWER(1+$A48,5)-'DCF - FCFF'!$O$24)/'DCF - FCFF'!$Q$24) | J48: =IF($A48-J$41<0.01,NA(),('DCF - FCFF'!$B$24*SUMPRODUCT(POWER(1+'DCF - FCFF'!$D$24,{1,2,3,4,5})/POWER(1+$A48,{1,2,3,4,5}))+'DCF - FCFF'!$B$24*POWER(1+'DCF - FCFF'!$D$24,5)*(1+J$41)/($A48-J$41)/POWER(1+$A48,5)-'DCF - FCFF'!$O$24)/'DCF - FCFF'!$Q$24)
A49: ='DCF - FCFF'!$E$24+0.015 | B49: =IF($A49-B$41<0.01,NA(),('DCF - FCFF'!$B$24*SUMPRODUCT(POWER(1+'DCF - FCFF'!$D$24,{1,2,3,4,5})/POWER(1+$A49,{1,2,3,4,5}))+'DCF - FCFF'!$B$24*POWER(1+'DCF - FCFF'!$D$24,5)*(1+B$41)/($A49-B$41)/POWER(1+$A49,5)-'DCF - FCFF'!$O$24)/'DCF - FCFF'!$Q$24) | C49: =IF($A49-C$41<0.01,NA(),('DCF - FCFF'!$B$24*SUMPRODUCT(POWER(1+'DCF - FCFF'!$D$24,{1,2,3,4,5})/POWER(1+$A49,{1,2,3,4,5}))+'DCF - FCFF'!$B$24*POWER(1+'DCF - FCFF'!$D$24,5)*(1+C$41)/($A49-C$41)/POWER(1+$A49,5)-'DCF - FCFF'!$O$24)/'DCF - FCFF'!$Q$24) | D49: =IF($A49-D$41<0.01,NA(),('DCF - FCFF'!$B$24*SUMPRODUCT(POWER(1+'DCF - FCFF'!$D$24,{1,2,3,4,5})/POWER(1+$A49,{1,2,3,4,5}))+'DCF - FCFF'!$B$24*POWER(1+'DCF - FCFF'!$D$24,5)*(1+D$41)/($A49-D$41)/POWER(1+$A49,5)-'DCF - FCFF'!$O$24)/'DCF - FCFF'!$Q$24) | E49: =IF($A49-E$41<0.01,NA(),('DCF - FCFF'!$B$24*SUMPRODUCT(POWER(1+'DCF - FCFF'!$D$24,{1,2,3,4,5})/POWER(1+$A49,{1,2,3,4,5}))+'DCF - FCFF'!$B$24*POWER(1+'DCF - FCFF'!$D$24,5)*(1+E$41)/($A49-E$41)/POWER(1+$A49,5)-'DCF - FCFF'!$O$24)/'DCF - FCFF'!$Q$24) | F49: =IF($A49-F$41<0.01,NA(),('DCF - FCFF'!$B$24*SUMPRODUCT(POWER(1+'DCF - FCFF'!$D$24,{1,2,3,4,5})/POWER(1+$A49,{1,2,3,4,5}))+'DCF - FCFF'!$B$24*POWER(1+'DCF - FCFF'!$D$24,5)*(1+F$41)/($A49-F$41)/POWER(1+$A49,5)-'DCF - FCFF'!$O$24)/'DCF - FCFF'!$Q$24) | G49: =IF($A49-G$41<0.01,NA(),('DCF - FCFF'!$B$24*SUMPRODUCT(POWER(1+'DCF - FCFF'!$D$24,{1,2,3,4,5})/POWER(1+$A49,{1,2,3,4,5}))+'DCF - FCFF'!$B$24*POWER(1+'DCF - FCFF'!$D$24,5)*(1+G$41)/($A49-G$41)/POWER(1+$A49,5)-'DCF - FCFF'!$O$24)/'DCF - FCFF'!$Q$24) | H49: =IF($A49-H$41<0.01,NA(),('DCF - FCFF'!$B$24*SUMPRODUCT(POWER(1+'DCF - FCFF'!$D$24,{1,2,3,4,5})/POWER(1+$A49,{1,2,3,4,5}))+'DCF - FCFF'!$B$24*POWER(1+'DCF - FCFF'!$D$24,5)*(1+H$41)/($A49-H$41)/POWER(1+$A49,5)-'DCF - FCFF'!$O$24)/'DCF - FCFF'!$Q$24) | I49: =IF($A49-I$41<0.01,NA(),('DCF - FCFF'!$B$24*SUMPRODUCT(POWER(1+'DCF - FCFF'!$D$24,{1,2,3,4,5})/POWER(1+$A49,{1,2,3,4,5}))+'DCF - FCFF'!$B$24*POWER(1+'DCF - FCFF'!$D$24,5)*(1+I$41)/($A49-I$41)/POWER(1+$A49,5)-'DCF - FCFF'!$O$24)/'DCF - FCFF'!$Q$24) | J49: =IF($A49-J$41<0.01,NA(),('DCF - FCFF'!$B$24*SUMPRODUCT(POWER(1+'DCF - FCFF'!$D$24,{1,2,3,4,5})/POWER(1+$A49,{1,2,3,4,5}))+'DCF - FCFF'!$B$24*POWER(1+'DCF - FCFF'!$D$24,5)*(1+J$41)/($A49-J$41)/POWER(1+$A49,5)-'DCF - FCFF'!$O$24)/'DCF - FCFF'!$Q$24)
A50: ='DCF - FCFF'!$E$24+0.02 | B50: =IF($A50-B$41<0.01,NA(),('DCF - FCFF'!$B$24*SUMPRODUCT(POWER(1+'DCF - FCFF'!$D$24,{1,2,3,4,5})/POWER(1+$A50,{1,2,3,4,5}))+'DCF - FCFF'!$B$24*POWER(1+'DCF - FCFF'!$D$24,5)*(1+B$41)/($A50-B$41)/POWER(1+$A50,5)-'DCF - FCFF'!$O$24)/'DCF - FCFF'!$Q$24) | C50: =IF($A50-C$41<0.01,NA(),('DCF - FCFF'!$B$24*SUMPRODUCT(POWER(1+'DCF - FCFF'!$D$24,{1,2,3,4,5})/POWER(1+$A50,{1,2,3,4,5}))+'DCF - FCFF'!$B$24*POWER(1+'DCF - FCFF'!$D$24,5)*(1+C$41)/($A50-C$41)/POWER(1+$A50,5)-'DCF - FCFF'!$O$24)/'DCF - FCFF'!$Q$24) | D50: =IF($A50-D$41<0.01,NA(),('DCF - FCFF'!$B$24*SUMPRODUCT(POWER(1+'DCF - FCFF'!$D$24,{1,2,3,4,5})/POWER(1+$A50,{1,2,3,4,5}))+'DCF - FCFF'!$B$24*POWER(1+'DCF - FCFF'!$D$24,5)*(1+D$41)/($A50-D$41)/POWER(1+$A50,5)-'DCF - FCFF'!$O$24)/'DCF - FCFF'!$Q$24) | E50: =IF($A50-E$41<0.01,NA(),('DCF - FCFF'!$B$24*SUMPRODUCT(POWER(1+'DCF - FCFF'!$D$24,{1,2,3,4,5})/POWER(1+$A50,{1,2,3,4,5}))+'DCF - FCFF'!$B$24*POWER(1+'DCF - FCFF'!$D$24,5)*(1+E$41)/($A50-E$41)/POWER(1+$A50,5)-'DCF - FCFF'!$O$24)/'DCF - FCFF'!$Q$24) | F50: =IF($A50-F$41<0.01,NA(),('DCF - FCFF'!$B$24*SUMPRODUCT(POWER(1+'DCF - FCFF'!$D$24,{1,2,3,4,5})/POWER(1+$A50,{1,2,3,4,5}))+'DCF - FCFF'!$B$24*POWER(1+'DCF - FCFF'!$D$24,5)*(1+F$41)/($A50-F$41)/POWER(1+$A50,5)-'DCF - FCFF'!$O$24)/'DCF - FCFF'!$Q$24) | G50: =IF($A50-G$41<0.01,NA(),('DCF - FCFF'!$B$24*SUMPRODUCT(POWER(1+'DCF - FCFF'!$D$24,{1,2,3,4,5})/POWER(1+$A50,{1,2,3,4,5}))+'DCF - FCFF'!$B$24*POWER(1+'DCF - FCFF'!$D$24,5)*(1+G$41)/($A50-G$41)/POWER(1+$A50,5)-'DCF - FCFF'!$O$24)/'DCF - FCFF'!$Q$24) | H50: =IF($A50-H$41<0.01,NA(),('DCF - FCFF'!$B$24*SUMPRODUCT(POWER(1+'DCF - FCFF'!$D$24,{1,2,3,4,5})/POWER(1+$A50,{1,2,3,4,5}))+'DCF - FCFF'!$B$24*POWER(1+'DCF - FCFF'!$D$24,5)*(1+H$41)/($A50-H$41)/POWER(1+$A50,5)-'DCF - FCFF'!$O$24)/'DCF - FCFF'!$Q$24) | I50: =IF($A50-I$41<0.01,NA(),('DCF - FCFF'!$B$24*SUMPRODUCT(POWER(1+'DCF - FCFF'!$D$24,{1,2,3,4,5})/POWER(1+$A50,{1,2,3,4,5}))+'DCF - FCFF'!$B$24*POWER(1+'DCF - FCFF'!$D$24,5)*(1+I$41)/($A50-I$41)/POWER(1+$A50,5)-'DCF - FCFF'!$O$24)/'DCF - FCFF'!$Q$24) | J50: =IF($A50-J$41<0.01,NA(),('DCF - FCFF'!$B$24*SUMPRODUCT(POWER(1+'DCF - FCFF'!$D$24,{1,2,3,4,5})/POWER(1+$A50,{1,2,3,4,5}))+'DCF - FCFF'!$B$24*POWER(1+'DCF - FCFF'!$D$24,5)*(1+J$41)/($A50-J$41)/POWER(1+$A50,5)-'DCF - FCFF'!$O$24)/'DCF - FCFF'!$Q$24)
A52: Colgate | B52: ='Market Data'!$C$6 | C52: ← market price · rows: WACC · cols: terminal g
B53: 0.01 | C53: 0.015 | D53: 0.02 | E53: 0.025 | F53: 0.03 | G53: 0.035 | H53: 0.04 | I53: 0.045 | J53: 0.05
A54: ='DCF - FCFF'!$E$25-0.02 | B54: =IF($A54-B$53<0.01,NA(),('DCF - FCFF'!$B$25*SUMPRODUCT(POWER(1+'DCF - FCFF'!$D$25,{1,2,3,4,5})/POWER(1+$A54,{1,2,3,4,5}))+'DCF - FCFF'!$B$25*POWER(1+'DCF - FCFF'!$D$25,5)*(1+B$53)/($A54-B$53)/POWER(1+$A54,5)-'DCF - FCFF'!$O$25)/'DCF - FCFF'!$Q$25) | C54: =IF($A54-C$53<0.01,NA(),('DCF - FCFF'!$B$25*SUMPRODUCT(POWER(1+'DCF - FCFF'!$D$25,{1,2,3,4,5})/POWER(1+$A54,{1,2,3,4,5}))+'DCF - FCFF'!$B$25*POWER(1+'DCF - FCFF'!$D$25,5)*(1+C$53)/($A54-C$53)/POWER(1+$A54,5)-'DCF - FCFF'!$O$25)/'DCF - FCFF'!$Q$25) | D54: =IF($A54-D$53<0.01,NA(),('DCF - FCFF'!$B$25*SUMPRODUCT(POWER(1+'DCF - FCFF'!$D$25,{1,2,3,4,5})/POWER(1+$A54,{1,2,3,4,5}))+'DCF - FCFF'!$B$25*POWER(1+'DCF - FCFF'!$D$25,5)*(1+D$53)/($A54-D$53)/POWER(1+$A54,5)-'DCF - FCFF'!$O$25)/'DCF - FCFF'!$Q$25) | E54: =IF($A54-E$53<0.01,NA(),('DCF - FCFF'!$B$25*SUMPRODUCT(POWER(1+'DCF - FCFF'!$D$25,{1,2,3,4,5})/POWER(1+$A54,{1,2,3,4,5}))+'DCF - FCFF'!$B$25*POWER(1+'DCF - FCFF'!$D$25,5)*(1+E$53)/($A54-E$53)/POWER(1+$A54,5)-'DCF - FCFF'!$O$25)/'DCF - FCFF'!$Q$25) | F54: =IF($A54-F$53<0.01,NA(),('DCF - FCFF'!$B$25*SUMPRODUCT(POWER(1+'DCF - FCFF'!$D$25,{1,2,3,4,5})/POWER(1+$A54,{1,2,3,4,5}))+'DCF - FCFF'!$B$25*POWER(1+'DCF - FCFF'!$D$25,5)*(1+F$53)/($A54-F$53)/POWER(1+$A54,5)-'DCF - FCFF'!$O$25)/'DCF - FCFF'!$Q$25) | G54: =IF($A54-G$53<0.01,NA(),('DCF - FCFF'!$B$25*SUMPRODUCT(POWER(1+'DCF - FCFF'!$D$25,{1,2,3,4,5})/POWER(1+$A54,{1,2,3,4,5}))+'DCF - FCFF'!$B$25*POWER(1+'DCF - FCFF'!$D$25,5)*(1+G$53)/($A54-G$53)/POWER(1+$A54,5)-'DCF - FCFF'!$O$25)/'DCF - FCFF'!$Q$25) | H54: =IF($A54-H$53<0.01,NA(),('DCF - FCFF'!$B$25*SUMPRODUCT(POWER(1+'DCF - FCFF'!$D$25,{1,2,3,4,5})/POWER(1+$A54,{1,2,3,4,5}))+'DCF - FCFF'!$B$25*POWER(1+'DCF - FCFF'!$D$25,5)*(1+H$53)/($A54-H$53)/POWER(1+$A54,5)-'DCF - FCFF'!$O$25)/'DCF - FCFF'!$Q$25) | I54: =IF($A54-I$53<0.01,NA(),('DCF - FCFF'!$B$25*SUMPRODUCT(POWER(1+'DCF - FCFF'!$D$25,{1,2,3,4,5})/POWER(1+$A54,{1,2,3,4,5}))+'DCF - FCFF'!$B$25*POWER(1+'DCF - FCFF'!$D$25,5)*(1+I$53)/($A54-I$53)/POWER(1+$A54,5)-'DCF - FCFF'!$O$25)/'DCF - FCFF'!$Q$25) | J54: =IF($A54-J$53<0.01,NA(),('DCF - FCFF'!$B$25*SUMPRODUCT(POWER(1+'DCF - FCFF'!$D$25,{1,2,3,4,5})/POWER(1+$A54,{1,2,3,4,5}))+'DCF - FCFF'!$B$25*POWER(1+'DCF - FCFF'!$D$25,5)*(1+J$53)/($A54-J$53)/POWER(1+$A54,5)-'DCF - FCFF'!$O$25)/'DCF - FCFF'!$Q$25)
A55: ='DCF - FCFF'!$E$25-0.015 | B55: =IF($A55-B$53<0.01,NA(),('DCF - FCFF'!$B$25*SUMPRODUCT(POWER(1+'DCF - FCFF'!$D$25,{1,2,3,4,5})/POWER(1+$A55,{1,2,3,4,5}))+'DCF - FCFF'!$B$25*POWER(1+'DCF - FCFF'!$D$25,5)*(1+B$53)/($A55-B$53)/POWER(1+$A55,5)-'DCF - FCFF'!$O$25)/'DCF - FCFF'!$Q$25) | C55: =IF($A55-C$53<0.01,NA(),('DCF - FCFF'!$B$25*SUMPRODUCT(POWER(1+'DCF - FCFF'!$D$25,{1,2,3,4,5})/POWER(1+$A55,{1,2,3,4,5}))+'DCF - FCFF'!$B$25*POWER(1+'DCF - FCFF'!$D$25,5)*(1+C$53)/($A55-C$53)/POWER(1+$A55,5)-'DCF - FCFF'!$O$25)/'DCF - FCFF'!$Q$25) | D55: =IF($A55-D$53<0.01,NA(),('DCF - FCFF'!$B$25*SUMPRODUCT(POWER(1+'DCF - FCFF'!$D$25,{1,2,3,4,5})/POWER(1+$A55,{1,2,3,4,5}))+'DCF - FCFF'!$B$25*POWER(1+'DCF - FCFF'!$D$25,5)*(1+D$53)/($A55-D$53)/POWER(1+$A55,5)-'DCF - FCFF'!$O$25)/'DCF - FCFF'!$Q$25) | E55: =IF($A55-E$53<0.01,NA(),('DCF - FCFF'!$B$25*SUMPRODUCT(POWER(1+'DCF - FCFF'!$D$25,{1,2,3,4,5})/POWER(1+$A55,{1,2,3,4,5}))+'DCF - FCFF'!$B$25*POWER(1+'DCF - FCFF'!$D$25,5)*(1+E$53)/($A55-E$53)/POWER(1+$A55,5)-'DCF - FCFF'!$O$25)/'DCF - FCFF'!$Q$25) | F55: =IF($A55-F$53<0.01,NA(),('DCF - FCFF'!$B$25*SUMPRODUCT(POWER(1+'DCF - FCFF'!$D$25,{1,2,3,4,5})/POWER(1+$A55,{1,2,3,4,5}))+'DCF - FCFF'!$B$25*POWER(1+'DCF - FCFF'!$D$25,5)*(1+F$53)/($A55-F$53)/POWER(1+$A55,5)-'DCF - FCFF'!$O$25)/'DCF - FCFF'!$Q$25) | G55: =IF($A55-G$53<0.01,NA(),('DCF - FCFF'!$B$25*SUMPRODUCT(POWER(1+'DCF - FCFF'!$D$25,{1,2,3,4,5})/POWER(1+$A55,{1,2,3,4,5}))+'DCF - FCFF'!$B$25*POWER(1+'DCF - FCFF'!$D$25,5)*(1+G$53)/($A55-G$53)/POWER(1+$A55,5)-'DCF - FCFF'!$O$25)/'DCF - FCFF'!$Q$25) | H55: =IF($A55-H$53<0.01,NA(),('DCF - FCFF'!$B$25*SUMPRODUCT(POWER(1+'DCF - FCFF'!$D$25,{1,2,3,4,5})/POWER(1+$A55,{1,2,3,4,5}))+'DCF - FCFF'!$B$25*POWER(1+'DCF - FCFF'!$D$25,5)*(1+H$53)/($A55-H$53)/POWER(1+$A55,5)-'DCF - FCFF'!$O$25)/'DCF - FCFF'!$Q$25) | I55: =IF($A55-I$53<0.01,NA(),('DCF - FCFF'!$B$25*SUMPRODUCT(POWER(1+'DCF - FCFF'!$D$25,{1,2,3,4,5})/POWER(1+$A55,{1,2,3,4,5}))+'DCF - FCFF'!$B$25*POWER(1+'DCF - FCFF'!$D$25,5)*(1+I$53)/($A55-I$53)/POWER(1+$A55,5)-'DCF - FCFF'!$O$25)/'DCF - FCFF'!$Q$25) | J55: =IF($A55-J$53<0.01,NA(),('DCF - FCFF'!$B$25*SUMPRODUCT(POWER(1+'DCF - FCFF'!$D$25,{1,2,3,4,5})/POWER(1+$A55,{1,2,3,4,5}))+'DCF - FCFF'!$B$25*POWER(1+'DCF - FCFF'!$D$25,5)*(1+J$53)/($A55-J$53)/POWER(1+$A55,5)-'DCF - FCFF'!$O$25)/'DCF - FCFF'!$Q$25)
A56: ='DCF - FCFF'!$E$25-0.01 | B56: =IF($A56-B$53<0.01,NA(),('DCF - FCFF'!$B$25*SUMPRODUCT(POWER(1+'DCF - FCFF'!$D$25,{1,2,3,4,5})/POWER(1+$A56,{1,2,3,4,5}))+'DCF - FCFF'!$B$25*POWER(1+'DCF - FCFF'!$D$25,5)*(1+B$53)/($A56-B$53)/POWER(1+$A56,5)-'DCF - FCFF'!$O$25)/'DCF - FCFF'!$Q$25) | C56: =IF($A56-C$53<0.01,NA(),('DCF - FCFF'!$B$25*SUMPRODUCT(POWER(1+'DCF - FCFF'!$D$25,{1,2,3,4,5})/POWER(1+$A56,{1,2,3,4,5}))+'DCF - FCFF'!$B$25*POWER(1+'DCF - FCFF'!$D$25,5)*(1+C$53)/($A56-C$53)/POWER(1+$A56,5)-'DCF - FCFF'!$O$25)/'DCF - FCFF'!$Q$25) | D56: =IF($A56-D$53<0.01,NA(),('DCF - FCFF'!$B$25*SUMPRODUCT(POWER(1+'DCF - FCFF'!$D$25,{1,2,3,4,5})/POWER(1+$A56,{1,2,3,4,5}))+'DCF - FCFF'!$B$25*POWER(1+'DCF - FCFF'!$D$25,5)*(1+D$53)/($A56-D$53)/POWER(1+$A56,5)-'DCF - FCFF'!$O$25)/'DCF - FCFF'!$Q$25) | E56: =IF($A56-E$53<0.01,NA(),('DCF - FCFF'!$B$25*SUMPRODUCT(POWER(1+'DCF - FCFF'!$D$25,{1,2,3,4,5})/POWER(1+$A56,{1,2,3,4,5}))+'DCF - FCFF'!$B$25*POWER(1+'DCF - FCFF'!$D$25,5)*(1+E$53)/($A56-E$53)/POWER(1+$A56,5)-'DCF - FCFF'!$O$25)/'DCF - FCFF'!$Q$25) | F56: =IF($A56-F$53<0.01,NA(),('DCF - FCFF'!$B$25*SUMPRODUCT(POWER(1+'DCF - FCFF'!$D$25,{1,2,3,4,5})/POWER(1+$A56,{1,2,3,4,5}))+'DCF - FCFF'!$B$25*POWER(1+'DCF - FCFF'!$D$25,5)*(1+F$53)/($A56-F$53)/POWER(1+$A56,5)-'DCF - FCFF'!$O$25)/'DCF - FCFF'!$Q$25) | G56: =IF($A56-G$53<0.01,NA(),('DCF - FCFF'!$B$25*SUMPRODUCT(POWER(1+'DCF - FCFF'!$D$25,{1,2,3,4,5})/POWER(1+$A56,{1,2,3,4,5}))+'DCF - FCFF'!$B$25*POWER(1+'DCF - FCFF'!$D$25,5)*(1+G$53)/($A56-G$53)/POWER(1+$A56,5)-'DCF - FCFF'!$O$25)/'DCF - FCFF'!$Q$25) | H56: =IF($A56-H$53<0.01,NA(),('DCF - FCFF'!$B$25*SUMPRODUCT(POWER(1+'DCF - FCFF'!$D$25,{1,2,3,4,5})/POWER(1+$A56,{1,2,3,4,5}))+'DCF - FCFF'!$B$25*POWER(1+'DCF - FCFF'!$D$25,5)*(1+H$53)/($A56-H$53)/POWER(1+$A56,5)-'DCF - FCFF'!$O$25)/'DCF - FCFF'!$Q$25) | I56: =IF($A56-I$53<0.01,NA(),('DCF - FCFF'!$B$25*SUMPRODUCT(POWER(1+'DCF - FCFF'!$D$25,{1,2,3,4,5})/POWER(1+$A56,{1,2,3,4,5}))+'DCF - FCFF'!$B$25*POWER(1+'DCF - FCFF'!$D$25,5)*(1+I$53)/($A56-I$53)/POWER(1+$A56,5)-'DCF - FCFF'!$O$25)/'DCF - FCFF'!$Q$25) | J56: =IF($A56-J$53<0.01,NA(),('DCF - FCFF'!$B$25*SUMPRODUCT(POWER(1+'DCF - FCFF'!$D$25,{1,2,3,4,5})/POWER(1+$A56,{1,2,3,4,5}))+'DCF - FCFF'!$B$25*POWER(1+'DCF - FCFF'!$D$25,5)*(1+J$53)/($A56-J$53)/POWER(1+$A56,5)-'DCF - FCFF'!$O$25)/'DCF - FCFF'!$Q$25)
A57: ='DCF - FCFF'!$E$25-0.005 | B57: =IF($A57-B$53<0.01,NA(),('DCF - FCFF'!$B$25*SUMPRODUCT(POWER(1+'DCF - FCFF'!$D$25,{1,2,3,4,5})/POWER(1+$A57,{1,2,3,4,5}))+'DCF - FCFF'!$B$25*POWER(1+'DCF - FCFF'!$D$25,5)*(1+B$53)/($A57-B$53)/POWER(1+$A57,5)-'DCF - FCFF'!$O$25)/'DCF - FCFF'!$Q$25) | C57: =IF($A57-C$53<0.01,NA(),('DCF - FCFF'!$B$25*SUMPRODUCT(POWER(1+'DCF - FCFF'!$D$25,{1,2,3,4,5})/POWER(1+$A57,{1,2,3,4,5}))+'DCF - FCFF'!$B$25*POWER(1+'DCF - FCFF'!$D$25,5)*(1+C$53)/($A57-C$53)/POWER(1+$A57,5)-'DCF - FCFF'!$O$25)/'DCF - FCFF'!$Q$25) | D57: =IF($A57-D$53<0.01,NA(),('DCF - FCFF'!$B$25*SUMPRODUCT(POWER(1+'DCF - FCFF'!$D$25,{1,2,3,4,5})/POWER(1+$A57,{1,2,3,4,5}))+'DCF - FCFF'!$B$25*POWER(1+'DCF - FCFF'!$D$25,5)*(1+D$53)/($A57-D$53)/POWER(1+$A57,5)-'DCF - FCFF'!$O$25)/'DCF - FCFF'!$Q$25) | E57: =IF($A57-E$53<0.01,NA(),('DCF - FCFF'!$B$25*SUMPRODUCT(POWER(1+'DCF - FCFF'!$D$25,{1,2,3,4,5})/POWER(1+$A57,{1,2,3,4,5}))+'DCF - FCFF'!$B$25*POWER(1+'DCF - FCFF'!$D$25,5)*(1+E$53)/($A57-E$53)/POWER(1+$A57,5)-'DCF - FCFF'!$O$25)/'DCF - FCFF'!$Q$25) | F57: =IF($A57-F$53<0.01,NA(),('DCF - FCFF'!$B$25*SUMPRODUCT(POWER(1+'DCF - FCFF'!$D$25,{1,2,3,4,5})/POWER(1+$A57,{1,2,3,4,5}))+'DCF - FCFF'!$B$25*POWER(1+'DCF - FCFF'!$D$25,5)*(1+F$53)/($A57-F$53)/POWER(1+$A57,5)-'DCF - FCFF'!$O$25)/'DCF - FCFF'!$Q$25) | G57: =IF($A57-G$53<0.01,NA(),('DCF - FCFF'!$B$25*SUMPRODUCT(POWER(1+'DCF - FCFF'!$D$25,{1,2,3,4,5})/POWER(1+$A57,{1,2,3,4,5}))+'DCF - FCFF'!$B$25*POWER(1+'DCF - FCFF'!$D$25,5)*(1+G$53)/($A57-G$53)/POWER(1+$A57,5)-'DCF - FCFF'!$O$25)/'DCF - FCFF'!$Q$25) | H57: =IF($A57-H$53<0.01,NA(),('DCF - FCFF'!$B$25*SUMPRODUCT(POWER(1+'DCF - FCFF'!$D$25,{1,2,3,4,5})/POWER(1+$A57,{1,2,3,4,5}))+'DCF - FCFF'!$B$25*POWER(1+'DCF - FCFF'!$D$25,5)*(1+H$53)/($A57-H$53)/POWER(1+$A57,5)-'DCF - FCFF'!$O$25)/'DCF - FCFF'!$Q$25) | I57: =IF($A57-I$53<0.01,NA(),('DCF - FCFF'!$B$25*SUMPRODUCT(POWER(1+'DCF - FCFF'!$D$25,{1,2,3,4,5})/POWER(1+$A57,{1,2,3,4,5}))+'DCF - FCFF'!$B$25*POWER(1+'DCF - FCFF'!$D$25,5)*(1+I$53)/($A57-I$53)/POWER(1+$A57,5)-'DCF - FCFF'!$O$25)/'DCF - FCFF'!$Q$25) | J57: =IF($A57-J$53<0.01,NA(),('DCF - FCFF'!$B$25*SUMPRODUCT(POWER(1+'DCF - FCFF'!$D$25,{1,2,3,4,5})/POWER(1+$A57,{1,2,3,4,5}))+'DCF - FCFF'!$B$25*POWER(1+'DCF - FCFF'!$D$25,5)*(1+J$53)/($A57-J$53)/POWER(1+$A57,5)-'DCF - FCFF'!$O$25)/'DCF - FCFF'!$Q$25)
A58: ='DCF - FCFF'!$E$25+0.0 | B58: =IF($A58-B$53<0.01,NA(),('DCF - FCFF'!$B$25*SUMPRODUCT(POWER(1+'DCF - FCFF'!$D$25,{1,2,3,4,5})/POWER(1+$A58,{1,2,3,4,5}))+'DCF - FCFF'!$B$25*POWER(1+'DCF - FCFF'!$D$25,5)*(1+B$53)/($A58-B$53)/POWER(1+$A58,5)-'DCF - FCFF'!$O$25)/'DCF - FCFF'!$Q$25) | C58: =IF($A58-C$53<0.01,NA(),('DCF - FCFF'!$B$25*SUMPRODUCT(POWER(1+'DCF - FCFF'!$D$25,{1,2,3,4,5})/POWER(1+$A58,{1,2,3,4,5}))+'DCF - FCFF'!$B$25*POWER(1+'DCF - FCFF'!$D$25,5)*(1+C$53)/($A58-C$53)/POWER(1+$A58,5)-'DCF - FCFF'!$O$25)/'DCF - FCFF'!$Q$25) | D58: =IF($A58-D$53<0.01,NA(),('DCF - FCFF'!$B$25*SUMPRODUCT(POWER(1+'DCF - FCFF'!$D$25,{1,2,3,4,5})/POWER(1+$A58,{1,2,3,4,5}))+'DCF - FCFF'!$B$25*POWER(1+'DCF - FCFF'!$D$25,5)*(1+D$53)/($A58-D$53)/POWER(1+$A58,5)-'DCF - FCFF'!$O$25)/'DCF - FCFF'!$Q$25) | E58: =IF($A58-E$53<0.01,NA(),('DCF - FCFF'!$B$25*SUMPRODUCT(POWER(1+'DCF - FCFF'!$D$25,{1,2,3,4,5})/POWER(1+$A58,{1,2,3,4,5}))+'DCF - FCFF'!$B$25*POWER(1+'DCF - FCFF'!$D$25,5)*(1+E$53)/($A58-E$53)/POWER(1+$A58,5)-'DCF - FCFF'!$O$25)/'DCF - FCFF'!$Q$25) | F58: =IF($A58-F$53<0.01,NA(),('DCF - FCFF'!$B$25*SUMPRODUCT(POWER(1+'DCF - FCFF'!$D$25,{1,2,3,4,5})/POWER(1+$A58,{1,2,3,4,5}))+'DCF - FCFF'!$B$25*POWER(1+'DCF - FCFF'!$D$25,5)*(1+F$53)/($A58-F$53)/POWER(1+$A58,5)-'DCF - FCFF'!$O$25)/'DCF - FCFF'!$Q$25) | G58: =IF($A58-G$53<0.01,NA(),('DCF - FCFF'!$B$25*SUMPRODUCT(POWER(1+'DCF - FCFF'!$D$25,{1,2,3,4,5})/POWER(1+$A58,{1,2,3,4,5}))+'DCF - FCFF'!$B$25*POWER(1+'DCF - FCFF'!$D$25,5)*(1+G$53)/($A58-G$53)/POWER(1+$A58,5)-'DCF - FCFF'!$O$25)/'DCF - FCFF'!$Q$25) | H58: =IF($A58-H$53<0.01,NA(),('DCF - FCFF'!$B$25*SUMPRODUCT(POWER(1+'DCF - FCFF'!$D$25,{1,2,3,4,5})/POWER(1+$A58,{1,2,3,4,5}))+'DCF - FCFF'!$B$25*POWER(1+'DCF - FCFF'!$D$25,5)*(1+H$53)/($A58-H$53)/POWER(1+$A58,5)-'DCF - FCFF'!$O$25)/'DCF - FCFF'!$Q$25) | I58: =IF($A58-I$53<0.01,NA(),('DCF - FCFF'!$B$25*SUMPRODUCT(POWER(1+'DCF - FCFF'!$D$25,{1,2,3,4,5})/POWER(1+$A58,{1,2,3,4,5}))+'DCF - FCFF'!$B$25*POWER(1+'DCF - FCFF'!$D$25,5)*(1+I$53)/($A58-I$53)/POWER(1+$A58,5)-'DCF - FCFF'!$O$25)/'DCF - FCFF'!$Q$25) | J58: =IF($A58-J$53<0.01,NA(),('DCF - FCFF'!$B$25*SUMPRODUCT(POWER(1+'DCF - FCFF'!$D$25,{1,2,3,4,5})/POWER(1+$A58,{1,2,3,4,5}))+'DCF - FCFF'!$B$25*POWER(1+'DCF - FCFF'!$D$25,5)*(1+J$53)/($A58-J$53)/POWER(1+$A58,5)-'DCF - FCFF'!$O$25)/'DCF - FCFF'!$Q$25)
A59: ='DCF - FCFF'!$E$25+0.005 | B59: =IF($A59-B$53<0.01,NA(),('DCF - FCFF'!$B$25*SUMPRODUCT(POWER(1+'DCF - FCFF'!$D$25,{1,2,3,4,5})/POWER(1+$A59,{1,2,3,4,5}))+'DCF - FCFF'!$B$25*POWER(1+'DCF - FCFF'!$D$25,5)*(1+B$53)/($A59-B$53)/POWER(1+$A59,5)-'DCF - FCFF'!$O$25)/'DCF - FCFF'!$Q$25) | C59: =IF($A59-C$53<0.01,NA(),('DCF - FCFF'!$B$25*SUMPRODUCT(POWER(1+'DCF - FCFF'!$D$25,{1,2,3,4,5})/POWER(1+$A59,{1,2,3,4,5}))+'DCF - FCFF'!$B$25*POWER(1+'DCF - FCFF'!$D$25,5)*(1+C$53)/($A59-C$53)/POWER(1+$A59,5)-'DCF - FCFF'!$O$25)/'DCF - FCFF'!$Q$25) | D59: =IF($A59-D$53<0.01,NA(),('DCF - FCFF'!$B$25*SUMPRODUCT(POWER(1+'DCF - FCFF'!$D$25,{1,2,3,4,5})/POWER(1+$A59,{1,2,3,4,5}))+'DCF - FCFF'!$B$25*POWER(1+'DCF - FCFF'!$D$25,5)*(1+D$53)/($A59-D$53)/POWER(1+$A59,5)-'DCF - FCFF'!$O$25)/'DCF - FCFF'!$Q$25) | E59: =IF($A59-E$53<0.01,NA(),('DCF - FCFF'!$B$25*SUMPRODUCT(POWER(1+'DCF - FCFF'!$D$25,{1,2,3,4,5})/POWER(1+$A59,{1,2,3,4,5}))+'DCF - FCFF'!$B$25*POWER(1+'DCF - FCFF'!$D$25,5)*(1+E$53)/($A59-E$53)/POWER(1+$A59,5)-'DCF - FCFF'!$O$25)/'DCF - FCFF'!$Q$25) | F59: =IF($A59-F$53<0.01,NA(),('DCF - FCFF'!$B$25*SUMPRODUCT(POWER(1+'DCF - FCFF'!$D$25,{1,2,3,4,5})/POWER(1+$A59,{1,2,3,4,5}))+'DCF - FCFF'!$B$25*POWER(1+'DCF - FCFF'!$D$25,5)*(1+F$53)/($A59-F$53)/POWER(1+$A59,5)-'DCF - FCFF'!$O$25)/'DCF - FCFF'!$Q$25) | G59: =IF($A59-G$53<0.01,NA(),('DCF - FCFF'!$B$25*SUMPRODUCT(POWER(1+'DCF - FCFF'!$D$25,{1,2,3,4,5})/POWER(1+$A59,{1,2,3,4,5}))+'DCF - FCFF'!$B$25*POWER(1+'DCF - FCFF'!$D$25,5)*(1+G$53)/($A59-G$53)/POWER(1+$A59,5)-'DCF - FCFF'!$O$25)/'DCF - FCFF'!$Q$25) | H59: =IF($A59-H$53<0.01,NA(),('DCF - FCFF'!$B$25*SUMPRODUCT(POWER(1+'DCF - FCFF'!$D$25,{1,2,3,4,5})/POWER(1+$A59,{1,2,3,4,5}))+'DCF - FCFF'!$B$25*POWER(1+'DCF - FCFF'!$D$25,5)*(1+H$53)/($A59-H$53)/POWER(1+$A59,5)-'DCF - FCFF'!$O$25)/'DCF - FCFF'!$Q$25) | I59: =IF($A59-I$53<0.01,NA(),('DCF - FCFF'!$B$25*SUMPRODUCT(POWER(1+'DCF - FCFF'!$D$25,{1,2,3,4,5})/POWER(1+$A59,{1,2,3,4,5}))+'DCF - FCFF'!$B$25*POWER(1+'DCF - FCFF'!$D$25,5)*(1+I$53)/($A59-I$53)/POWER(1+$A59,5)-'DCF - FCFF'!$O$25)/'DCF - FCFF'!$Q$25) | J59: =IF($A59-J$53<0.01,NA(),('DCF - FCFF'!$B$25*SUMPRODUCT(POWER(1+'DCF - FCFF'!$D$25,{1,2,3,4,5})/POWER(1+$A59,{1,2,3,4,5}))+'DCF - FCFF'!$B$25*POWER(1+'DCF - FCFF'!$D$25,5)*(1+J$53)/($A59-J$53)/POWER(1+$A59,5)-'DCF - FCFF'!$O$25)/'DCF - FCFF'!$Q$25)
A60: ='DCF - FCFF'!$E$25+0.01 | B60: =IF($A60-B$53<0.01,NA(),('DCF - FCFF'!$B$25*SUMPRODUCT(POWER(1+'DCF - FCFF'!$D$25,{1,2,3,4,5})/POWER(1+$A60,{1,2,3,4,5}))+'DCF - FCFF'!$B$25*POWER(1+'DCF - FCFF'!$D$25,5)*(1+B$53)/($A60-B$53)/POWER(1+$A60,5)-'DCF - FCFF'!$O$25)/'DCF - FCFF'!$Q$25) | C60: =IF($A60-C$53<0.01,NA(),('DCF - FCFF'!$B$25*SUMPRODUCT(POWER(1+'DCF - FCFF'!$D$25,{1,2,3,4,5})/POWER(1+$A60,{1,2,3,4,5}))+'DCF - FCFF'!$B$25*POWER(1+'DCF - FCFF'!$D$25,5)*(1+C$53)/($A60-C$53)/POWER(1+$A60,5)-'DCF - FCFF'!$O$25)/'DCF - FCFF'!$Q$25) | D60: =IF($A60-D$53<0.01,NA(),('DCF - FCFF'!$B$25*SUMPRODUCT(POWER(1+'DCF - FCFF'!$D$25,{1,2,3,4,5})/POWER(1+$A60,{1,2,3,4,5}))+'DCF - FCFF'!$B$25*POWER(1+'DCF - FCFF'!$D$25,5)*(1+D$53)/($A60-D$53)/POWER(1+$A60,5)-'DCF - FCFF'!$O$25)/'DCF - FCFF'!$Q$25) | E60: =IF($A60-E$53<0.01,NA(),('DCF - FCFF'!$B$25*SUMPRODUCT(POWER(1+'DCF - FCFF'!$D$25,{1,2,3,4,5})/POWER(1+$A60,{1,2,3,4,5}))+'DCF - FCFF'!$B$25*POWER(1+'DCF - FCFF'!$D$25,5)*(1+E$53)/($A60-E$53)/POWER(1+$A60,5)-'DCF - FCFF'!$O$25)/'DCF - FCFF'!$Q$25) | F60: =IF($A60-F$53<0.01,NA(),('DCF - FCFF'!$B$25*SUMPRODUCT(POWER(1+'DCF - FCFF'!$D$25,{1,2,3,4,5})/POWER(1+$A60,{1,2,3,4,5}))+'DCF - FCFF'!$B$25*POWER(1+'DCF - FCFF'!$D$25,5)*(1+F$53)/($A60-F$53)/POWER(1+$A60,5)-'DCF - FCFF'!$O$25)/'DCF - FCFF'!$Q$25) | G60: =IF($A60-G$53<0.01,NA(),('DCF - FCFF'!$B$25*SUMPRODUCT(POWER(1+'DCF - FCFF'!$D$25,{1,2,3,4,5})/POWER(1+$A60,{1,2,3,4,5}))+'DCF - FCFF'!$B$25*POWER(1+'DCF - FCFF'!$D$25,5)*(1+G$53)/($A60-G$53)/POWER(1+$A60,5)-'DCF - FCFF'!$O$25)/'DCF - FCFF'!$Q$25) | H60: =IF($A60-H$53<0.01,NA(),('DCF - FCFF'!$B$25*SUMPRODUCT(POWER(1+'DCF - FCFF'!$D$25,{1,2,3,4,5})/POWER(1+$A60,{1,2,3,4,5}))+'DCF - FCFF'!$B$25*POWER(1+'DCF - FCFF'!$D$25,5)*(1+H$53)/($A60-H$53)/POWER(1+$A60,5)-'DCF - FCFF'!$O$25)/'DCF - FCFF'!$Q$25) | I60: =IF($A60-I$53<0.01,NA(),('DCF - FCFF'!$B$25*SUMPRODUCT(POWER(1+'DCF - FCFF'!$D$25,{1,2,3,4,5})/POWER(1+$A60,{1,2,3,4,5}))+'DCF - FCFF'!$B$25*POWER(1+'DCF - FCFF'!$D$25,5)*(1+I$53)/($A60-I$53)/POWER(1+$A60,5)-'DCF - FCFF'!$O$25)/'DCF - FCFF'!$Q$25) | J60: =IF($A60-J$53<0.01,NA(),('DCF - FCFF'!$B$25*SUMPRODUCT(POWER(1+'DCF - FCFF'!$D$25,{1,2,3,4,5})/POWER(1+$A60,{1,2,3,4,5}))+'DCF - FCFF'!$B$25*POWER(1+'DCF - FCFF'!$D$25,5)*(1+J$53)/($A60-J$53)/POWER(1+$A60,5)-'DCF - FCFF'!$O$25)/'DCF - FCFF'!$Q$25)
A61: ='DCF - FCFF'!$E$25+0.015 | B61: =IF($A61-B$53<0.01,NA(),('DCF - FCFF'!$B$25*SUMPRODUCT(POWER(1+'DCF - FCFF'!$D$25,{1,2,3,4,5})/POWER(1+$A61,{1,2,3,4,5}))+'DCF - FCFF'!$B$25*POWER(1+'DCF - FCFF'!$D$25,5)*(1+B$53)/($A61-B$53)/POWER(1+$A61,5)-'DCF - FCFF'!$O$25)/'DCF - FCFF'!$Q$25) | C61: =IF($A61-C$53<0.01,NA(),('DCF - FCFF'!$B$25*SUMPRODUCT(POWER(1+'DCF - FCFF'!$D$25,{1,2,3,4,5})/POWER(1+$A61,{1,2,3,4,5}))+'DCF - FCFF'!$B$25*POWER(1+'DCF - FCFF'!$D$25,5)*(1+C$53)/($A61-C$53)/POWER(1+$A61,5)-'DCF - FCFF'!$O$25)/'DCF - FCFF'!$Q$25) | D61: =IF($A61-D$53<0.01,NA(),('DCF - FCFF'!$B$25*SUMPRODUCT(POWER(1+'DCF - FCFF'!$D$25,{1,2,3,4,5})/POWER(1+$A61,{1,2,3,4,5}))+'DCF - FCFF'!$B$25*POWER(1+'DCF - FCFF'!$D$25,5)*(1+D$53)/($A61-D$53)/POWER(1+$A61,5)-'DCF - FCFF'!$O$25)/'DCF - FCFF'!$Q$25) | E61: =IF($A61-E$53<0.01,NA(),('DCF - FCFF'!$B$25*SUMPRODUCT(POWER(1+'DCF - FCFF'!$D$25,{1,2,3,4,5})/POWER(1+$A61,{1,2,3,4,5}))+'DCF - FCFF'!$B$25*POWER(1+'DCF - FCFF'!$D$25,5)*(1+E$53)/($A61-E$53)/POWER(1+$A61,5)-'DCF - FCFF'!$O$25)/'DCF - FCFF'!$Q$25) | F61: =IF($A61-F$53<0.01,NA(),('DCF - FCFF'!$B$25*SUMPRODUCT(POWER(1+'DCF - FCFF'!$D$25,{1,2,3,4,5})/POWER(1+$A61,{1,2,3,4,5}))+'DCF - FCFF'!$B$25*POWER(1+'DCF - FCFF'!$D$25,5)*(1+F$53)/($A61-F$53)/POWER(1+$A61,5)-'DCF - FCFF'!$O$25)/'DCF - FCFF'!$Q$25) | G61: =IF($A61-G$53<0.01,NA(),('DCF - FCFF'!$B$25*SUMPRODUCT(POWER(1+'DCF - FCFF'!$D$25,{1,2,3,4,5})/POWER(1+$A61,{1,2,3,4,5}))+'DCF - FCFF'!$B$25*POWER(1+'DCF - FCFF'!$D$25,5)*(1+G$53)/($A61-G$53)/POWER(1+$A61,5)-'DCF - FCFF'!$O$25)/'DCF - FCFF'!$Q$25) | H61: =IF($A61-H$53<0.01,NA(),('DCF - FCFF'!$B$25*SUMPRODUCT(POWER(1+'DCF - FCFF'!$D$25,{1,2,3,4,5})/POWER(1+$A61,{1,2,3,4,5}))+'DCF - FCFF'!$B$25*POWER(1+'DCF - FCFF'!$D$25,5)*(1+H$53)/($A61-H$53)/POWER(1+$A61,5)-'DCF - FCFF'!$O$25)/'DCF - FCFF'!$Q$25) | I61: =IF($A61-I$53<0.01,NA(),('DCF - FCFF'!$B$25*SUMPRODUCT(POWER(1+'DCF - FCFF'!$D$25,{1,2,3,4,5})/POWER(1+$A61,{1,2,3,4,5}))+'DCF - FCFF'!$B$25*POWER(1+'DCF - FCFF'!$D$25,5)*(1+I$53)/($A61-I$53)/POWER(1+$A61,5)-'DCF - FCFF'!$O$25)/'DCF - FCFF'!$Q$25) | J61: =IF($A61-J$53<0.01,NA(),('DCF - FCFF'!$B$25*SUMPRODUCT(POWER(1+'DCF - FCFF'!$D$25,{1,2,3,4,5})/POWER(1+$A61,{1,2,3,4,5}))+'DCF - FCFF'!$B$25*POWER(1+'DCF - FCFF'!$D$25,5)*(1+J$53)/($A61-J$53)/POWER(1+$A61,5)-'DCF - FCFF'!$O$25)/'DCF - FCFF'!$Q$25)
A62: ='DCF - FCFF'!$E$25+0.02 | B62: =IF($A62-B$53<0.01,NA(),('DCF - FCFF'!$B$25*SUMPRODUCT(POWER(1+'DCF - FCFF'!$D$25,{1,2,3,4,5})/POWER(1+$A62,{1,2,3,4,5}))+'DCF - FCFF'!$B$25*POWER(1+'DCF - FCFF'!$D$25,5)*(1+B$53)/($A62-B$53)/POWER(1+$A62,5)-'DCF - FCFF'!$O$25)/'DCF - FCFF'!$Q$25) | C62: =IF($A62-C$53<0.01,NA(),('DCF - FCFF'!$B$25*SUMPRODUCT(POWER(1+'DCF - FCFF'!$D$25,{1,2,3,4,5})/POWER(1+$A62,{1,2,3,4,5}))+'DCF - FCFF'!$B$25*POWER(1+'DCF - FCFF'!$D$25,5)*(1+C$53)/($A62-C$53)/POWER(1+$A62,5)-'DCF - FCFF'!$O$25)/'DCF - FCFF'!$Q$25) | D62: =IF($A62-D$53<0.01,NA(),('DCF - FCFF'!$B$25*SUMPRODUCT(POWER(1+'DCF - FCFF'!$D$25,{1,2,3,4,5})/POWER(1+$A62,{1,2,3,4,5}))+'DCF - FCFF'!$B$25*POWER(1+'DCF - FCFF'!$D$25,5)*(1+D$53)/($A62-D$53)/POWER(1+$A62,5)-'DCF - FCFF'!$O$25)/'DCF - FCFF'!$Q$25) | E62: =IF($A62-E$53<0.01,NA(),('DCF - FCFF'!$B$25*SUMPRODUCT(POWER(1+'DCF - FCFF'!$D$25,{1,2,3,4,5})/POWER(1+$A62,{1,2,3,4,5}))+'DCF - FCFF'!$B$25*POWER(1+'DCF - FCFF'!$D$25,5)*(1+E$53)/($A62-E$53)/POWER(1+$A62,5)-'DCF - FCFF'!$O$25)/'DCF - FCFF'!$Q$25) | F62: =IF($A62-F$53<0.01,NA(),('DCF - FCFF'!$B$25*SUMPRODUCT(POWER(1+'DCF - FCFF'!$D$25,{1,2,3,4,5})/POWER(1+$A62,{1,2,3,4,5}))+'DCF - FCFF'!$B$25*POWER(1+'DCF - FCFF'!$D$25,5)*(1+F$53)/($A62-F$53)/POWER(1+$A62,5)-'DCF - FCFF'!$O$25)/'DCF - FCFF'!$Q$25) | G62: =IF($A62-G$53<0.01,NA(),('DCF - FCFF'!$B$25*SUMPRODUCT(POWER(1+'DCF - FCFF'!$D$25,{1,2,3,4,5})/POWER(1+$A62,{1,2,3,4,5}))+'DCF - FCFF'!$B$25*POWER(1+'DCF - FCFF'!$D$25,5)*(1+G$53)/($A62-G$53)/POWER(1+$A62,5)-'DCF - FCFF'!$O$25)/'DCF - FCFF'!$Q$25) | H62: =IF($A62-H$53<0.01,NA(),('DCF - FCFF'!$B$25*SUMPRODUCT(POWER(1+'DCF - FCFF'!$D$25,{1,2,3,4,5})/POWER(1+$A62,{1,2,3,4,5}))+'DCF - FCFF'!$B$25*POWER(1+'DCF - FCFF'!$D$25,5)*(1+H$53)/($A62-H$53)/POWER(1+$A62,5)-'DCF - FCFF'!$O$25)/'DCF - FCFF'!$Q$25) | I62: =IF($A62-I$53<0.01,NA(),('DCF - FCFF'!$B$25*SUMPRODUCT(POWER(1+'DCF - FCFF'!$D$25,{1,2,3,4,5})/POWER(1+$A62,{1,2,3,4,5}))+'DCF - FCFF'!$B$25*POWER(1+'DCF - FCFF'!$D$25,5)*(1+I$53)/($A62-I$53)/POWER(1+$A62,5)-'DCF - FCFF'!$O$25)/'DCF - FCFF'!$Q$25) | J62: =IF($A62-J$53<0.01,NA(),('DCF - FCFF'!$B$25*SUMPRODUCT(POWER(1+'DCF - FCFF'!$D$25,{1,2,3,4,5})/POWER(1+$A62,{1,2,3,4,5}))+'DCF - FCFF'!$B$25*POWER(1+'DCF - FCFF'!$D$25,5)*(1+J$53)/($A62-J$53)/POWER(1+$A62,5)-'DCF - FCFF'!$O$25)/'DCF - FCFF'!$Q$25)
A64: Nestle | B64: ='Market Data'!$C$7 | C64: ← market price · rows: WACC · cols: terminal g
B65: 0.01 | C65: 0.015 | D65: 0.02 | E65: 0.025 | F65: 0.03 | G65: 0.035 | H65: 0.04 | I65: 0.045 | J65: 0.05
A66: ='DCF - FCFF'!$E$26-0.02 | B66: =IF($A66-B$65<0.01,NA(),('DCF - FCFF'!$B$26*SUMPRODUCT(POWER(1+'DCF - FCFF'!$D$26,{1,2,3,4,5})/POWER(1+$A66,{1,2,3,4,5}))+'DCF - FCFF'!$B$26*POWER(1+'DCF - FCFF'!$D$26,5)*(1+B$65)/($A66-B$65)/POWER(1+$A66,5)-'DCF - FCFF'!$O$26)/'DCF - FCFF'!$Q$26) | C66: =IF($A66-C$65<0.01,NA(),('DCF - FCFF'!$B$26*SUMPRODUCT(POWER(1+'DCF - FCFF'!$D$26,{1,2,3,4,5})/POWER(1+$A66,{1,2,3,4,5}))+'DCF - FCFF'!$B$26*POWER(1+'DCF - FCFF'!$D$26,5)*(1+C$65)/($A66-C$65)/POWER(1+$A66,5)-'DCF - FCFF'!$O$26)/'DCF - FCFF'!$Q$26) | D66: =IF($A66-D$65<0.01,NA(),('DCF - FCFF'!$B$26*SUMPRODUCT(POWER(1+'DCF - FCFF'!$D$26,{1,2,3,4,5})/POWER(1+$A66,{1,2,3,4,5}))+'DCF - FCFF'!$B$26*POWER(1+'DCF - FCFF'!$D$26,5)*(1+D$65)/($A66-D$65)/POWER(1+$A66,5)-'DCF - FCFF'!$O$26)/'DCF - FCFF'!$Q$26) | E66: =IF($A66-E$65<0.01,NA(),('DCF - FCFF'!$B$26*SUMPRODUCT(POWER(1+'DCF - FCFF'!$D$26,{1,2,3,4,5})/POWER(1+$A66,{1,2,3,4,5}))+'DCF - FCFF'!$B$26*POWER(1+'DCF - FCFF'!$D$26,5)*(1+E$65)/($A66-E$65)/POWER(1+$A66,5)-'DCF - FCFF'!$O$26)/'DCF - FCFF'!$Q$26) | F66: =IF($A66-F$65<0.01,NA(),('DCF - FCFF'!$B$26*SUMPRODUCT(POWER(1+'DCF - FCFF'!$D$26,{1,2,3,4,5})/POWER(1+$A66,{1,2,3,4,5}))+'DCF - FCFF'!$B$26*POWER(1+'DCF - FCFF'!$D$26,5)*(1+F$65)/($A66-F$65)/POWER(1+$A66,5)-'DCF - FCFF'!$O$26)/'DCF - FCFF'!$Q$26) | G66: =IF($A66-G$65<0.01,NA(),('DCF - FCFF'!$B$26*SUMPRODUCT(POWER(1+'DCF - FCFF'!$D$26,{1,2,3,4,5})/POWER(1+$A66,{1,2,3,4,5}))+'DCF - FCFF'!$B$26*POWER(1+'DCF - FCFF'!$D$26,5)*(1+G$65)/($A66-G$65)/POWER(1+$A66,5)-'DCF - FCFF'!$O$26)/'DCF - FCFF'!$Q$26) | H66: =IF($A66-H$65<0.01,NA(),('DCF - FCFF'!$B$26*SUMPRODUCT(POWER(1+'DCF - FCFF'!$D$26,{1,2,3,4,5})/POWER(1+$A66,{1,2,3,4,5}))+'DCF - FCFF'!$B$26*POWER(1+'DCF - FCFF'!$D$26,5)*(1+H$65)/($A66-H$65)/POWER(1+$A66,5)-'DCF - FCFF'!$O$26)/'DCF - FCFF'!$Q$26) | I66: =IF($A66-I$65<0.01,NA(),('DCF - FCFF'!$B$26*SUMPRODUCT(POWER(1+'DCF - FCFF'!$D$26,{1,2,3,4,5})/POWER(1+$A66,{1,2,3,4,5}))+'DCF - FCFF'!$B$26*POWER(1+'DCF - FCFF'!$D$26,5)*(1+I$65)/($A66-I$65)/POWER(1+$A66,5)-'DCF - FCFF'!$O$26)/'DCF - FCFF'!$Q$26) | J66: =IF($A66-J$65<0.01,NA(),('DCF - FCFF'!$B$26*SUMPRODUCT(POWER(1+'DCF - FCFF'!$D$26,{1,2,3,4,5})/POWER(1+$A66,{1,2,3,4,5}))+'DCF - FCFF'!$B$26*POWER(1+'DCF - FCFF'!$D$26,5)*(1+J$65)/($A66-J$65)/POWER(1+$A66,5)-'DCF - FCFF'!$O$26)/'DCF - FCFF'!$Q$26)
A67: ='DCF - FCFF'!$E$26-0.015 | B67: =IF($A67-B$65<0.01,NA(),('DCF - FCFF'!$B$26*SUMPRODUCT(POWER(1+'DCF - FCFF'!$D$26,{1,2,3,4,5})/POWER(1+$A67,{1,2,3,4,5}))+'DCF - FCFF'!$B$26*POWER(1+'DCF - FCFF'!$D$26,5)*(1+B$65)/($A67-B$65)/POWER(1+$A67,5)-'DCF - FCFF'!$O$26)/'DCF - FCFF'!$Q$26) | C67: =IF($A67-C$65<0.01,NA(),('DCF - FCFF'!$B$26*SUMPRODUCT(POWER(1+'DCF - FCFF'!$D$26,{1,2,3,4,5})/POWER(1+$A67,{1,2,3,4,5}))+'DCF - FCFF'!$B$26*POWER(1+'DCF - FCFF'!$D$26,5)*(1+C$65)/($A67-C$65)/POWER(1+$A67,5)-'DCF - FCFF'!$O$26)/'DCF - FCFF'!$Q$26) | D67: =IF($A67-D$65<0.01,NA(),('DCF - FCFF'!$B$26*SUMPRODUCT(POWER(1+'DCF - FCFF'!$D$26,{1,2,3,4,5})/POWER(1+$A67,{1,2,3,4,5}))+'DCF - FCFF'!$B$26*POWER(1+'DCF - FCFF'!$D$26,5)*(1+D$65)/($A67-D$65)/POWER(1+$A67,5)-'DCF - FCFF'!$O$26)/'DCF - FCFF'!$Q$26) | E67: =IF($A67-E$65<0.01,NA(),('DCF - FCFF'!$B$26*SUMPRODUCT(POWER(1+'DCF - FCFF'!$D$26,{1,2,3,4,5})/POWER(1+$A67,{1,2,3,4,5}))+'DCF - FCFF'!$B$26*POWER(1+'DCF - FCFF'!$D$26,5)*(1+E$65)/($A67-E$65)/POWER(1+$A67,5)-'DCF - FCFF'!$O$26)/'DCF - FCFF'!$Q$26) | F67: =IF($A67-F$65<0.01,NA(),('DCF - FCFF'!$B$26*SUMPRODUCT(POWER(1+'DCF - FCFF'!$D$26,{1,2,3,4,5})/POWER(1+$A67,{1,2,3,4,5}))+'DCF - FCFF'!$B$26*POWER(1+'DCF - FCFF'!$D$26,5)*(1+F$65)/($A67-F$65)/POWER(1+$A67,5)-'DCF - FCFF'!$O$26)/'DCF - FCFF'!$Q$26) | G67: =IF($A67-G$65<0.01,NA(),('DCF - FCFF'!$B$26*SUMPRODUCT(POWER(1+'DCF - FCFF'!$D$26,{1,2,3,4,5})/POWER(1+$A67,{1,2,3,4,5}))+'DCF - FCFF'!$B$26*POWER(1+'DCF - FCFF'!$D$26,5)*(1+G$65)/($A67-G$65)/POWER(1+$A67,5)-'DCF - FCFF'!$O$26)/'DCF - FCFF'!$Q$26) | H67: =IF($A67-H$65<0.01,NA(),('DCF - FCFF'!$B$26*SUMPRODUCT(POWER(1+'DCF - FCFF'!$D$26,{1,2,3,4,5})/POWER(1+$A67,{1,2,3,4,5}))+'DCF - FCFF'!$B$26*POWER(1+'DCF - FCFF'!$D$26,5)*(1+H$65)/($A67-H$65)/POWER(1+$A67,5)-'DCF - FCFF'!$O$26)/'DCF - FCFF'!$Q$26) | I67: =IF($A67-I$65<0.01,NA(),('DCF - FCFF'!$B$26*SUMPRODUCT(POWER(1+'DCF - FCFF'!$D$26,{1,2,3,4,5})/POWER(1+$A67,{1,2,3,4,5}))+'DCF - FCFF'!$B$26*POWER(1+'DCF - FCFF'!$D$26,5)*(1+I$65)/($A67-I$65)/POWER(1+$A67,5)-'DCF - FCFF'!$O$26)/'DCF - FCFF'!$Q$26) | J67: =IF($A67-J$65<0.01,NA(),('DCF - FCFF'!$B$26*SUMPRODUCT(POWER(1+'DCF - FCFF'!$D$26,{1,2,3,4,5})/POWER(1+$A67,{1,2,3,4,5}))+'DCF - FCFF'!$B$26*POWER(1+'DCF - FCFF'!$D$26,5)*(1+J$65)/($A67-J$65)/POWER(1+$A67,5)-'DCF - FCFF'!$O$26)/'DCF - FCFF'!$Q$26)
A68: ='DCF - FCFF'!$E$26-0.01 | B68: =IF($A68-B$65<0.01,NA(),('DCF - FCFF'!$B$26*SUMPRODUCT(POWER(1+'DCF - FCFF'!$D$26,{1,2,3,4,5})/POWER(1+$A68,{1,2,3,4,5}))+'DCF - FCFF'!$B$26*POWER(1+'DCF - FCFF'!$D$26,5)*(1+B$65)/($A68-B$65)/POWER(1+$A68,5)-'DCF - FCFF'!$O$26)/'DCF - FCFF'!$Q$26) | C68: =IF($A68-C$65<0.01,NA(),('DCF - FCFF'!$B$26*SUMPRODUCT(POWER(1+'DCF - FCFF'!$D$26,{1,2,3,4,5})/POWER(1+$A68,{1,2,3,4,5}))+'DCF - FCFF'!$B$26*POWER(1+'DCF - FCFF'!$D$26,5)*(1+C$65)/($A68-C$65)/POWER(1+$A68,5)-'DCF - FCFF'!$O$26)/'DCF - FCFF'!$Q$26) | D68: =IF($A68-D$65<0.01,NA(),('DCF - FCFF'!$B$26*SUMPRODUCT(POWER(1+'DCF - FCFF'!$D$26,{1,2,3,4,5})/POWER(1+$A68,{1,2,3,4,5}))+'DCF - FCFF'!$B$26*POWER(1+'DCF - FCFF'!$D$26,5)*(1+D$65)/($A68-D$65)/POWER(1+$A68,5)-'DCF - FCFF'!$O$26)/'DCF - FCFF'!$Q$26) | E68: =IF($A68-E$65<0.01,NA(),('DCF - FCFF'!$B$26*SUMPRODUCT(POWER(1+'DCF - FCFF'!$D$26,{1,2,3,4,5})/POWER(1+$A68,{1,2,3,4,5}))+'DCF - FCFF'!$B$26*POWER(1+'DCF - FCFF'!$D$26,5)*(1+E$65)/($A68-E$65)/POWER(1+$A68,5)-'DCF - FCFF'!$O$26)/'DCF - FCFF'!$Q$26) | F68: =IF($A68-F$65<0.01,NA(),('DCF - FCFF'!$B$26*SUMPRODUCT(POWER(1+'DCF - FCFF'!$D$26,{1,2,3,4,5})/POWER(1+$A68,{1,2,3,4,5}))+'DCF - FCFF'!$B$26*POWER(1+'DCF - FCFF'!$D$26,5)*(1+F$65)/($A68-F$65)/POWER(1+$A68,5)-'DCF - FCFF'!$O$26)/'DCF - FCFF'!$Q$26) | G68: =IF($A68-G$65<0.01,NA(),('DCF - FCFF'!$B$26*SUMPRODUCT(POWER(1+'DCF - FCFF'!$D$26,{1,2,3,4,5})/POWER(1+$A68,{1,2,3,4,5}))+'DCF - FCFF'!$B$26*POWER(1+'DCF - FCFF'!$D$26,5)*(1+G$65)/($A68-G$65)/POWER(1+$A68,5)-'DCF - FCFF'!$O$26)/'DCF - FCFF'!$Q$26) | H68: =IF($A68-H$65<0.01,NA(),('DCF - FCFF'!$B$26*SUMPRODUCT(POWER(1+'DCF - FCFF'!$D$26,{1,2,3,4,5})/POWER(1+$A68,{1,2,3,4,5}))+'DCF - FCFF'!$B$26*POWER(1+'DCF - FCFF'!$D$26,5)*(1+H$65)/($A68-H$65)/POWER(1+$A68,5)-'DCF - FCFF'!$O$26)/'DCF - FCFF'!$Q$26) | I68: =IF($A68-I$65<0.01,NA(),('DCF - FCFF'!$B$26*SUMPRODUCT(POWER(1+'DCF - FCFF'!$D$26,{1,2,3,4,5})/POWER(1+$A68,{1,2,3,4,5}))+'DCF - FCFF'!$B$26*POWER(1+'DCF - FCFF'!$D$26,5)*(1+I$65)/($A68-I$65)/POWER(1+$A68,5)-'DCF - FCFF'!$O$26)/'DCF - FCFF'!$Q$26) | J68: =IF($A68-J$65<0.01,NA(),('DCF - FCFF'!$B$26*SUMPRODUCT(POWER(1+'DCF - FCFF'!$D$26,{1,2,3,4,5})/POWER(1+$A68,{1,2,3,4,5}))+'DCF - FCFF'!$B$26*POWER(1+'DCF - FCFF'!$D$26,5)*(1+J$65)/($A68-J$65)/POWER(1+$A68,5)-'DCF - FCFF'!$O$26)/'DCF - FCFF'!$Q$26)
A69: ='DCF - FCFF'!$E$26-0.005 | B69: =IF($A69-B$65<0.01,NA(),('DCF - FCFF'!$B$26*SUMPRODUCT(POWER(1+'DCF - FCFF'!$D$26,{1,2,3,4,5})/POWER(1+$A69,{1,2,3,4,5}))+'DCF - FCFF'!$B$26*POWER(1+'DCF - FCFF'!$D$26,5)*(1+B$65)/($A69-B$65)/POWER(1+$A69,5)-'DCF - FCFF'!$O$26)/'DCF - FCFF'!$Q$26) | C69: =IF($A69-C$65<0.01,NA(),('DCF - FCFF'!$B$26*SUMPRODUCT(POWER(1+'DCF - FCFF'!$D$26,{1,2,3,4,5})/POWER(1+$A69,{1,2,3,4,5}))+'DCF - FCFF'!$B$26*POWER(1+'DCF - FCFF'!$D$26,5)*(1+C$65)/($A69-C$65)/POWER(1+$A69,5)-'DCF - FCFF'!$O$26)/'DCF - FCFF'!$Q$26) | D69: =IF($A69-D$65<0.01,NA(),('DCF - FCFF'!$B$26*SUMPRODUCT(POWER(1+'DCF - FCFF'!$D$26,{1,2,3,4,5})/POWER(1+$A69,{1,2,3,4,5}))+'DCF - FCFF'!$B$26*POWER(1+'DCF - FCFF'!$D$26,5)*(1+D$65)/($A69-D$65)/POWER(1+$A69,5)-'DCF - FCFF'!$O$26)/'DCF - FCFF'!$Q$26) | E69: =IF($A69-E$65<0.01,NA(),('DCF - FCFF'!$B$26*SUMPRODUCT(POWER(1+'DCF - FCFF'!$D$26,{1,2,3,4,5})/POWER(1+$A69,{1,2,3,4,5}))+'DCF - FCFF'!$B$26*POWER(1+'DCF - FCFF'!$D$26,5)*(1+E$65)/($A69-E$65)/POWER(1+$A69,5)-'DCF - FCFF'!$O$26)/'DCF - FCFF'!$Q$26) | F69: =IF($A69-F$65<0.01,NA(),('DCF - FCFF'!$B$26*SUMPRODUCT(POWER(1+'DCF - FCFF'!$D$26,{1,2,3,4,5})/POWER(1+$A69,{1,2,3,4,5}))+'DCF - FCFF'!$B$26*POWER(1+'DCF - FCFF'!$D$26,5)*(1+F$65)/($A69-F$65)/POWER(1+$A69,5)-'DCF - FCFF'!$O$26)/'DCF - FCFF'!$Q$26) | G69: =IF($A69-G$65<0.01,NA(),('DCF - FCFF'!$B$26*SUMPRODUCT(POWER(1+'DCF - FCFF'!$D$26,{1,2,3,4,5})/POWER(1+$A69,{1,2,3,4,5}))+'DCF - FCFF'!$B$26*POWER(1+'DCF - FCFF'!$D$26,5)*(1+G$65)/($A69-G$65)/POWER(1+$A69,5)-'DCF - FCFF'!$O$26)/'DCF - FCFF'!$Q$26) | H69: =IF($A69-H$65<0.01,NA(),('DCF - FCFF'!$B$26*SUMPRODUCT(POWER(1+'DCF - FCFF'!$D$26,{1,2,3,4,5})/POWER(1+$A69,{1,2,3,4,5}))+'DCF - FCFF'!$B$26*POWER(1+'DCF - FCFF'!$D$26,5)*(1+H$65)/($A69-H$65)/POWER(1+$A69,5)-'DCF - FCFF'!$O$26)/'DCF - FCFF'!$Q$26) | I69: =IF($A69-I$65<0.01,NA(),('DCF - FCFF'!$B$26*SUMPRODUCT(POWER(1+'DCF - FCFF'!$D$26,{1,2,3,4,5})/POWER(1+$A69,{1,2,3,4,5}))+'DCF - FCFF'!$B$26*POWER(1+'DCF - FCFF'!$D$26,5)*(1+I$65)/($A69-I$65)/POWER(1+$A69,5)-'DCF - FCFF'!$O$26)/'DCF - FCFF'!$Q$26) | J69: =IF($A69-J$65<0.01,NA(),('DCF - FCFF'!$B$26*SUMPRODUCT(POWER(1+'DCF - FCFF'!$D$26,{1,2,3,4,5})/POWER(1+$A69,{1,2,3,4,5}))+'DCF - FCFF'!$B$26*POWER(1+'DCF - FCFF'!$D$26,5)*(1+J$65)/($A69-J$65)/POWER(1+$A69,5)-'DCF - FCFF'!$O$26)/'DCF - FCFF'!$Q$26)
A70: ='DCF - FCFF'!$E$26+0.0 | B70: =IF($A70-B$65<0.01,NA(),('DCF - FCFF'!$B$26*SUMPRODUCT(POWER(1+'DCF - FCFF'!$D$26,{1,2,3,4,5})/POWER(1+$A70,{1,2,3,4,5}))+'DCF - FCFF'!$B$26*POWER(1+'DCF - FCFF'!$D$26,5)*(1+B$65)/($A70-B$65)/POWER(1+$A70,5)-'DCF - FCFF'!$O$26)/'DCF - FCFF'!$Q$26) | C70: =IF($A70-C$65<0.01,NA(),('DCF - FCFF'!$B$26*SUMPRODUCT(POWER(1+'DCF - FCFF'!$D$26,{1,2,3,4,5})/POWER(1+$A70,{1,2,3,4,5}))+'DCF - FCFF'!$B$26*POWER(1+'DCF - FCFF'!$D$26,5)*(1+C$65)/($A70-C$65)/POWER(1+$A70,5)-'DCF - FCFF'!$O$26)/'DCF - FCFF'!$Q$26) | D70: =IF($A70-D$65<0.01,NA(),('DCF - FCFF'!$B$26*SUMPRODUCT(POWER(1+'DCF - FCFF'!$D$26,{1,2,3,4,5})/POWER(1+$A70,{1,2,3,4,5}))+'DCF - FCFF'!$B$26*POWER(1+'DCF - FCFF'!$D$26,5)*(1+D$65)/($A70-D$65)/POWER(1+$A70,5)-'DCF - FCFF'!$O$26)/'DCF - FCFF'!$Q$26) | E70: =IF($A70-E$65<0.01,NA(),('DCF - FCFF'!$B$26*SUMPRODUCT(POWER(1+'DCF - FCFF'!$D$26,{1,2,3,4,5})/POWER(1+$A70,{1,2,3,4,5}))+'DCF - FCFF'!$B$26*POWER(1+'DCF - FCFF'!$D$26,5)*(1+E$65)/($A70-E$65)/POWER(1+$A70,5)-'DCF - FCFF'!$O$26)/'DCF - FCFF'!$Q$26) | F70: =IF($A70-F$65<0.01,NA(),('DCF - FCFF'!$B$26*SUMPRODUCT(POWER(1+'DCF - FCFF'!$D$26,{1,2,3,4,5})/POWER(1+$A70,{1,2,3,4,5}))+'DCF - FCFF'!$B$26*POWER(1+'DCF - FCFF'!$D$26,5)*(1+F$65)/($A70-F$65)/POWER(1+$A70,5)-'DCF - FCFF'!$O$26)/'DCF - FCFF'!$Q$26) | G70: =IF($A70-G$65<0.01,NA(),('DCF - FCFF'!$B$26*SUMPRODUCT(POWER(1+'DCF - FCFF'!$D$26,{1,2,3,4,5})/POWER(1+$A70,{1,2,3,4,5}))+'DCF - FCFF'!$B$26*POWER(1+'DCF - FCFF'!$D$26,5)*(1+G$65)/($A70-G$65)/POWER(1+$A70,5)-'DCF - FCFF'!$O$26)/'DCF - FCFF'!$Q$26) | H70: =IF($A70-H$65<0.01,NA(),('DCF - FCFF'!$B$26*SUMPRODUCT(POWER(1+'DCF - FCFF'!$D$26,{1,2,3,4,5})/POWER(1+$A70,{1,2,3,4,5}))+'DCF - FCFF'!$B$26*POWER(1+'DCF - FCFF'!$D$26,5)*(1+H$65)/($A70-H$65)/POWER(1+$A70,5)-'DCF - FCFF'!$O$26)/'DCF - FCFF'!$Q$26) | I70: =IF($A70-I$65<0.01,NA(),('DCF - FCFF'!$B$26*SUMPRODUCT(POWER(1+'DCF - FCFF'!$D$26,{1,2,3,4,5})/POWER(1+$A70,{1,2,3,4,5}))+'DCF - FCFF'!$B$26*POWER(1+'DCF - FCFF'!$D$26,5)*(1+I$65)/($A70-I$65)/POWER(1+$A70,5)-'DCF - FCFF'!$O$26)/'DCF - FCFF'!$Q$26) | J70: =IF($A70-J$65<0.01,NA(),('DCF - FCFF'!$B$26*SUMPRODUCT(POWER(1+'DCF - FCFF'!$D$26,{1,2,3,4,5})/POWER(1+$A70,{1,2,3,4,5}))+'DCF - FCFF'!$B$26*POWER(1+'DCF - FCFF'!$D$26,5)*(1+J$65)/($A70-J$65)/POWER(1+$A70,5)-'DCF - FCFF'!$O$26)/'DCF - FCFF'!$Q$26)
A71: ='DCF - FCFF'!$E$26+0.005 | B71: =IF($A71-B$65<0.01,NA(),('DCF - FCFF'!$B$26*SUMPRODUCT(POWER(1+'DCF - FCFF'!$D$26,{1,2,3,4,5})/POWER(1+$A71,{1,2,3,4,5}))+'DCF - FCFF'!$B$26*POWER(1+'DCF - FCFF'!$D$26,5)*(1+B$65)/($A71-B$65)/POWER(1+$A71,5)-'DCF - FCFF'!$O$26)/'DCF - FCFF'!$Q$26) | C71: =IF($A71-C$65<0.01,NA(),('DCF - FCFF'!$B$26*SUMPRODUCT(POWER(1+'DCF - FCFF'!$D$26,{1,2,3,4,5})/POWER(1+$A71,{1,2,3,4,5}))+'DCF - FCFF'!$B$26*POWER(1+'DCF - FCFF'!$D$26,5)*(1+C$65)/($A71-C$65)/POWER(1+$A71,5)-'DCF - FCFF'!$O$26)/'DCF - FCFF'!$Q$26) | D71: =IF($A71-D$65<0.01,NA(),('DCF - FCFF'!$B$26*SUMPRODUCT(POWER(1+'DCF - FCFF'!$D$26,{1,2,3,4,5})/POWER(1+$A71,{1,2,3,4,5}))+'DCF - FCFF'!$B$26*POWER(1+'DCF - FCFF'!$D$26,5)*(1+D$65)/($A71-D$65)/POWER(1+$A71,5)-'DCF - FCFF'!$O$26)/'DCF - FCFF'!$Q$26) | E71: =IF($A71-E$65<0.01,NA(),('DCF - FCFF'!$B$26*SUMPRODUCT(POWER(1+'DCF - FCFF'!$D$26,{1,2,3,4,5})/POWER(1+$A71,{1,2,3,4,5}))+'DCF - FCFF'!$B$26*POWER(1+'DCF - FCFF'!$D$26,5)*(1+E$65)/($A71-E$65)/POWER(1+$A71,5)-'DCF - FCFF'!$O$26)/'DCF - FCFF'!$Q$26) | F71: =IF($A71-F$65<0.01,NA(),('DCF - FCFF'!$B$26*SUMPRODUCT(POWER(1+'DCF - FCFF'!$D$26,{1,2,3,4,5})/POWER(1+$A71,{1,2,3,4,5}))+'DCF - FCFF'!$B$26*POWER(1+'DCF - FCFF'!$D$26,5)*(1+F$65)/($A71-F$65)/POWER(1+$A71,5)-'DCF - FCFF'!$O$26)/'DCF - FCFF'!$Q$26) | G71: =IF($A71-G$65<0.01,NA(),('DCF - FCFF'!$B$26*SUMPRODUCT(POWER(1+'DCF - FCFF'!$D$26,{1,2,3,4,5})/POWER(1+$A71,{1,2,3,4,5}))+'DCF - FCFF'!$B$26*POWER(1+'DCF - FCFF'!$D$26,5)*(1+G$65)/($A71-G$65)/POWER(1+$A71,5)-'DCF - FCFF'!$O$26)/'DCF - FCFF'!$Q$26) | H71: =IF($A71-H$65<0.01,NA(),('DCF - FCFF'!$B$26*SUMPRODUCT(POWER(1+'DCF - FCFF'!$D$26,{1,2,3,4,5})/POWER(1+$A71,{1,2,3,4,5}))+'DCF - FCFF'!$B$26*POWER(1+'DCF - FCFF'!$D$26,5)*(1+H$65)/($A71-H$65)/POWER(1+$A71,5)-'DCF - FCFF'!$O$26)/'DCF - FCFF'!$Q$26) | I71: =IF($A71-I$65<0.01,NA(),('DCF - FCFF'!$B$26*SUMPRODUCT(POWER(1+'DCF - FCFF'!$D$26,{1,2,3,4,5})/POWER(1+$A71,{1,2,3,4,5}))+'DCF - FCFF'!$B$26*POWER(1+'DCF - FCFF'!$D$26,5)*(1+I$65)/($A71-I$65)/POWER(1+$A71,5)-'DCF - FCFF'!$O$26)/'DCF - FCFF'!$Q$26) | J71: =IF($A71-J$65<0.01,NA(),('DCF - FCFF'!$B$26*SUMPRODUCT(POWER(1+'DCF - FCFF'!$D$26,{1,2,3,4,5})/POWER(1+$A71,{1,2,3,4,5}))+'DCF - FCFF'!$B$26*POWER(1+'DCF - FCFF'!$D$26,5)*(1+J$65)/($A71-J$65)/POWER(1+$A71,5)-'DCF - FCFF'!$O$26)/'DCF - FCFF'!$Q$26)
A72: ='DCF - FCFF'!$E$26+0.01 | B72: =IF($A72-B$65<0.01,NA(),('DCF - FCFF'!$B$26*SUMPRODUCT(POWER(1+'DCF - FCFF'!$D$26,{1,2,3,4,5})/POWER(1+$A72,{1,2,3,4,5}))+'DCF - FCFF'!$B$26*POWER(1+'DCF - FCFF'!$D$26,5)*(1+B$65)/($A72-B$65)/POWER(1+$A72,5)-'DCF - FCFF'!$O$26)/'DCF - FCFF'!$Q$26) | C72: =IF($A72-C$65<0.01,NA(),('DCF - FCFF'!$B$26*SUMPRODUCT(POWER(1+'DCF - FCFF'!$D$26,{1,2,3,4,5})/POWER(1+$A72,{1,2,3,4,5}))+'DCF - FCFF'!$B$26*POWER(1+'DCF - FCFF'!$D$26,5)*(1+C$65)/($A72-C$65)/POWER(1+$A72,5)-'DCF - FCFF'!$O$26)/'DCF - FCFF'!$Q$26) | D72: =IF($A72-D$65<0.01,NA(),('DCF - FCFF'!$B$26*SUMPRODUCT(POWER(1+'DCF - FCFF'!$D$26,{1,2,3,4,5})/POWER(1+$A72,{1,2,3,4,5}))+'DCF - FCFF'!$B$26*POWER(1+'DCF - FCFF'!$D$26,5)*(1+D$65)/($A72-D$65)/POWER(1+$A72,5)-'DCF - FCFF'!$O$26)/'DCF - FCFF'!$Q$26) | E72: =IF($A72-E$65<0.01,NA(),('DCF - FCFF'!$B$26*SUMPRODUCT(POWER(1+'DCF - FCFF'!$D$26,{1,2,3,4,5})/POWER(1+$A72,{1,2,3,4,5}))+'DCF - FCFF'!$B$26*POWER(1+'DCF - FCFF'!$D$26,5)*(1+E$65)/($A72-E$65)/POWER(1+$A72,5)-'DCF - FCFF'!$O$26)/'DCF - FCFF'!$Q$26) | F72: =IF($A72-F$65<0.01,NA(),('DCF - FCFF'!$B$26*SUMPRODUCT(POWER(1+'DCF - FCFF'!$D$26,{1,2,3,4,5})/POWER(1+$A72,{1,2,3,4,5}))+'DCF - FCFF'!$B$26*POWER(1+'DCF - FCFF'!$D$26,5)*(1+F$65)/($A72-F$65)/POWER(1+$A72,5)-'DCF - FCFF'!$O$26)/'DCF - FCFF'!$Q$26) | G72: =IF($A72-G$65<0.01,NA(),('DCF - FCFF'!$B$26*SUMPRODUCT(POWER(1+'DCF - FCFF'!$D$26,{1,2,3,4,5})/POWER(1+$A72,{1,2,3,4,5}))+'DCF - FCFF'!$B$26*POWER(1+'DCF - FCFF'!$D$26,5)*(1+G$65)/($A72-G$65)/POWER(1+$A72,5)-'DCF - FCFF'!$O$26)/'DCF - FCFF'!$Q$26) | H72: =IF($A72-H$65<0.01,NA(),('DCF - FCFF'!$B$26*SUMPRODUCT(POWER(1+'DCF - FCFF'!$D$26,{1,2,3,4,5})/POWER(1+$A72,{1,2,3,4,5}))+'DCF - FCFF'!$B$26*POWER(1+'DCF - FCFF'!$D$26,5)*(1+H$65)/($A72-H$65)/POWER(1+$A72,5)-'DCF - FCFF'!$O$26)/'DCF - FCFF'!$Q$26) | I72: =IF($A72-I$65<0.01,NA(),('DCF - FCFF'!$B$26*SUMPRODUCT(POWER(1+'DCF - FCFF'!$D$26,{1,2,3,4,5})/POWER(1+$A72,{1,2,3,4,5}))+'DCF - FCFF'!$B$26*POWER(1+'DCF - FCFF'!$D$26,5)*(1+I$65)/($A72-I$65)/POWER(1+$A72,5)-'DCF - FCFF'!$O$26)/'DCF - FCFF'!$Q$26) | J72: =IF($A72-J$65<0.01,NA(),('DCF - FCFF'!$B$26*SUMPRODUCT(POWER(1+'DCF - FCFF'!$D$26,{1,2,3,4,5})/POWER(1+$A72,{1,2,3,4,5}))+'DCF - FCFF'!$B$26*POWER(1+'DCF - FCFF'!$D$26,5)*(1+J$65)/($A72-J$65)/POWER(1+$A72,5)-'DCF - FCFF'!$O$26)/'DCF - FCFF'!$Q$26)
A73: ='DCF - FCFF'!$E$26+0.015 | B73: =IF($A73-B$65<0.01,NA(),('DCF - FCFF'!$B$26*SUMPRODUCT(POWER(1+'DCF - FCFF'!$D$26,{1,2,3,4,5})/POWER(1+$A73,{1,2,3,4,5}))+'DCF - FCFF'!$B$26*POWER(1+'DCF - FCFF'!$D$26,5)*(1+B$65)/($A73-B$65)/POWER(1+$A73,5)-'DCF - FCFF'!$O$26)/'DCF - FCFF'!$Q$26) | C73: =IF($A73-C$65<0.01,NA(),('DCF - FCFF'!$B$26*SUMPRODUCT(POWER(1+'DCF - FCFF'!$D$26,{1,2,3,4,5})/POWER(1+$A73,{1,2,3,4,5}))+'DCF - FCFF'!$B$26*POWER(1+'DCF - FCFF'!$D$26,5)*(1+C$65)/($A73-C$65)/POWER(1+$A73,5)-'DCF - FCFF'!$O$26)/'DCF - FCFF'!$Q$26) | D73: =IF($A73-D$65<0.01,NA(),('DCF - FCFF'!$B$26*SUMPRODUCT(POWER(1+'DCF - FCFF'!$D$26,{1,2,3,4,5})/POWER(1+$A73,{1,2,3,4,5}))+'DCF - FCFF'!$B$26*POWER(1+'DCF - FCFF'!$D$26,5)*(1+D$65)/($A73-D$65)/POWER(1+$A73,5)-'DCF - FCFF'!$O$26)/'DCF - FCFF'!$Q$26) | E73: =IF($A73-E$65<0.01,NA(),('DCF - FCFF'!$B$26*SUMPRODUCT(POWER(1+'DCF - FCFF'!$D$26,{1,2,3,4,5})/POWER(1+$A73,{1,2,3,4,5}))+'DCF - FCFF'!$B$26*POWER(1+'DCF - FCFF'!$D$26,5)*(1+E$65)/($A73-E$65)/POWER(1+$A73,5)-'DCF - FCFF'!$O$26)/'DCF - FCFF'!$Q$26) | F73: =IF($A73-F$65<0.01,NA(),('DCF - FCFF'!$B$26*SUMPRODUCT(POWER(1+'DCF - FCFF'!$D$26,{1,2,3,4,5})/POWER(1+$A73,{1,2,3,4,5}))+'DCF - FCFF'!$B$26*POWER(1+'DCF - FCFF'!$D$26,5)*(1+F$65)/($A73-F$65)/POWER(1+$A73,5)-'DCF - FCFF'!$O$26)/'DCF - FCFF'!$Q$26) | G73: =IF($A73-G$65<0.01,NA(),('DCF - FCFF'!$B$26*SUMPRODUCT(POWER(1+'DCF - FCFF'!$D$26,{1,2,3,4,5})/POWER(1+$A73,{1,2,3,4,5}))+'DCF - FCFF'!$B$26*POWER(1+'DCF - FCFF'!$D$26,5)*(1+G$65)/($A73-G$65)/POWER(1+$A73,5)-'DCF - FCFF'!$O$26)/'DCF - FCFF'!$Q$26) | H73: =IF($A73-H$65<0.01,NA(),('DCF - FCFF'!$B$26*SUMPRODUCT(POWER(1+'DCF - FCFF'!$D$26,{1,2,3,4,5})/POWER(1+$A73,{1,2,3,4,5}))+'DCF - FCFF'!$B$26*POWER(1+'DCF - FCFF'!$D$26,5)*(1+H$65)/($A73-H$65)/POWER(1+$A73,5)-'DCF - FCFF'!$O$26)/'DCF - FCFF'!$Q$26) | I73: =IF($A73-I$65<0.01,NA(),('DCF - FCFF'!$B$26*SUMPRODUCT(POWER(1+'DCF - FCFF'!$D$26,{1,2,3,4,5})/POWER(1+$A73,{1,2,3,4,5}))+'DCF - FCFF'!$B$26*POWER(1+'DCF - FCFF'!$D$26,5)*(1+I$65)/($A73-I$65)/POWER(1+$A73,5)-'DCF - FCFF'!$O$26)/'DCF - FCFF'!$Q$26) | J73: =IF($A73-J$65<0.01,NA(),('DCF - FCFF'!$B$26*SUMPRODUCT(POWER(1+'DCF - FCFF'!$D$26,{1,2,3,4,5})/POWER(1+$A73,{1,2,3,4,5}))+'DCF - FCFF'!$B$26*POWER(1+'DCF - FCFF'!$D$26,5)*(1+J$65)/($A73-J$65)/POWER(1+$A73,5)-'DCF - FCFF'!$O$26)/'DCF - FCFF'!$Q$26)
A74: ='DCF - FCFF'!$E$26+0.02 | B74: =IF($A74-B$65<0.01,NA(),('DCF - FCFF'!$B$26*SUMPRODUCT(POWER(1+'DCF - FCFF'!$D$26,{1,2,3,4,5})/POWER(1+$A74,{1,2,3,4,5}))+'DCF - FCFF'!$B$26*POWER(1+'DCF - FCFF'!$D$26,5)*(1+B$65)/($A74-B$65)/POWER(1+$A74,5)-'DCF - FCFF'!$O$26)/'DCF - FCFF'!$Q$26) | C74: =IF($A74-C$65<0.01,NA(),('DCF - FCFF'!$B$26*SUMPRODUCT(POWER(1+'DCF - FCFF'!$D$26,{1,2,3,4,5})/POWER(1+$A74,{1,2,3,4,5}))+'DCF - FCFF'!$B$26*POWER(1+'DCF - FCFF'!$D$26,5)*(1+C$65)/($A74-C$65)/POWER(1+$A74,5)-'DCF - FCFF'!$O$26)/'DCF - FCFF'!$Q$26) | D74: =IF($A74-D$65<0.01,NA(),('DCF - FCFF'!$B$26*SUMPRODUCT(POWER(1+'DCF - FCFF'!$D$26,{1,2,3,4,5})/POWER(1+$A74,{1,2,3,4,5}))+'DCF - FCFF'!$B$26*POWER(1+'DCF - FCFF'!$D$26,5)*(1+D$65)/($A74-D$65)/POWER(1+$A74,5)-'DCF - FCFF'!$O$26)/'DCF - FCFF'!$Q$26) | E74: =IF($A74-E$65<0.01,NA(),('DCF - FCFF'!$B$26*SUMPRODUCT(POWER(1+'DCF - FCFF'!$D$26,{1,2,3,4,5})/POWER(1+$A74,{1,2,3,4,5}))+'DCF - FCFF'!$B$26*POWER(1+'DCF - FCFF'!$D$26,5)*(1+E$65)/($A74-E$65)/POWER(1+$A74,5)-'DCF - FCFF'!$O$26)/'DCF - FCFF'!$Q$26) | F74: =IF($A74-F$65<0.01,NA(),('DCF - FCFF'!$B$26*SUMPRODUCT(POWER(1+'DCF - FCFF'!$D$26,{1,2,3,4,5})/POWER(1+$A74,{1,2,3,4,5}))+'DCF - FCFF'!$B$26*POWER(1+'DCF - FCFF'!$D$26,5)*(1+F$65)/($A74-F$65)/POWER(1+$A74,5)-'DCF - FCFF'!$O$26)/'DCF - FCFF'!$Q$26) | G74: =IF($A74-G$65<0.01,NA(),('DCF - FCFF'!$B$26*SUMPRODUCT(POWER(1+'DCF - FCFF'!$D$26,{1,2,3,4,5})/POWER(1+$A74,{1,2,3,4,5}))+'DCF - FCFF'!$B$26*POWER(1+'DCF - FCFF'!$D$26,5)*(1+G$65)/($A74-G$65)/POWER(1+$A74,5)-'DCF - FCFF'!$O$26)/'DCF - FCFF'!$Q$26) | H74: =IF($A74-H$65<0.01,NA(),('DCF - FCFF'!$B$26*SUMPRODUCT(POWER(1+'DCF - FCFF'!$D$26,{1,2,3,4,5})/POWER(1+$A74,{1,2,3,4,5}))+'DCF - FCFF'!$B$26*POWER(1+'DCF - FCFF'!$D$26,5)*(1+H$65)/($A74-H$65)/POWER(1+$A74,5)-'DCF - FCFF'!$O$26)/'DCF - FCFF'!$Q$26) | I74: =IF($A74-I$65<0.01,NA(),('DCF - FCFF'!$B$26*SUMPRODUCT(POWER(1+'DCF - FCFF'!$D$26,{1,2,3,4,5})/POWER(1+$A74,{1,2,3,4,5}))+'DCF - FCFF'!$B$26*POWER(1+'DCF - FCFF'!$D$26,5)*(1+I$65)/($A74-I$65)/POWER(1+$A74,5)-'DCF - FCFF'!$O$26)/'DCF - FCFF'!$Q$26) | J74: =IF($A74-J$65<0.01,NA(),('DCF - FCFF'!$B$26*SUMPRODUCT(POWER(1+'DCF - FCFF'!$D$26,{1,2,3,4,5})/POWER(1+$A74,{1,2,3,4,5}))+'DCF - FCFF'!$B$26*POWER(1+'DCF - FCFF'!$D$26,5)*(1+J$65)/($A74-J$65)/POWER(1+$A74,5)-'DCF - FCFF'!$O$26)/'DCF - FCFF'!$Q$26)
A76: Godrej | B76: ='Market Data'!$C$8 | C76: ← market price · rows: WACC · cols: terminal g
B77: 0.01 | C77: 0.015 | D77: 0.02 | E77: 0.025 | F77: 0.03 | G77: 0.035 | H77: 0.04 | I77: 0.045 | J77: 0.05
